Workbook

Sheet Scenarios
B2: Scenario | C2: 2 | E2: Pelo Baixo impacto geral "Other Bets" e "Hedging" foram deixados para serem alterados no caso especificos, deixando valores justos baseados no passado nos calculos
B3: =IF(C2=2,"Base Case",IF(C2=1,"Bear Case","Bull Case")) -> Base Case
D5: Search Growth (%) | M5: g | O5: fonte | P5: k/pp | R5: λ(alavancagem
D6: 2Q26e | E6: 3Q26e | F6: 4Q26e | G6: =2027 -> 2027 | H6: =G6+1 -> 2028 | I6: =H6+1 -> 2029 | J6: 2030 | K6: 2031 | M6: =M7-1% -> 0.035 | O6: Search | P6: =AN22 -> 0.23222731 | R6: 0.4 | S6: Bull
B7: Scenario | C7: =C2 -> 2 | M7: 0.045 | O7: YouTube | P7: =AN23 -> 0.17054934 | R7: 0.25 | S7: Bear
B8: Bear | D8: =D9*(1-$P$6*$R$6) -> 0.13606636 | E8: =E9*(1-$P$6*$R$6) -> 0.13606636 | F8: =F9*(1-$P$6*$R$6) -> 0.13606636 | G8: =G9*(1-$P$6*$R$6) -> 0.18142182 | H8: =H9*(1-$P$6*$R$6) -> 0.15420854 | I8: =I9*(1-$P$6*$R$6) -> 0.12699527 | J8: =J9*(1-$P$6*$R$6) -> 0.10885309 | K8: =K9*(1-$P$6*$R$6) -> 0.090710908 | M8: =M7+0.5% -> 0.05 | O8: Subs | P8: =AN24 -> 0.28996213
B9: Base | D9: 0.15 | E9: 0.15 | F9: 0.15 | G9: 0.2 | H9: 0.17 | I9: 0.14 | J9: 0.12 | K9: 0.1 | M9: =CHOOSE($C$2,M6,M7,M8) -> 0.045 | O9: Cloud | P9: =AN25 -> 0.34561102 | R9: instensidade
B10: Bull | D10: =D9*(1+$P$6*$R$10) -> 0.16741705 | E10: =E9*(1+$P$6*$R$10) -> 0.16741705 | F10: =F9*(1+$P$6*$R$10) -> 0.16741705 | G10: =G9*(1+$P$6*$R$10) -> 0.22322273 | H10: =H9*(1+$P$6*$R$10) -> 0.18973932 | I10: =I9*(1+$P$6*$R$10) -> 0.15625591 | J10: =J9*(1+$P$6*$R$10) -> 0.13393364 | K10: =K9*(1+$P$6*$R$10) -> 0.11161137 | O10: Network | P10: =AM26 -> 0.013554432 | R10: 0.5
B11: Running | D11: =CHOOSE($C$2,D8,D9,D10) -> 0.15 | E11: =CHOOSE($C$2,E8,E9,E10) -> 0.15 | F11: =CHOOSE($C$2,F8,F9,F10) -> 0.15 | G11: =CHOOSE($C$2,G8,G9,G10) -> 0.2 | H11: =CHOOSE($C$2,H8,H9,H10) -> 0.17 | I11: =CHOOSE($C$2,I8,I9,I10) -> 0.14 | J11: =CHOOSE($C$2,J8,J9,J10) -> 0.12 | K11: =CHOOSE($C$2,K8,K9,K10) -> 0.1 | O11: ServMg | P11: =AM27 -> 0.020254053
O12: CloudMg | P12: =AM28 -> 0.067296354
D13: Youtube Ads Growth (%)
D14: 2Q26e | E14: 3Q26e | F14: 4Q26e | G14: =2027 -> 2027 | H14: =G14+1 -> 2028 | I14: =H14+1 -> 2029 | J14: 2030 | K14: 2031
B15: Scenario | C15: =C2 -> 2
B16: Bear | D16: =D17*(1-$P$7*$R$10) -> 0.08232528 | E16: =E17*(1-$P$7*$R$10) -> 0.08232528 | F16: =F17*(1-$P$7*$R$10) -> 0.08232528 | G16: =G17*(1-$P$7*$R$10) -> 0.10976704 | H16: =H17*(1-$P$7*$R$10) -> 0.10061979 | I16: =I17*(1-$P$7*$R$10) -> 0.10061979 | J16: =J17*(1-$P$7*$R$10) -> 0.091472533 | K16: =K17*(1-$P$7*$R$10) -> 0.08232528
B17: Base | D17: 0.09 | E17: 0.09 | F17: 0.09 | G17: 0.12 | H17: 0.11 | I17: 0.11 | J17: 0.1 | K17: 0.09
B18: Bull | D18: =D17*(1+$P$7*$R$10) -> 0.09767472 | E18: =E17*(1+$P$7*$R$10) -> 0.09767472 | F18: =F17*(1+$P$7*$R$10) -> 0.09767472 | G18: =G17*(1+$P$7*$R$10) -> 0.13023296 | H18: =H17*(1+$P$7*$R$10) -> 0.11938021 | I18: =I17*(1+$P$7*$R$10) -> 0.11938021 | J18: =J17*(1+$P$7*$R$10) -> 0.10852747 | K18: =K17*(1+$P$7*$R$10) -> 0.09767472
B19: Running | D19: =CHOOSE($C2,D16,D17,D18) -> 0.09 | E19: =CHOOSE($C2,E16,E17,E18) -> 0.09 | F19: =CHOOSE($C2,F16,F17,F18) -> 0.09 | G19: =CHOOSE($C2,G16,G17,G18) -> 0.12 | H19: =CHOOSE($C2,H16,H17,H18) -> 0.11 | I19: =CHOOSE($C2,I16,I17,I18) -> 0.11 | J19: =CHOOSE($C2,J16,J17,J18) -> 0.1 | K19: =CHOOSE($C2,K16,K17,K18) -> 0.09
X20: Cálculo do k (base histórica)
D21: Google Subscription Growth (%) | X21: Driver | Y21: 1Q23 | Z21: 2Q23 | AA21: 3Q23 | AB21: 4Q23 | AC21: 1Q24 | AD21: 2Q24 | AE21: 3Q24 | AF21: 4Q24 | AG21: 1Q25 | AH21: 2Q25 | AI21: 3Q25 | AJ21: 4Q25 | AK21: 1Q26 | AL21: μ (13t) | AM21: σ (8t) | AN21: k = σ/μ
D22: 2Q26e | E22: 3Q26e | F22: 4Q26e | G22: =2027 -> 2027 | H22: =G22+1 -> 2028 | I22: =H22+1 -> 2029 | J22: 2030 | K22: 2031 | X22: Search | Y22: ='Build Up'!K8/'Build Up'!F8-1 -> 0.01870362 | Z22: ='Build Up'!L8/'Build Up'!G8-1 -> 0.047654157 | AA22: ='Build Up'!M8/'Build Up'!H8-1 -> 0.11348289 | AB22: ='Build Up'!N8/'Build Up'!I8-1 -> 0.12712421 | AC22: ='Build Up'!P8/'Build Up'!K8-1 -> 0.14363587 | AD22: ='Build Up'!Q8/'Build Up'!L8-1 -> 0.13796096 | AE22: ='Build Up'!R8/'Build Up'!M8-1 -> 0.12172353 | AF22: ='Build Up'!S8/'Build Up'!N8-1 -> 0.12523948 | AG22: ='Build Up'!U8/'Build Up'!P8-1 -> 0.09849207 | AH22: ='Build Up'!V8/'Build Up'!Q8-1 -> 0.11711229 | AI22: ='Build Up'!W8/'Build Up'!R8-1 -> 0.14542877 | AJ22: ='Build Up'!X8/'Build Up'!S8-1 -> 0.16728356 | AK22: ='Build Up'!Z8/'Build Up'!U8-1 -> 0.19125478 | AL22: =AVERAGE(Y22:AK22) -> 0.11962278 | AM22: =STDEVP(AD22:AK22) -> 0.027779677 | AN22: =AM22/AL22 -> 0.23222731
B23: Scenario | C23: =C2 -> 2 | X23: YouTube | Y23: ='Build Up'!K11/'Build Up'!F11-1 -> -0.025622361 | Z23: ='Build Up'!L11/'Build Up'!G11-1 -> 0.044277929 | AA23: ='Build Up'!M11/'Build Up'!H11-1 -> 0.12459341 | AB23: ='Build Up'!N11/'Build Up'!I11-1 -> 0.15534346 | AC23: ='Build Up'!P11/'Build Up'!K11-1 -> 0.20872553 | AD23: ='Build Up'!Q11/'Build Up'!L11-1 -> 0.13020222 | AE23: ='Build Up'!R11/'Build Up'!M11-1 -> 0.12185614 | AF23: ='Build Up'!S11/'Build Up'!N11-1 -> 0.13836957 | AG23: ='Build Up'!U11/'Build Up'!P11-1 -> 0.10346106 | AH23: ='Build Up'!V11/'Build Up'!Q11-1 -> 0.1307861 | AI23: ='Build Up'!W11/'Build Up'!R11-1 -> 0.15020738 | AJ23: ='Build Up'!X11/'Build Up'!S11-1 -> 0.086890098 | AK23: ='Build Up'!Z11/'Build Up'!U11-1 -> 0.10709085 | AL23: =AVERAGE(Y23:AK23) -> 0.11355241 | AM23: =STDEVP(AD23:AK23) -> 0.019366289 | AN23: =AM23/AL23 -> 0.17054934
B24: Bear | D24: =D25*(1-$P$8*$R$10) -> 0.11970265 | E24: =E25*(1-$P$8*$R$10) -> 0.11970265 | F24: =F25*(1-$P$8*$R$10) -> 0.11970265 | G24: =G25*(1-$P$8*$R$10) -> 0.12825284 | H24: =H25*(1-$P$8*$R$10) -> 0.13680303 | I24: =I25*(1-$P$8*$R$10) -> 0.14535322 | J24: =J25*(1-$P$8*$R$10) -> 0.13680303 | K24: =K25*(1-$P$8*$R$10) -> 0.12825284 | X24: Subscriptions | Y24: ='Build Up'!K17/'Build Up'!F17-1 -> 0.088386434 | Z24: ='Build Up'!L17/'Build Up'!G17-1 -> 0.24248436 | AA24: ='Build Up'!M17/'Build Up'!H17-1 -> 0.20942712 | AB24: ='Build Up'!N17/'Build Up'!I17-1 -> 0.2271487 | AC24: ='Build Up'!P17/'Build Up'!K17-1 -> 0.17887495 | AD24: ='Build Up'!Q17/'Build Up'!L17-1 -> 0.14369934 | AE24: ='Build Up'!R17/'Build Up'!M17-1 -> 0.27785106 | AF24: ='Build Up'!S17/'Build Up'!N17-1 -> 0.077728368 | AG24: ='Build Up'!U17/'Build Up'!P17-1 -> 0.18766449 | AH24: ='Build Up'!V17/'Build Up'!Q17-1 -> 0.20307131 | AI24: ='Build Up'!W17/'Build Up'!R17-1 -> 0.20777027 | AJ24: ='Build Up'!X17/'Build Up'!S17-1 -> 0.16719677 | AK24: ='Build Up'!Z17/'Build Up'!U17-1 -> 0.19317853 | AL24: =AVERAGE(Y24:AK24) -> 0.18496013 | AM24: =STDEVP(AD24:AK24) -> 0.053631434 | AN24: =AM24/AL24 -> 0.28996213
B25: Base | D25: 0.14 | E25: 0.14 | F25: 0.14 | G25: 0.15 | H25: 0.16 | I25: 0.17 | J25: 0.16 | K25: 0.15 | X25: Cloud | Y25: ='Build Up'!K22/'Build Up'!F22-1 -> 0.28053599 | Z25: ='Build Up'!L22/'Build Up'!G22-1 -> 0.27963671 | AA25: ='Build Up'!M22/'Build Up'!H22-1 -> 0.22466511 | AB25: ='Build Up'!N22/'Build Up'!I22-1 -> 0.25659604 | AC25: ='Build Up'!P22/'Build Up'!K22-1 -> 0.28441105 | AD25: ='Build Up'!Q22/'Build Up'!L22-1 -> 0.28838252 | AE25: ='Build Up'!R22/'Build Up'!M22-1 -> 0.34978005 | AF25: ='Build Up'!S22/'Build Up'!N22-1 -> 0.30058747 | AG25: ='Build Up'!U22/'Build Up'!P22-1 -> 0.28055149 | AH25: ='Build Up'!V22/'Build Up'!Q22-1 -> 0.31671016 | AI25: ='Build Up'!W22/'Build Up'!R22-1 -> 0.33506562 | AJ25: ='Build Up'!X22/'Build Up'!S22-1 -> 0.47754078 | AK25: ='Build Up'!Z22/'Build Up'!U22-1 -> 0.63360522 | AL25: =AVERAGE(Y25:AK25) -> 0.33138986 | AM25: =STDEVP(AD25:AK25) -> 0.11453199 | AN25: =AM25/AL25 -> 0.34561102
B26: Bull | D26: =D25*(1+$P$8*$R$10) -> 0.16029735 | E26: =E25*(1+$P$8*$R$10) -> 0.16029735 | F26: =F25*(1+$P$8*$R$10) -> 0.16029735 | G26: =G25*(1+$P$8*$R$10) -> 0.17174716 | H26: =H25*(1+$P$8*$R$10) -> 0.18319697 | I26: =I25*(1+$P$8*$R$10) -> 0.19464678 | J26: =J25*(1+$P$8*$R$10) -> 0.18319697 | K26: =K25*(1+$P$8*$R$10) -> 0.17174716 | X26: Network | Y26: ='Build Up'!K14/'Build Up'!F14-1 -> -0.082945926 | Z26: ='Build Up'!L14/'Build Up'!G14-1 -> -0.049521734 | AA26: ='Build Up'!M14/'Build Up'!H14-1 -> -0.025787602 | AB26: ='Build Up'!N14/'Build Up'!I14-1 -> -0.02100295 | AC26: ='Build Up'!P14/'Build Up'!K14-1 -> -0.011072572 | AD26: ='Build Up'!Q14/'Build Up'!L14-1 -> -0.051719745 | AE26: ='Build Up'!R14/'Build Up'!M14-1 -> -0.015777807 | AF26: ='Build Up'!S14/'Build Up'!N14-1 -> -0.041340243 | AG26: ='Build Up'!U14/'Build Up'!P14-1 -> -0.02117901 | AH26: ='Build Up'!V14/'Build Up'!Q14-1 -> -0.012090274 | AI26: ='Build Up'!W14/'Build Up'!R14-1 -> -0.025702173 | AJ26: ='Build Up'!X14/'Build Up'!S14-1 -> -0.015841086 | AK26: ='Build Up'!Z14/'Build Up'!U14-1 -> -0.039277839 | AL26: =AVERAGE(Y26:AK26) -> -0.031789151 | AM26: =STDEVP(AD26:AK26) -> 0.013554432
B27: Running | D27: =CHOOSE($C2,D24,D25,D26) -> 0.14 | E27: =CHOOSE($C2,E24,E25,E26) -> 0.14 | F27: =CHOOSE($C2,F24,F25,F26) -> 0.14 | G27: =CHOOSE($C2,G24,G25,G26) -> 0.15 | H27: =CHOOSE($C2,H24,H25,H26) -> 0.16 | I27: =CHOOSE($C2,I24,I25,I26) -> 0.17 | J27: =CHOOSE($C2,J24,J25,J26) -> 0.16 | K27: =CHOOSE($C2,K24,K25,K26) -> 0.15 | X27: Margem Services | Y27: ='Build Up'!K36 -> 0.35081745 | Z27: ='Build Up'!L36 -> 0.35383571 | AA27: ='Build Up'!M36 -> 0.35208719 | AB27: ='Build Up'!N36 -> 0.35027716 | AC27: ='Build Up'!P36 -> 0.39627546 | AD27: ='Build Up'!Q36 -> 0.40139054 | AE27: ='Build Up'!R36 -> 0.40329369 | AF27: ='Build Up'!S36 -> 0.39046781 | AG27: ='Build Up'!U36 -> 0.4229913 | AH27: ='Build Up'!V36 -> 0.40055486 | AI27: ='Build Up'!W36 -> 0.38513762 | AJ27: ='Build Up'!X36 -> 0.41864347 | AK27: ='Build Up'!Z36 -> 0.45281524 | AL27: =AVERAGE(Y27:AK27) -> 0.39066058 | AM27: =STDEVP(AD27:AK27) -> 0.020254053
X28: Margem Cloud | Y28: ='Build Up'!K39 -> 0.025623826 | Z28: ='Build Up'!L39 -> 0.04918441 | AA28: ='Build Up'!M39 -> 0.031625253 | AB28: ='Build Up'!N39 -> 0.093994778 | AC28: ='Build Up'!P39 -> 0.094004596 | AD28: ='Build Up'!Q39 -> 0.11326955 | AE28: ='Build Up'!R39 -> 0.17149652 | AF28: ='Build Up'!S39 -> 0.17507319 | AG28: ='Build Up'!U39 -> 0.17756933 | AH28: ='Build Up'!V39 -> 0.20742807 | AI28: ='Build Up'!W39 -> 0.23711816 | AJ28: ='Build Up'!X39 -> 0.30078125 | AK28: ='Build Up'!Z39 -> 0.32943879 | AL28: =AVERAGE(Y28:AK28) -> 0.15435444 | AM28: =STDEVP(AD28:AK28) -> 0.067296354
D29: Google Cloud Growth (%)
D30: 2Q26e | E30: 3Q26e | F30: 4Q26e | G30: =2027 -> 2027 | H30: =G30+1 -> 2028 | I30: =H30+1 -> 2029 | J30: 2030 | K30: 2031
B31: Scenario | C31: =C2 -> 2
B32: Bear | D32: =D33*(1-$P$9*$R$10) -> 0.24815835 | E32: =E33*(1-$P$9*$R$10) -> 0.24815835 | F32: =F33*(1-$P$9*$R$10) -> 0.24815835 | G32: =G33*(1-$P$9*$R$10) -> 0.41359725 | H32: =H33*(1-$P$9*$R$10) -> 0.26470224 | I32: =I33*(1-$P$9*$R$10) -> 0.1654389 | J32: =J33*(1-$P$9*$R$10) -> 0.12407917 | K32: =K33*(1-$P$9*$R$10) -> 0.082719449
B33: Base | D33: 0.3 | E33: 0.3 | F33: 0.3 | G33: 0.5 | H33: 0.32 | I33: 0.2 | J33: 0.15 | K33: 0.1
B34: Bull | D34: =D33*(1+$P$9*$R$10) -> 0.35184165 | E34: =E33*(1+$P$9*$R$10) -> 0.35184165 | F34: =F33*(1+$P$9*$R$10) -> 0.35184165 | G34: =G33*(1+$P$9*$R$10) -> 0.58640275 | H34: =H33*(1+$P$9*$R$10) -> 0.37529776 | I34: =I33*(1+$P$9*$R$10) -> 0.2345611 | J34: =J33*(1+$P$9*$R$10) -> 0.17592083 | K34: =K33*(1+$P$9*$R$10) -> 0.11728055
B35: Running | D35: =CHOOSE($C2,D32,D33,D34) -> 0.3 | E35: =CHOOSE($C2,E32,E33,E34) -> 0.3 | F35: =CHOOSE($C2,F32,F33,F34) -> 0.3 | G35: =CHOOSE($C2,G32,G33,G34) -> 0.5 | H35: =CHOOSE($C2,H32,H33,H34) -> 0.32 | I35: =CHOOSE($C2,I32,I33,I34) -> 0.2 | J35: =CHOOSE($C2,J32,J33,J34) -> 0.15 | K35: =CHOOSE($C2,K32,K33,K34) -> 0.1
D37: Google Cloud Margin (%)
D38: 2Q26e | E38: 3Q26e | F38: 4Q26e | G38: =2027 -> 2027 | H38: =G38+1 -> 2028 | I38: =H38+1 -> 2029 | J38: 2030 | K38: 2031
B39: Scenario | C39: =C2 -> 2
B40: Bear | D40: =D41-$P$12*$R$10-(D33*$P$9*$R$10*$R$7) -> 0.30339141 | E40: =E41-$P$12*$R$10-(E33*$P$9*$R$10*$R$7) -> 0.29339141 | F40: =F41-$P$12*$R$10-(F33*$P$9*$R$10*$R$7) -> 0.29339141 | G40: =G41-$P$12*$R$10-(G33*$P$9*$R$10*$R$7) -> 0.28475113 | H40: =H41-$P$12*$R$10-(H33*$P$9*$R$10*$R$7) -> 0.30252738 | I40: =I41-$P$12*$R$10-(I33*$P$9*$R$10*$R$7) -> 0.31771155 | J40: =J41-$P$12*$R$10-(J33*$P$9*$R$10*$R$7) -> 0.32987162 | K40: =K41-$P$12*$R$10-(K33*$P$9*$R$10*$R$7) -> 0.34203169
B41: Base | D41: 0.35 | E41: 0.34 | F41: 0.34 | G41: 0.34 | H41: 0.35 | I41: 0.36 | J41: 0.37 | K41: 0.38
B42: Bull | D42: =D41+$P$12*$R$10+(D33*$P$9*$R$10*$R$6) -> 0.40438484 | E42: =E41+$P$12*$R$10+(E33*$P$9*$R$10*$R$6) -> 0.39438484 | F42: =F41+$P$12*$R$10+(F33*$P$9*$R$10*$R$6) -> 0.39438484 | G42: =G41+$P$12*$R$10+(G33*$P$9*$R$10*$R$6) -> 0.40820928 | H42: =H41+$P$12*$R$10+(H33*$P$9*$R$10*$R$6) -> 0.40576728 | I42: =I41+$P$12*$R$10+(I33*$P$9*$R$10*$R$6) -> 0.40747262 | J42: =J41+$P$12*$R$10+(J33*$P$9*$R$10*$R$6) -> 0.41401651 | K42: =K41+$P$12*$R$10+(K33*$P$9*$R$10*$R$6) -> 0.4205604
B43: Running | D43: =CHOOSE($C7,D40,D41,D42) -> 0.35 | E43: =CHOOSE($C7,E40,E41,E42) -> 0.34 | F43: =CHOOSE($C7,F40,F41,F42) -> 0.34 | G43: =CHOOSE($C7,G40,G41,G42) -> 0.34 | H43: =CHOOSE($C7,H40,H41,H42) -> 0.35 | I43: =CHOOSE($C7,I40,I41,I42) -> 0.36 | J43: =CHOOSE($C7,J40,J41,J42) -> 0.37 | K43: =CHOOSE($C7,K40,K41,K42) -> 0.38
D45: Google Services Margin (%)
D46: 2Q26e | E46: 3Q26e | F46: 4Q26e | G46: =2027 -> 2027 | H46: =G46+1 -> 2028 | I46: =H46+1 -> 2029 | J46: 2030 | K46: 2031
B47: Scenario | C47: =C2 -> 2
B48: Bear | D48: =D49-$P$11*$R$10-(D9*$P$6*$R$10*$R$7) -> 0.43551871 | E48: =E49-$P$11*$R$10-(E9*$P$6*$R$10*$R$7) -> 0.43551871 | F48: =F49-$P$11*$R$10-(F9*$P$6*$R$10*$R$7) -> 0.43551871 | G48: =G49-$P$11*$R$10-(G9*$P$6*$R$10*$R$7) -> 0.43406729 | H48: =H49-$P$11*$R$10-(H9*$P$6*$R$10*$R$7) -> 0.44493814 | I48: =I49-$P$11*$R$10-(I9*$P$6*$R$10*$R$7) -> 0.455809 | J48: =J49-$P$11*$R$10-(J9*$P$6*$R$10*$R$7) -> 0.45638956 | K48: =K49-$P$11*$R$10-(K9*$P$6*$R$10*$R$7) -> 0.45697013
B49: Base | D49: 0.45 | E49: 0.45 | F49: 0.45 | G49: 0.45 | H49: 0.46 | I49: 0.47 | J49: 0.47 | K49: 0.47
B50: Bull | D50: =D49+$P$11*$R$10+(D9*$P$6*$R$10*$R$6) -> 0.46709385 | E50: =E49+$P$11*$R$10+(E9*$P$6*$R$10*$R$6) -> 0.46709385 | F50: =F49+$P$11*$R$10+(F9*$P$6*$R$10*$R$6) -> 0.46709385 | G50: =G49+$P$11*$R$10+(G9*$P$6*$R$10*$R$6) -> 0.46941612 | H50: =H49+$P$11*$R$10+(H9*$P$6*$R$10*$R$6) -> 0.47802276 | I50: =I49+$P$11*$R$10+(I9*$P$6*$R$10*$R$6) -> 0.48662939 | J50: =J49+$P$11*$R$10+(J9*$P$6*$R$10*$R$6) -> 0.48570048 | K50: =K49+$P$11*$R$10+(K9*$P$6*$R$10*$R$6) -> 0.48477157
B51: Running | D51: =CHOOSE($C$2,D48,D49,D50) -> 0.45 | E51: =CHOOSE($C$2,E48,E49,E50) -> 0.45 | F51: =CHOOSE($C$2,F48,F49,F50) -> 0.45 | G51: =CHOOSE($C$2,G48,G49,G50) -> 0.45 | H51: =CHOOSE($C$2,H48,H49,H50) -> 0.46 | I51: =CHOOSE($C$2,I48,I49,I50) -> 0.47 | J51: =CHOOSE($C$2,J48,J49,J50) -> 0.47 | K51: =CHOOSE($C$2,K48,K49,K50) -> 0.47
D53: CapEx Revenue (%)
D54: 2Q26e | E54: 3Q26e | F54: 4Q26e | G54: =2027 -> 2027 | H54: =G54+1 -> 2028 | I54: =H54+1 -> 2029 | J54: 2030 | K54: 2031
B55: Scenario | C55: =C2 -> 2
B56: Bear | D56: =D57-1% -> 0.36 | E56: =E57-1% -> 0.39 | F56: =F57-1% -> 0.47 | G56: =G57-1% -> 0.39 | H56: =H57-1% -> 0.34 | I56: =I57-1% -> 0.29 | J56: =J57-1% -> 0.19 | K56: =K57-1% -> 0.14
B57: Base | D57: 0.37 | E57: 0.4 | F57: 0.48 | G57: 0.4 | H57: 0.35 | I57: 0.3 | J57: 0.2 | K57: 0.15
B58: Bull | D58: =D57+1% -> 0.38 | E58: =E57+1% -> 0.41 | F58: =F57+1% -> 0.49 | G58: =G57+1% -> 0.41 | H58: =H57+1% -> 0.36 | I58: =I57+1% -> 0.31 | J58: =J57+1% -> 0.21 | K58: =K57+1% -> 0.16
B59: Running | D59: =CHOOSE($C$2,D56,D57,D58) -> 0.37 | E59: =CHOOSE($C$2,E56,E57,E58) -> 0.4 | F59: =CHOOSE($C$2,F56,F57,F58) -> 0.48 | G59: =CHOOSE($C$2,G56,G57,G58) -> 0.4 | H59: =CHOOSE($C$2,H56,H57,H58) -> 0.35 | I59: =CHOOSE($C$2,I56,I57,I58) -> 0.3 | J59: =CHOOSE($C$2,J56,J57,J58) -> 0.2 | K59: =CHOOSE($C$2,K56,K57,K58) -> 0.15
D61: Google Network (%)
D62: 2Q26e | E62: 3Q26e | F62: 4Q26e | G62: =2027 -> 2027 | H62: =G62+1 -> 2028 | I62: =H62+1 -> 2029 | J62: 2030 | K62: 2031
B63: Scenario | C63: =C2 -> 2
B64: Bear | D64: =D65-$P$10*$R$10 -> -0.0097772159 | E64: =E65-$P$10*$R$10 -> -0.0097772159 | F64: =F65-$P$10*$R$10 -> -0.0097772159 | G64: =G65-$P$10*$R$10 -> -0.016777216 | H64: =H65-$P$10*$R$10 -> -0.014777216 | I64: =I65-$P$10*$R$10 -> -0.012777216 | J64: =J65-$P$10*$R$10 -> -0.010777216 | K64: =K65-$P$10*$R$10 -> -0.0087772159
B65: Base | D65: -0.003 | E65: -0.003 | F65: -0.003 | G65: -0.01 | H65: -0.008 | I65: -0.006 | J65: -0.004 | K65: -0.002
B66: Bull | D66: =D65+$P$10*$R$10 -> 0.0037772159 | E66: =E65+$P$10*$R$10 -> 0.0037772159 | F66: =F65+$P$10*$R$10 -> 0.0037772159 | G66: =G65+$P$10*$R$10 -> -0.0032227841 | H66: =H65+$P$10*$R$10 -> -0.0012227841 | I66: =I65+$P$10*$R$10 -> 0.00077721585 | J66: =J65+$P$10*$R$10 -> 0.0027772159 | K66: =K65+$P$10*$R$10 -> 0.0047772159
B67: Running | D67: =CHOOSE($C2,D64,D65,D66) -> -0.003 | E67: =CHOOSE($C2,E64,E65,E66) -> -0.003 | F67: =CHOOSE($C2,F64,F65,F66) -> -0.003 | G67: =CHOOSE($C2,G64,G65,G66) -> -0.01 | H67: =CHOOSE($C2,H64,H65,H66) -> -0.008 | I67: =CHOOSE($C2,I64,I65,I66) -> -0.006 | J67: =CHOOSE($C2,J64,J65,J66) -> -0.004 | K67: =CHOOSE($C2,K64,K65,K66) -> -0.002

Sheet Income Statement
O1: Hardcode
O2: Formula
O3: Assumption
A5: Income Statement (Mn USD) | D5: 2020 | E5: 2021 | F5: 1Q22 | G5: 2Q22 | H5: 3Q22 | I5: 4Q22 | J5: 2022 | K5: 1Q23 | L5: 2Q23 | M5: 3Q23 | N5: 4Q23 | O5: 2023 | P5: 1Q24 | Q5: 2Q24 | R5: 3Q24 | S5: 4Q24 | T5: 2024 | U5: 1Q25 | V5: 2Q25 | W5: 3Q25 | X5: 4Q25 | Y5: 2025 | Z5: 1Q26 | AA5: 2Q26 | AB5: 3Q26 | AC5: 4Q26 | AD5: 2026 | AE5: 2027 | AF5: 2028 | AG5: 2029 | AH5: 2030 | AI5: 2031
A6: Revenues | D6: 182527 | E6: 257637 | F6: 68011 | G6: 69685 | H6: 69092 | I6: =J6-SUM(F6:H6) -> 76048 | J6: 282836 | K6: 69787 | L6: 74604 | M6: 76693 | N6: =O6-SUM(K6:M6) -> 86310 | O6: 307394 | P6: 80539 | Q6: 84742 | R6: 88268 | S6: =T6-SUM(P6:R6) -> 96469 | T6: 350018 | U6: 90234 | V6: 96428 | W6: 102346 | X6: =Y6-SUM(U6:W6) -> 113828 | Y6: 402836 | Z6: 109896 | AA6: ='Build Up'!AA6 -> 119510.96 | AB6: ='Build Up'!AB6 -> 134833.52 | AC6: ='Build Up'!AC6 -> 153408.59 | AD6: ='Build Up'!AD6 -> 517649.07 | AE6: ='Build Up'!AE6 -> 632924.59 | AF6: ='Build Up'!AF6 -> 749787.04 | AG6: ='Build Up'!AG6 -> 860924.23 | AH6: ='Build Up'!AH6 -> 969031.63 | AI6: ='Build Up'!AI6 -> 1067907.9
A7: y/y(%) | E7: =E6/D6-1 -> 0.41150076 | J7: =J6/E6-1 -> 0.097808156 | K7: =K6/F6-1 -> 0.026113423 | L7: =L6/G6-1 -> 0.070589079 | M7: =M6/H6-1 -> 0.11001274 | N7: =N6/I6-1 -> 0.13494109 | O7: =O6/J6-1 -> 0.086827702 | P7: =P6/K6-1 -> 0.15406881 | Q7: =Q6/L6-1 -> 0.13589084 | ... AD7: =AD6/Y6-1 -> 0.28501194 | AE7: =AE6/AD6-1 -> 0.22269048 | AF7: =AF6/AE6-1 -> 0.18463882 | AG7: =AG6/AF6-1 -> 0.14822501 | AH7: =AH6/AG6-1 -> 0.12557132 | AI7: =AI6/AH6-1 -> 0.10203615
A8: (-)Cost of revenues | D8: 84732 | E8: 110939 | F8: 29599 | G8: 30104 | H8: 31158 | I8: =J8-SUM(F8:H8) -> 35342 | J8: 126203 | K8: 30612 | L8: 31916 | M8: 33229 | N8: =O8-SUM(K8:M8) -> 37575 | O8: 133332 | P8: 33712 | Q8: 35507 | R8: 36474 | S8: =T8-SUM(P8:R8) -> 40613 | T8: 146306 | U8: 36361 | V8: 39039 | W8: 41369 | X8: =Y8-SUM(U8:W8) -> 45766 | Y8: 162535 | Z8: 41271 | AA8: ='Build Up'!AA50 -> 43331.862 | AB8: ='Build Up'!AB50 -> 48966.555 | AC8: ='Build Up'!AC50 -> 55687.164 | AD8: ='Build Up'!AD50 -> 189263.18 | AE8: ='Build Up'!AE50 -> 230709.54 | AF8: ='Build Up'!AF50 -> 269268.43 | AG8: ='Build Up'!AG50 -> 304178.06 | AH8: ='Build Up'!AH50 -> 341036.4 | AI8: ='Build Up'!AI50 -> 374216.09
A10: Gross Profit | D10: =D6-D8 -> 97795 | E10: =E6-E8 -> 146698 | F10: =F6-F8 -> 38412 | G10: =G6-G8 -> 39581 | H10: =H6-H8 -> 37934 | I10: =I6-I8 -> 40706 | J10: =J6-J8 -> 156633 | K10: =K6-K8 -> 39175 | ... AI10: =AI6-AI8 -> 693691.8
A12: (-)SG&A | D12: =D13+D14+D15 -> 56571 | E12: =E13+E14+E15 -> 67984 | F12: =F13+F14+F15 -> 18318 | G12: =G13+G14+G15 -> 20128 | H12: =H13+H14+H15 -> 20799 | I12: =I13+I14+I15 -> 22546 | J12: =J13+J14+J15 -> 81791 | K12: =K13+K14+K15 -> 21760 | ... Z12: =Z13+Z14+Z15 -> 28929 | AA12: ='Build Up'!AA53 -> 30361.781 | AB12: ='Build Up'!AB53 -> 34309.899 | AC12: ='Build Up'!AC53 -> 39018.897 | AD12: ='Build Up'!AD53 -> 132619.58 | AE12: ='Build Up'!AE53 -> 159299.45 | AF12: ='Build Up'!AF53 -> 185923.44 | AG12: ='Build Up'!AG53 -> 210027.71 | AH12: ='Build Up'!AH53 -> 235477.51 | AI12: ='Build Up'!AI53 -> 258387.3
B13: Research and development | D13: 27573 | E13: 31562 | F13: 9119 | G13: 9841 | H13: 10273 | I13: =J13-SUM(F13:H13) -> 10267 | J13: 39500 | K13: 11468 | L13: 10588 | M13: 11258 | N13: =O13-SUM(K13:M13) -> 12113 | O13: 45427 | P13: 11903 | Q13: 11860 | R13: 12447 | S13: =T13-SUM(P13:R13) -> 13116 | T13: 49326 | U13: 13556 | V13: 13808 | W13: 15151 | X13: =Y13-SUM(U13:W13) -> 18572 | Y13: 61087 | Z13: 17032 | AA13: =AA$12*Z13/SUM(Z$13:Z$15) -> 17875.552 | AB13: =AB$12*AA13/SUM(AA$13:AA$15) -> 20200.014 | AC13: =AC$12*AB13/SUM(AB$13:AB$15) -> 22972.445 | AD13: =AD$12*AC13/SUM(AC$13:AC$15) -> 78080.011 | AE13: =AE$12*AD13/SUM(AD$13:AD$15) -> 93787.831 | AF13: =AF$12*AE13/SUM(AE$13:AE$15) -> 109462.76 | AG13: =AG$12*AF13/SUM(AF$13:AF$15) -> 123654.19 | AH13: =AH$12*AG13/SUM(AG$13:AG$15) -> 138637.8 | AI13: =AI$12*AH13/SUM(AH$13:AH$15) -> 152125.98
B14: Sales and marketing | D14: 17946 | E14: 22912 | F14: 5825 | G14: 6630 | H14: 6929 | I14: =J14-SUM(F14:H14) -> 7183 | J14: 26567 | K14: 6533 | L14: 6781 | M14: 6884 | N14: =O14-SUM(K14:M14) -> 7719 | O14: 27917 | P14: 6426 | Q14: 6792 | R14: 7227 | S14: =T14-SUM(P14:R14) -> 7363 | T14: 27808 | U14: 6172 | V14: 7101 | W14: 7205 | X14: =Y14-SUM(U14:W14) -> 8215 | Y14: 28693 | Z14: 7606 | AA14: =AA$12*Z14/SUM(Z$13:Z$15) -> 7982.7061 | AB14: =AB$12*AA14/SUM(AA$13:AA$15) -> 9020.7437 | AC14: =AC$12*AB14/SUM(AB$13:AB$15) -> 10258.831 | AD14: =AD$12*AC14/SUM(AC$13:AC$15) -> 34868.281 | AE14: =AE$12*AD14/SUM(AD$13:AD$15) -> 41882.941 | AF14: =AF$12*AE14/SUM(AE$13:AE$15) -> 48882.91 | AG14: =AG$12*AF14/SUM(AF$13:AF$15) -> 55220.393 | AH14: =AH$12*AG14/SUM(AG$13:AG$15) -> 61911.645 | AI14: =AI$12*AH14/SUM(AH$13:AH$15) -> 67935.076
B15: General and administrative | D15: 11052 | E15: 13510 | F15: 3374 | G15: 3657 | H15: 3597 | I15: =J15-SUM(F15:H15) -> 5096 | J15: 15724 | K15: 3759 | L15: 3481 | M15: 3979 | N15: =O15-SUM(K15:M15) -> 5206 | O15: 16425 | P15: 3026 | Q15: 3158 | R15: 3599 | S15: =T15-SUM(P15:R15) -> 4405 | T15: 14188 | U15: 3539 | V15: 5209 | W15: 7393 | X15: =Y15-SUM(U15:W15) -> 5341 | Y15: 21482 | Z15: 4291 | AA15: =AA$12*Z15/SUM(Z$13:Z$15) -> 4503.5224 | AB15: =AB$12*AA15/SUM(AA$13:AA$15) -> 5089.1416 | AC15: =AC$12*AB15/SUM(AB$13:AB$15) -> 5787.621 | AD15: =AD$12*AC15/SUM(AC$13:AC$15) -> 19671.285 | AE15: =AE$12*AD15/SUM(AD$13:AD$15) -> 23628.674 | AF15: =AF$12*AE15/SUM(AE$13:AE$15) -> 27577.776 | AG15: =AG$12*AF15/SUM(AF$13:AF$15) -> 31153.13 | AH15: =AH$12*AG15/SUM(AG$13:AG$15) -> 34928.066 | AI15: =AI$12*AH15/SUM(AH$13:AH$15) -> 38326.244
A17: EBIT | D17: 41224 | E17: 78714 | F17: =F10-F12 -> 20094 | G17: =G10-G12 -> 19453 | H17: =H10-H12 -> 17135 | I17: =I10-I12 -> 18160 | J17: 74842 | K17: =K10-K12 -> 17415 | L17: =L10-L12 -> 21838 | M17: =M10-M12 -> 21343 | N17: =N10-N12 -> 23697 | O17: 84293 | P17: =P10-P12 -> 25472 | Q17: =Q10-Q12 -> 27425 | R17: =R10-R12 -> 28521 | S17: =S10-S12 -> 30972 | T17: 112390 | U17: =U10-U12 -> 30606 | V17: =V10-V12 -> 31271 | W17: =W10-W12 -> 31228 | X17: =X10-X12 -> 35934 | Y17: 129039 | Z17: =Z10-Z12 -> 39696 | AA17: ='Build Up'!AA32 -> 45817.322 | AB17: ='Build Up'!AB32 -> 51557.065 | AC17: ='Build Up'!AC32 -> 58702.525 | AD17: ='Build Up'!AD32 -> 195772.91 | AE17: ='Build Up'!AE32 -> 240561.42 | AF17: ='Build Up'!AF32 -> 291847.53 | AG17: ='Build Up'!AG32 -> 343614.6 | AH17: ='Build Up'!AH32 -> 389037.75 | AI17: ='Build Up'!AI32 -> 431485.97
A19: (+/-)Financial Result | D19: 6858 | E19: 12020 | F19: -1160 | G19: -439 | H19: -902 | I19: =J19-SUM(F19:H19) -> -1013 | J19: -3514 | K19: 790 | L19: 65 | M19: -146 | N19: =O19-SUM(K19:M19) -> 715 | O19: 1424 | P19: 2843 | Q19: 126 | R19: 3185 | S19: =T19-SUM(P19:R19) -> 1271 | T19: 7425 | U19: 11183 | V19: 2662 | W19: 12759 | X19: =Y19-SUM(U19:W19) -> 3183 | Y19: 29787 | Z19: 37716 | AA19: =SUM(AA20:AA23) -> 3464.8552 | AB19: =SUM(AB20:AB23) -> 2228.0046 | AC19: =SUM(AC20:AC23) -> 7130.4042 | AD19: =SUM(AD20:AD23) -> 50539.264 | AE19: =SUM(AE20:AE23) -> 2524.012 | AF19: =SUM(AF20:AF23) -> -440.3219 | AG19: =SUM(AG20:AG23) -> 10855.905 | AH19: =SUM(AH20:AH23) -> 3572.9113 | AI19: =SUM(AI20:AI23) -> 822.46911
B20: (-) Interest Expense | D20: -135 | E20: -346 | F20: -83 | G20: -83 | H20: -101 | I20: =J20-SUM(F20:H20) -> -90 | J20: -357 | K20: -80 | L20: -43 | M20: -116 | N20: =O20-SUM(K20:M20) -> -69 | O20: -308 | P20: -94 | Q20: -67 | R20: -54 | S20: =T20-SUM(P20:R20) -> -53 | T20: -268 | U20: -34 | V20: -261 | W20: -143 | X20: =Y20-SUM(U20:W20) -> -298 | Y20: -736 | Z20: -533 | AA20: ='Debt Schedule'!W15 -> -796.30662 | AB20: ='Debt Schedule'!X15 -> -836.12195 | AC20: ='Debt Schedule'!Y15 -> -877.92805 | AD20: ='Debt Schedule'!Z15 -> -3043.3566 | AE20: ='Debt Schedule'!AA15 -> -3919.9547 | AF20: ='Debt Schedule'!AB15 -> -4233.5511 | AG20: ='Debt Schedule'!AC15 -> -4487.5641 | AH20: ='Debt Schedule'!AD15 -> -4667.0667 | AI20: ='Debt Schedule'!AE15 -> -4760.408
B21: (+) Interest Income | D21: 1865 | E21: 1499 | F21: 414 | G21: 486 | H21: 615 | I21: =J21-SUM(F21:H21) -> 659 | J21: 2174 | K21: 797 | L21: 892 | M21: 1066 | N21: =O21-SUM(K21:M21) -> 930 | O21: 3685 | P21: 1061 | Q21: 1090 | R21: 1243 | S21: =T21-SUM(P21:R21) -> 1088 | T21: 4482 | U21: 1001 | V21: 1050 | W21: 1076 | X21: =Y21-SUM(U21:W21) -> 1210 | Y21: 4337 | Z21: 1381 | AA21: ='Debt Schedule'!W18 -> 2216.1618 | AB21: ='Debt Schedule'!X18 -> 2143.1266 | AC21: ='Debt Schedule'!Y18 -> 1948.3322 | AD21: ='Debt Schedule'!Z18 -> 7688.6207 | AE21: ='Debt Schedule'!AA18 -> 4958.2167 | AF21: ='Debt Schedule'!AB18 -> 2585.2292 | AG21: ='Debt Schedule'!AC18 -> 760.21916 | AH21: ='Debt Schedule'!AD18 -> 2188.478 | AI21: ='Debt Schedule'!AE18 -> 4042.3771
B22: (+/-) Currency Exchange | D22: -344 | E22: -240 | F22: -73 | G22: -260 | H22: -136 | I22: =J22-SUM(F22:H22) -> -185 | J22: -654 | K22: -210 | L22: -268 | M22: -311 | N22: =O22-SUM(K22:M22) -> -449 | O22: -1238 | P22: -238 | Q22: -173 | R22: 23 | S22: =T22-SUM(P22:R22) -> -21 | T22: -409 | U22: -106 | V22: -69 | W22: -143 | X22: =Y22-SUM(U22:W22) -> -64 | Y22: -382 | Z22: 146 | AA22: =MEDIAN(Z22,U22:X22,P22:S22) -> -69 | AB22: =MEDIAN(Y22,T22,O22,J22) -> -531.5 | AC22: =MEDIAN(Z22,U22,P22,K22) -> -158 | AD22: =SUM(Z22:AC22) -> -612.5 | AE22: =MEDIAN(AB22,W22,R22,M22) -> -227 | AF22: =MEDIAN(AC22,X22,S22,N22) -> -111 | AG22: =MEDIAN(AD22,Y22,T22,O22) -> -510.75 | AH22: =MEDIAN(AE22,Z22,U22,P22) -> -166.5 | AI22: =MEDIAN(AF22,AA22,V22,Q22) -> -90
B23: (+/-) Others | D23: =D19-D20-D21-D22 -> 5472 | E23: =E19-E20-E21-E22 -> 11107 | F23: =F19-F20-F21-F22 -> -1418 | G23: =G19-G20-G21-G22 -> -582 | H23: =H19-H20-H21-H22 -> -1280 | I23: =I19-I20-I21-I22 -> -1397 | J23: =J19-J20-J21-J22 -> -4677 | K23: =K19-K20-K21-K22 -> 283 | ... Z23: =Z19-Z20-Z21-Z22 -> 36722 | AA23: =MEDIAN(Z23,U23:X23,P23:S23) -> 2114 | AB23: =MEDIAN(Y23,T23,O23,J23) -> 1452.5 | AC23: =MEDIAN(Z23,U23,P23,K23) -> 6218 | AD23: =SUM(Z23:AC23) -> 46506.5 | AE23: =MEDIAN(AB23,W23,R23,M23) -> 1712.75 | AF23: =MEDIAN(AC23,X23,S23,N23) -> 1319 | AG23: =MEDIAN(AD23,Y23,T23,O23) -> 15094 | AH23: =MEDIAN(AE23,Z23,U23,P23) -> 6218 | AI23: =MEDIAN(AF23,AA23,V23,Q23) -> 1630.5
A25: EBT | D25: 48082 | E25: 90734 | F25: =F17+F19 -> 18934 | G25: =G17+G19 -> 19014 | H25: =H17+H19 -> 16233 | I25: =I17+I19 -> 17147 | J25: 71328 | K25: =K17+K19 -> 18205 | L25: =L17+L19 -> 21903 | M25: =M17+M19 -> 21197 | N25: =N17+N19 -> 24412 | O25: 85717 | P25: =P17+P19 -> 28315 | Q25: =Q17+Q19 -> 27551 | R25: =R17+R19 -> 31706 | S25: =S17+S19 -> 32243 | T25: 119815 | U25: =U17+U19 -> 41789 | V25: =V17+V19 -> 33933 | W25: =W17+W19 -> 43987 | X25: =X17+X19 -> 39117 | Y25: 158826 | Z25: =Z17+Z19 -> 77412 | AA25: =AA17+AA19 -> 49282.177 | AB25: =AB17+AB19 -> 53785.07 | AC25: =AC17+AC19 -> 65832.929 | AD25: =AD17+AD19 -> 246312.18 | AE25: =AE17+AE19 -> 243085.44 | AF25: =AF17+AF19 -> 291407.21 | AG25: =AG17+AG19 -> 354470.51 | ... AI25: =AI17+AI19 -> 432308.43
A27: Taxes | D27: 7813 | E27: 14701 | F27: 2498 | G27: 3012 | H27: 2323 | I27: =J27-SUM(F27:H27) -> 3523 | J27: 11356 | K27: 3154 | L27: 3535 | M27: 1508 | N27: =O27-SUM(K27:M27) -> 3725 | O27: 11922 | P27: 4653 | Q27: 3932 | R27: 5405 | S27: =T27-SUM(P27:R27) -> 5707 | T27: 19697 | U27: 7249 | V27: 5737 | W27: 9008 | X27: =Y27-SUM(U27:W27) -> 4662 | Y27: 26656 | Z27: 14834 | AA27: =AA28*AA25 -> 9443.6498 | AB27: =AB28*AB25 -> 10306.512 | AC27: =AC28*AC25 -> 12615.172 | AD27: =AD28*AD25 -> 47199.334 | AE27: =AE28*AE25 -> 46581.013 | AF27: =AF28*AF25 -> 55840.625 | AG27: =AG28*AG25 -> 67925.07 | AH27: =AH28*AH25 -> 75233.641 | AI27: =AI28*AI25 -> 82840.688
B28: Effective Tax Rate | D28: =D27/D25 -> 0.16249324 | E28: =E27/E25 -> 0.16202306 | F28: =F27/F25 -> 0.13193197 | G28: =G27/G25 -> 0.15840959 | H28: =H27/H25 -> 0.14310355 | I28: =I27/I25 -> 0.20545868 | J28: =J27/J25 -> 0.15920817 | K28: =K27/K25 -> 0.17324911 | ... Z28: =Z27/Z25 -> 0.19162404 | AA28: =Z28 -> 0.19162404 | AB28: =AA28 -> 0.19162404 | AC28: =AB28 -> 0.19162404 | AD28: =AC28 -> 0.19162404 | AE28: =AD28 -> 0.19162404 | AF28: =AE28 -> 0.19162404 | AG28: =AF28 -> 0.19162404 | AH28: =AG28 -> 0.19162404 | AI28: =AH28 -> 0.19162404
A29: Net Income | D29: 40269 | E29: 76033 | F29: =F25-F27 -> 16436 | G29: =G25-G27 -> 16002 | H29: =H25-H27 -> 13910 | I29: =I25-I27 -> 13624 | J29: 59972 | K29: =K25-K27 -> 15051 | L29: =L25-L27 -> 18368 | M29: =M25-M27 -> 19689 | N29: =N25-N27 -> 20687 | O29: 73795 | P29: =P25-P27 -> 23662 | Q29: =Q25-Q27 -> 23619 | R29: =R25-R27 -> 26301 | S29: =S25-S27 -> 26536 | T29: 100118 | U29: =U25-U27 -> 34540 | V29: =V25-V27 -> 28196 | W29: =W25-W27 -> 34979 | X29: =X25-X27 -> 34455 | Y29: 132170 | Z29: =Z25-Z27 -> 62578 | AA29: =AA25-AA27 -> 39838.528 | AB29: =AB25-AB27 -> 43478.558 | AC29: =AC25-AC27 -> 53217.758 | AD29: =AD25-AD27 -> 199112.84 | AE29: =AE25-AE27 -> 196504.42 | AF29: =AF25-AF27 -> 235566.58 | AG29: =AG25-AG27 -> 286545.44 | ... AI29: =AI25-AI27 -> 349467.75
B30: Net Margin(%) | D30: =D29/D6 -> 0.22061942 | E30: =E29/E6 -> 0.29511677 | F30: =F29/F6 -> 0.24166679 | G30: =G29/G6 -> 0.22963335 | H30: =H29/H6 -> 0.20132577 | I30: =I29/I6 -> 0.17915001 | J30: =J29/J6 -> 0.21203807 | K30: =K29/K6 -> 0.21567054 | ... Z30: =Z29/Z6 -> 0.56942928
A32: Payout | D32: =-('CFS - Estimates'!D24+'CFS - Estimates'!D23) -> 31149 | E32: =-('CFS - Estimates'!E24+'CFS - Estimates'!E23) -> 50274 | J32: =-('CFS - Estimates'!F24+'CFS - Estimates'!F23) -> 59296 | O32: =-('CFS - Estimates'!K24+'CFS - Estimates'!K23) -> 61504 | T32: =-('CFS - Estimates'!P24+'CFS - Estimates'!P23) -> 69585 | Y32: =-('CFS - Estimates'!U24+'CFS - Estimates'!U23) -> 55758 | AA32: =AA29*AA33 -> 11951.558 | AB32: =AB29*AB33 -> 13043.567 | AC32: =AC29*AC33 -> 15965.327 | AD32: =AD29*AD33 -> 59733.853 | AE32: =AE29*AE33 -> 68776.548 | AF32: =AF29*AF33 -> 94226.632 | AG32: =AG29*AG33 -> 143272.72 | AH32: =AH29*AH33 -> 174557.36 | AI32: =AI29*AI33 -> 235890.73
D33: =D32/D29 -> 0.77352306 | E33: =E32/E29 -> 0.66121289 | J33: =J32/J29 -> 0.98872807 | O33: =O32/O29 -> 0.833444 | T33: =T32/T29 -> 0.69502986 | Y33: =Y32/Y29 -> 0.42186578 | AA33: 0.3 | AB33: =AA33 -> 0.3 | AC33: =AB33 -> 0.3 | AD33: =AC33 -> 0.3 | AE33: =35% -> 0.35 | AF33: 0.4 | AG33: 0.5 | AH33: 0.55 | AI33: 0.675
A35: Retained Profits | D35: =D29-D32 -> 9120 | E35: =E29-E32 -> 25759 | J35: =J29-J32 -> 676 | O35: =O29-O32 -> 12291 | T35: =T29-T32 -> 30533 | Y35: =Y29-Y32 -> 76412 | AA35: =AA29-AA32 -> 27886.969 | AB35: =AB29-AB32 -> 30434.99 | AC35: =AC29-AC32 -> 37252.43 | AD35: =AD29-AD32 -> 139378.99 | AE35: =AE29-AE32 -> 127727.88 | AF35: =AF29-AF32 -> 141339.95 | AG35: =AG29-AG32 -> 143272.72 | AH35: =AH29-AH32 -> 142819.66 | AI35: =AI29-AI32 -> 113577.02
A37: Dividens | D37: ='CFS - Estimates'!D23 -> 0 | E37: ='CFS - Estimates'!E23 -> 0 | F37: ='CFS - Estimates'!F23 -> 0 | G37: ='CFS - Estimates'!G23 -> 0 | H37: ='CFS - Estimates'!H23 -> 0 | I37: ='CFS - Estimates'!I23 -> 0 | J37: ='CFS - Estimates'!J23 -> 0 | K37: ='CFS - Estimates'!G23 -> 0 | L37: ='CFS - Estimates'!H23 -> 0 | M37: ='CFS - Estimates'!I23 -> 0 | N37: ='CFS - Estimates'!J23 -> 0 | O37: ='CFS - Estimates'!K23 -> 0 | P37: ='CFS - Estimates'!L23 -> 0 | Q37: ='CFS - Estimates'!M23 -> -2466 | R37: ='CFS - Estimates'!N23 -> -2455 | ... Z37: ='CFS - Estimates'!V23 -> -2542 | AA37: =AA32*AA38 -> 2390.3117 | AB37: =AB32*AB38 -> 2608.7135 | AC37: =AC32*AC38 -> 3193.0655 | AD37: =AD32*AD38 -> 11946.771 | AE37: =AE32*AE38 -> 13755.31 | AF37: =AF32*AF38 -> 18845.326 | AG37: =AG32*AG38 -> 28654.544 | AH37: =AH32*AH38 -> 34911.473 | AI37: =AI32*AI38 -> 47178.146
B38: As % of Payout | D38: 0 | E38: 0 | F38: 0 | G38: 0 | H38: 0 | I38: 0 | J38: 0 | K38: 0 | L38: 0 | M38: 0 | N38: 0 | O38: 0 | P38: 0 | Q38: =Q37/(Q40+Q37) -> 0.13586777 | R38: =R37/(R40+R37) -> 0.13834103 | S38: =S37/(S40+S37) -> 0.13571945 | T38: =-T37/T32 -> 0.10581303 | U38: =U37/(U40+U37) -> 0.13906982 | V38: =V37/(V40+V37) -> 0.15715963 | W38: =W37/(W40+W37) -> 0.18062678 | X38: =X37/(X40+X37) -> 0.31561917 | Y38: =-Y37/Y32 -> 0.18022526 | Z38: =Z37/(Z40+Z37) -> 1 | AA38: 0.2 | AB38: 0.2 | AC38: 0.2 | AD38: 0.2 | AE38: 0.2 | AF38: 0.2 | AG38: 0.2 | AH38: 0.2 | AI38: 0.2
A40: Repurchase of Stock | D40: ='CFS - Estimates'!D24 -> -31149 | E40: ='CFS - Estimates'!E24 -> -50274 | J40: ='CFS - Estimates'!F24 -> -59296 | K40: ='CFS - Estimates'!G24 -> -14557 | L40: ='CFS - Estimates'!H24 -> -14969 | M40: ='CFS - Estimates'!I24 -> -15787 | N40: ='CFS - Estimates'!J24 -> -16191 | O40: ='CFS - Estimates'!K24 -> -61504 | P40: ='CFS - Estimates'!L24 -> -15696 | Q40: ='CFS - Estimates'!M24 -> -15684 | ... Z40: ='CFS - Estimates'!V24 -> 0 | AA40: =AA32*AA41 -> 9561.2466 | AB40: =AB32*AB41 -> 10434.854 | AC40: =AC32*AC41 -> 12772.262 | AD40: =AD32*AD41 -> 47787.082 | AE40: =AE32*AE41 -> 55021.239 | AF40: =AF32*AF41 -> 75381.306 | AG40: =AG32*AG41 -> 114618.18 | AH40: =AH32*AH41 -> 139645.89 | AI40: =AI32*AI41 -> 188712.58
B41: As % of Payout | D41: 1 | E41: 1 | J41: 1 | K41: 1 | L41: 1 | M41: 1 | N41: 1 | O41: 1 | P41: 1 | Q41: =Q40/(Q37+Q40) -> 0.86413223 | R41: =R40/(R37+R40) -> 0.86165897 | S41: =S40/(S37+S40) -> 0.86428055 | T41: =-T40/T32 -> 0.89418697 | U41: =U40/(U37+U40) -> 0.86093018 | V41: =V40/(V37+V40) -> 0.84284037 | W41: =W40/(W37+W40) -> 0.81937322 | X41: =X40/(X37+X40) -> 0.68438083 | Y41: =-Y40/Y32 -> 0.81977474 | Z41: =Z40/(Z37+Z40) -> 0 | AA41: 0.8 | AB41: 0.8 | AC41: 0.8 | AD41: 0.8 | AE41: 0.8 | AF41: 0.8 | AG41: 0.8 | AH41: 0.8 | AI41: 0.8
A43: EBITDA | D43: =D17+'CFS - Estimates'!D9 -> 54921 | E43: =E17+'CFS - Estimates'!E9 -> 91155 | F43: =F17+'CFS - Estimates'!F9 -> 36022 | G43: =G17+'CFS - Estimates'!G9 -> 22639 | H43: =H17+'CFS - Estimates'!H9 -> 20532 | I43: =I17+'CFS - Estimates'!I9 -> 21960 | J43: =J17+'CFS - Estimates'!F9 -> 90770 | K43: =K17+'CFS - Estimates'!G9 -> 20601 | L43: =L17+'CFS - Estimates'!H9 -> 25235 | M43: =M17+'CFS - Estimates'!I9 -> 25143 | N43: =N17+'CFS - Estimates'!J9 -> 25260 | O43: =O17+'CFS - Estimates'!K9 -> 96239 | P43: =P17+'CFS - Estimates'!L9 -> 28885 | Q43: =Q17+'CFS - Estimates'!M9 -> 31133 | ... AI43: =AI17+'CFS - Estimates'!AE9 -> 484881.36
A44: EBITDA Margin | D44: =D43/D6 -> 0.30089247 | E44: =E43/E6 -> 0.35381176 | F44: =F43/F6 -> 0.52964962 | G44: =G43/G6 -> 0.32487623 | H44: =H43/H6 -> 0.29716899 | I44: =I43/I6 -> 0.28876499 | J44: =J43/J6 -> 0.32092803 | K44: =K43/K6 -> 0.29519825 | ... AI44: =AI43/AI6 -> 0.45404792

Sheet BS
K1: Hardcode | S1: Hardcode
K2: Formula | S2: Formula
S3: Assumption
D4: =IF(D7=D40,"OK",D7-D40) -> OK | E4: =IF(E7=E40,"OK",E7-E40) -> OK | F4: =IF(F7=F40,"OK",F7-F40) -> OK | G4: =IF(G7=G40,"OK",G7-G40) -> OK | H4: =IF(H7=H40,"OK",H7-H40) -> OK | I4: =IF(I7=I40,"OK",I7-I40) -> OK | J4: =IF(J7=J40,"OK",J7-J40) -> OK | K4: =IF(K7=K40,"OK",K7-K40) -> OK | ... AE4: =IF(AE7=AE40,"OK",AE7-AE40) -> OK
A5: Balance Sheet (Mn USD) | D5: 2020 | E5: 2021 | F5: 2022 | G5: 1Q23 | H5: 1Q23 | I5: 1Q23 | J5: 1Q23 | K5: 2023 | L5: 1Q24 | M5: 2Q24 | N5: 3Q24 | O5: 4Q24 | P5: 2024 | Q5: 1Q25 | R5: 1Q25 | S5: 1Q25 | T5: 1Q25 | U5: 2025 | V5: 1Q26 | W5: 2Q26 | X5: 3Q26 | Y5: 4Q26 | Z5: 2026 | AA5: 2027 | AB5: 2028 | AC5: 2029 | AD5: 2030 | AE5: 2031
A7: Assets | D7: =D9+D14 -> 319616 | E7: =E9+E14 -> 359268 | F7: =F9+F14 -> 365264 | G7: =G9+G14 -> 369491 | H7: =H9+H14 -> 383044 | I7: =I9+I14 -> 396711 | J7: =J9+J14 -> 402392 | K7: =K9+K14 -> 402392 | ... AE7: =AE9+AE14 -> 1837821.8
A9: Current Assets | D9: =D10+D11+D12 -> 174296 | E9: =E10+E11+E12 -> 188143 | F9: =F10+F11+F12 -> 164795 | G9: =G10+G11+G12 -> 161985 | H9: =H10+H11+H12 -> 168788 | I9: =I10+I11+I12 -> 176310 | J9: =J10+J11+J12 -> 171530 | K9: =K10+K11+K12 -> 171530 | ... V9: =V10+V11+V12 -> 213753 | W9: =SUM(W10:W12) -> 286540.59 | X9: =SUM(X10:X12) -> 290989.95 | Y9: =SUM(Y10:Y12) -> 286778.25 | Z9: =SUM(Z10:Z12) -> 286778.25 | AA9: =SUM(AA10:AA12) -> 224340.92 | AB9: =SUM(AB10:AB12) -> 192665.62 | AC9: =SUM(AC10:AC12) -> 172138.61 | AD9: =SUM(AD10:AD12) -> 223380.23 | AE9: =SUM(AE10:AE12) -> 282418.6
A10: Cash and cash equivalents | D10: 136694 | E10: 139649 | F10: 113762 | G10: ='Q - BS'!C9 -> 115102 | H10: ='Q - BS'!D9 -> 118332 | I10: ='Q - BS'!E9 -> 119935 | J10: ='Q - BS'!F9 -> 110916 | K10: 110916 | L10: ='Q - BS'!G9 -> 108090 | M10: ='Q - BS'!H9 -> 100725 | N10: ='Q - BS'!I9 -> 93230 | O10: ='Q - BS'!J9 -> 95657 | P10: 95657 | Q10: ='Q - BS'!K9 -> 95328 | R10: ='Q - BS'!L9 -> 95148 | S10: ='Q - BS'!M9 -> 98496 | T10: ='Q - BS'!N9 -> 126843 | U10: 126843 | V10: ='Q - BS'!O9 -> 126840 | W10: ='CFS - Estimates'!W33 -> 200340.67 | X10: ='CFS - Estimates'!X33 -> 193738.29 | Y10: ='CFS - Estimates'!Y33 -> 176128.91 | Z10: ='CFS - Estimates'!Z33 -> 176128.91 | AA10: ='CFS - Estimates'!AA33 -> 110213.21 | AB10: ='CFS - Estimates'!AB33 -> 57465.5 | AC10: ='CFS - Estimates'!AC33 -> 16898.453 | AD10: ='CFS - Estimates'!AD33 -> 48646.356 | AE10: ='CFS - Estimates'!AE33 -> 89855.563
A11: Accounts receivable | D11: 30930 | E11: 39304 | F11: 40258 | G11: ='Q - BS'!C10 -> 36036 | H11: ='Q - BS'!D10 -> 38804 | I11: ='Q - BS'!E10 -> 41020 | J11: ='Q - BS'!F10 -> 47964 | K11: 47964 | L11: ='Q - BS'!G10 -> 44552 | M11: ='Q - BS'!H10 -> 47087 | N11: ='Q - BS'!I10 -> 49104 | O11: ='Q - BS'!J10 -> 52340 | P11: 52340 | Q11: ='Q - BS'!K10 -> 51000 | R11: ='Q - BS'!L10 -> 55048 | S11: ='Q - BS'!M10 -> 57148 | T11: ='Q - BS'!N10 -> 62886 | U11: 62886 | V11: ='Q - BS'!O10 -> 62999 | W11: =W50 -> 66732.58 | X11: =X50 -> 75288.394 | Y11: =Y50 -> 85660.347 | Z11: =Z50 -> 85660.347 | AA11: =AA50 -> 88353.171 | AB11: =AB50 -> 104666.6 | AC11: =AC50 -> 120180.8 | AD11: =AD50 -> 135272.07 | AE11: =AE50 -> 149074.71
A12: Other current assets | D12: 6672 | E12: 9190 | F12: 10775 | G12: ='Q - BS'!C11 -> 10847 | H12: ='Q - BS'!D11 -> 11652 | I12: ='Q - BS'!E11 -> 15355 | J12: ='Q - BS'!F11 -> 12650 | K12: 12650 | L12: ='Q - BS'!G11 -> 12829 | M12: ='Q - BS'!H11 -> 14183 | N12: ='Q - BS'!I11 -> 15207 | O12: ='Q - BS'!J11 -> 15714 | P12: 15714 | Q12: ='Q - BS'!K11 -> 15724 | R12: ='Q - BS'!L11 -> 16020 | S12: ='Q - BS'!M11 -> 18303 | T12: ='Q - BS'!N11 -> 16309 | U12: 16309 | V12: ='Q - BS'!O11 -> 23914 | W12: =W53 -> 19467.345 | X12: =X53 -> 21963.262 | Y12: =Y53 -> 24988.986 | Z12: =Z53 -> 24988.986 | AA12: =AA53 -> 25774.542 | AB12: =AB53 -> 30533.523 | AC12: =AC53 -> 35059.354 | AD12: =AD53 -> 39461.804 | AE12: =AE53 -> 43488.334
A14: Non Current Assets | D14: =D15+D16+D17+D18+D19 -> 145320 | E14: =E15+E16+E17+E18+E19 -> 171125 | F14: =F15+F16+F17+F18+F19 -> 200469 | G14: =SUM(G15:G19) -> 207506 | H14: =SUM(H15:H19) -> 214256 | I14: =SUM(I15:I19) -> 220401 | J14: =SUM(J15:J19) -> 230862 | K14: =K15+K16+K17+K18+K19 -> 230862 | L14: =SUM(L15:L19) -> 241879 | M14: =SUM(M15:M19) -> 252775 | N14: =SUM(N15:N19) -> 272725 | O14: =SUM(O15:O19) -> 286545 | P14: =P15+P16+P17+P18+P19 -> 286545 | Q14: =SUM(Q15:Q19) -> 313322 | R14: =SUM(R15:R19) -> 335837 | S14: =SUM(S15:S19) -> 362522 | T14: =SUM(T15:T19) -> 389243 | U14: =U15+U16+U17+U18+U19 -> 389243 | V14: =SUM(V15:V19) -> 490166 | W14: =SUM(W15:W19) -> 528409.51 | X14: =SUM(X15:X19) -> 575601.24 | Y14: =SUM(Y15:Y19) -> 641566.93 | Z14: =SUM(Z15:Z19) -> 641566.93 | AA14: =SUM(AA15:AA19) -> 863090.54 | AB14: =SUM(AB15:AB19) -> 1088026.7 | AC14: =SUM(AC15:AC19) -> 1303257.7 | ... AE14: =SUM(AE15:AE19) -> 1555403.2
A15: Investiments | D15: 20703 | E15: 29549 | F15: 30492 | G15: ='Q - BS'!C14 -> 31213 | H15: ='Q - BS'!D14 -> 31224 | I15: ='Q - BS'!E14 -> 30907 | J15: ='Q - BS'!F14 -> 31008 | K15: 31008 | L15: ='Q - BS'!G14 -> 33994 | M15: ='Q - BS'!H14 -> 34172 | N15: ='Q - BS'!I14 -> 36177 | O15: ='Q - BS'!J14 -> 37982 | P15: 37982 | Q15: ='Q - BS'!K14 -> 51029 | R15: ='Q - BS'!L14 -> 52574 | S15: ='Q - BS'!M14 -> 63800 | T15: ='Q - BS'!N14 -> 68687 | U15: 68687 | V15: ='Q - BS'!O14 -> 106946 | W15: =V15 -> 106946 | X15: =W15 -> 106946 | Y15: =X15 -> 106946 | Z15: =Y15 -> 106946 | AA15: =Z15 -> 106946 | AB15: =AA15 -> 106946 | AC15: =AB15 -> 106946 | AD15: =AC15 -> 106946 | AE15: =AD15 -> 106946
A16: PP&E | D16: 84749 | E16: 97599 | F16: 112668 | G16: ='Q - BS'!C15 -> 117560 | H16: ='Q - BS'!D15 -> 121208 | I16: ='Q - BS'!E15 -> 125705 | J16: ='Q - BS'!F15 -> 134345 | K16: 134345 | L16: ='Q - BS'!G15 -> 143182 | M16: ='Q - BS'!H15 -> 151155 | N16: ='Q - BS'!I15 -> 161270 | O16: ='Q - BS'!J15 -> 171036 | P16: 171036 | Q16: ='Q - BS'!K15 -> 185062 | R16: ='Q - BS'!L15 -> 203231 | S16: ='Q - BS'!M15 -> 223787 | T16: ='Q - BS'!N15 -> 246597 | U16: 246597 | V16: ='Q - BS'!O15 -> 281020 | W16: =V16-'CFS - Estimates'!W17-'CFS - Estimates'!W9 -> 319263.51 | X16: =W16-'CFS - Estimates'!X17-'CFS - Estimates'!X9 -> 366455.24 | Y16: =X16-'CFS - Estimates'!Y17-'CFS - Estimates'!Y9 -> 432420.93 | Z16: =Y16 -> 432420.93 | AA16: =Z16-'CFS - Estimates'!AA17-'CFS - Estimates'!AA9 -> 653944.54 | AB16: =AA16-'CFS - Estimates'!AB17-'CFS - Estimates'!AB9 -> 878880.65 | AC16: =AB16-'CFS - Estimates'!AC17-'CFS - Estimates'!AC9 -> 1094111.7 | AD16: =AC16-'CFS - Estimates'!AD17-'CFS - Estimates'!AD9 -> 1239466.5 | AE16: =AD16-'CFS - Estimates'!AE17-'CFS - Estimates'!AE9 -> 1346257.2
A17: Lease | D17: 12211 | E17: 12959 | F17: 14381 | G17: ='Q - BS'!C16 -> 14447 | H17: ='Q - BS'!D16 -> 14469 | I17: ='Q - BS'!E16 -> 14199 | J17: ='Q - BS'!F16 -> 14091 | K17: 14091 | L17: ='Q - BS'!G16 -> 13768 | M17: ='Q - BS'!H16 -> 13606 | N17: ='Q - BS'!I16 -> 13561 | O17: ='Q - BS'!J16 -> 13588 | P17: 13588 | Q17: ='Q - BS'!K16 -> 13722 | R17: ='Q - BS'!L16 -> 14255 | S17: ='Q - BS'!M16 -> 14524 | T17: ='Q - BS'!N16 -> 15221 | U17: 15221 | V17: ='Q - BS'!O16 -> 15509 | W17: =V17 -> 15509 | X17: =W17 -> 15509 | Y17: =X17 -> 15509 | Z17: =Y17 -> 15509 | AA17: =Z17 -> 15509 | AB17: =AA17 -> 15509 | AC17: =AB17 -> 15509 | AD17: =AC17 -> 15509 | AE17: =AD17 -> 15509
A18: Goodwill | D18: 21175 | E18: 22956 | F18: 28960 | G18: ='Q - BS'!C17 -> 28994 | H18: ='Q - BS'!D17 -> 29210 | I18: ='Q - BS'!E17 -> 29146 | J18: ='Q - BS'!F17 -> 29198 | K18: 29198 | L18: ='Q - BS'!G17 -> 29183 | M18: ='Q - BS'!H17 -> 29185 | N18: ='Q - BS'!I17 -> 31935 | O18: ='Q - BS'!J17 -> 31885 | P18: 31885 | Q18: ='Q - BS'!K17 -> 32173 | R18: ='Q - BS'!L17 -> 32335 | S18: ='Q - BS'!M17 -> 33269 | T18: ='Q - BS'!N17 -> 33380 | U18: 33380 | V18: ='Q - BS'!O17 -> 57774 | W18: =V18 -> 57774 | X18: =W18 -> 57774 | Y18: =X18 -> 57774 | Z18: =Y18 -> 57774 | AA18: =Z18 -> 57774 | AB18: =AA18 -> 57774 | AC18: =AB18 -> 57774 | AD18: =AC18 -> 57774 | AE18: =AD18 -> 57774
A19: Others Non Current Assets | D19: 6482 | E19: 8062 | F19: 13968 | G19: ='Q - BS'!C18 -> 15292 | H19: ='Q - BS'!D18 -> 18145 | I19: ='Q - BS'!E18 -> 20444 | J19: ='Q - BS'!F18 -> 22220 | K19: 22220 | L19: ='Q - BS'!G18 -> 21752 | M19: ='Q - BS'!H18 -> 24657 | N19: ='Q - BS'!I18 -> 29782 | O19: ='Q - BS'!J18 -> 32054 | P19: 32054 | Q19: ='Q - BS'!K18 -> 31336 | R19: ='Q - BS'!L18 -> 33442 | S19: ='Q - BS'!M18 -> 27142 | T19: ='Q - BS'!N18 -> 25358 | U19: 25358 | V19: ='Q - BS'!O18 -> 28917 | W19: =V19 -> 28917 | X19: =W19 -> 28917 | Y19: =X19 -> 28917 | Z19: =Y19 -> 28917 | AA19: =Z19 -> 28917 | AB19: =AA19 -> 28917 | AC19: =AB19 -> 28917 | AD19: =AC19 -> 28917 | AE19: =AD19 -> 28917
A21: Liabilities | D21: =D23+D29 -> 97072 | E21: =E23+E29 -> 107633 | F21: =F23+F29 -> 109120 | G21: =G23+G29 -> 108597 | H21: =H23+H29 -> 115903 | I21: =I23+I29 -> 123509 | J21: =J23+J29 -> 119013 | K21: =K23+K29 -> 119013 | ... AE21: =AE23+AE29 -> 376721.27
A23: Current Liabilities | D23: =D24+D25+D26+D27 -> 56834 | E23: =E24+E25+E26+E27 -> 64254 | F23: =F24+F25+F26+F27 -> 69300 | G23: =G24+G25+G26+G27 -> 68854 | H23: =H24+H25+H26+H27 -> 77709 | I23: =I24+I25+I26+I27 -> 86295 | J23: =J24+J25+J26+J27 -> 81814 | K23: =K24+K25+K26+K27 -> 81814 | ... V23: =V24+V25+V26+V27 -> 111188 | W23: =SUM(W24:W27) -> 102309.29 | X23: =SUM(X24:X27) -> 115613.16 | Y23: =SUM(Y24:Y27) -> 131480.94 | Z23: =SUM(Z24:Z27) -> 131480.94 | AA23: =SUM(AA24:AA27) -> 135873.08 | AB23: =SUM(AB24:AB27) -> 158581.79 | AC23: =SUM(AC24:AC27) -> 179141.32 | AD23: =SUM(AD24:AD27) -> 200848.51 | AE23: =SUM(AE24:AE27) -> 220389.21
A24: Accounts Payable | D24: 5589 | E24: 6037 | F24: 5128 | G24: ='Q - BS'!C23 -> 4184 | H24: ='Q - BS'!D23 -> 5313 | I24: ='Q - BS'!E23 -> 5803 | J24: ='Q - BS'!F23 -> 7493 | K24: 7493 | L24: ='Q - BS'!G23 -> 6198 | M24: ='Q - BS'!H23 -> 6092 | N24: ='Q - BS'!I23 -> 7049 | O24: ='Q - BS'!J23 -> 7987 | P24: 7987 | Q24: ='Q - BS'!K23 -> 8497 | R24: ='Q - BS'!L23 -> 8347 | S24: ='Q - BS'!M23 -> 10546 | T24: ='Q - BS'!N23 -> 12200 | U24: 12200 | V24: ='Q - BS'!O23 -> 16852 | W24: =W64 -> 9264.8646 | X24: =X64 -> 10469.629 | Y24: =Y64 -> 11906.574 | Z24: =Z64 -> 11906.574 | AA24: =AA64 -> 12332.107 | AB24: =AB64 -> 14393.194 | AC24: =AC64 -> 16259.217 | AD24: =AD64 -> 18229.404 | AE24: =AE64 -> 20002.957
A25: Salary | D25: 11086 | E25: 13889 | F25: 14028 | G25: ='Q - BS'!C24 -> 9954 | H25: ='Q - BS'!D24 -> 11260 | I25: ='Q - BS'!E24 -> 12562 | J25: ='Q - BS'!F24 -> 15140 | K25: 15140 | L25: ='Q - BS'!G24 -> 9703 | M25: ='Q - BS'!H24 -> 11373 | N25: ='Q - BS'!I24 -> 12908 | O25: ='Q - BS'!J24 -> 15069 | P25: 15069 | Q25: ='Q - BS'!K24 -> 9984 | R25: ='Q - BS'!L24 -> 12168 | S25: ='Q - BS'!M24 -> 13944 | T25: ='Q - BS'!N24 -> 17546 | U25: 17546 | V25: ='Q - BS'!O24 -> 13947 | W25: =W58 -> 15832.395 | X25: =X58 -> 17891.173 | Y25: =Y58 -> 20346.718 | Z25: =Z58 -> 20346.718 | AA25: =AA58 -> 20766.995 | AB25: =AB58 -> 24237.819 | AC25: =AC58 -> 27380.16 | AD25: =AD58 -> 30697.911 | AE25: =AE58 -> 33684.534
A26: Accrued Revenue Share | D26: 7500 | E26: 8996 | F26: 8370 | G26: ='Q - BS'!C25 -> 7816 | H26: ='Q - BS'!D25 -> 7990 | I26: ='Q - BS'!E25 -> 8025 | J26: ='Q - BS'!F25 -> 8876 | K26: 8876 | L26: ='Q - BS'!G25 -> 8520 | M26: ='Q - BS'!H25 -> 8899 | N26: ='Q - BS'!I25 -> 9365 | O26: ='Q - BS'!J25 -> 9802 | P26: 9802 | Q26: ='Q - BS'!K25 -> 9965 | R26: ='Q - BS'!L25 -> 9787 | S26: ='Q - BS'!M25 -> 10081 | T26: ='Q - BS'!N25 -> 10864 | U26: 10864 | V26: ='Q - BS'!O25 -> 10208 | W26: =W61 -> 10951.218 | X26: =X61 -> 12375.268 | Y26: =Y61 -> 14073.761 | Z26: =Z61 -> 14073.761 | AA26: =AA61 -> 14576.748 | AB26: =AB61 -> 17012.985 | AC26: =AC61 -> 19218.654 | AD26: =AD61 -> 21547.447 | AE26: =AE61 -> 23643.814
A27: Other Current Liabilities | D27: 32659 | E27: 35332 | F27: 41774 | G27: ='Q - BS'!C26 -> 46900 | H27: ='Q - BS'!D26 -> 53146 | I27: ='Q - BS'!E26 -> 59905 | J27: ='Q - BS'!F26 -> 50305 | K27: 50305 | L27: ='Q - BS'!G26 -> 52576 | M27: ='Q - BS'!H26 -> 51549 | N27: ='Q - BS'!I26 -> 51481 | O27: ='Q - BS'!J26 -> 56264 | P27: 56264 | Q27: ='Q - BS'!K26 -> 63208 | R27: ='Q - BS'!L26 -> 57008 | S27: ='Q - BS'!M26 -> 64979 | T27: ='Q - BS'!N26 -> 62135 | U27: 62135 | V27: ='Q - BS'!O26 -> 70181 | W27: =W67 -> 66260.811 | X27: =X67 -> 74877.089 | Y27: =Y67 -> 85153.891 | Z27: =Z67 -> 85153.891 | AA27: =AA67 -> 88197.234 | AB27: =AB67 -> 102937.79 | AC27: =AC67 -> 116283.29 | AD27: =AD67 -> 130373.75 | AE27: =AE67 -> 143057.91
A29: Non Current Liabilities | D29: =D30+D31+D32+D33 -> 40238 | E29: =E30+E31+E32+E33 -> 43379 | F29: =F30+F31+F32+F33 -> 39820 | G29: =G30+G31+G32+G33 -> 39743 | H29: =H30+H31+H32+H33 -> 38194 | I29: =I30+I31+I32+I33 -> 37214 | J29: =J30+J31+J32+J33 -> 37199 | K29: =K30+K31+K32+K33 -> 37199 | ... V29: =V30+V31+V32+V33 -> 113985 | W29: =SUM(W30:W33) -> 117860.05 | X29: =SUM(X30:X33) -> 121928.85 | Y29: =SUM(Y30:Y33) -> 126201.1 | Z29: =SUM(Z30:Z33) -> 126201.1 | AA29: =SUM(AA30:AA33) -> 135172.8 | AB29: =SUM(AB30:AB33) -> 143067.91 | AC29: =SUM(AC30:AC33) -> 149462.94 | AD29: =SUM(AD30:AD33) -> 153982.1 | AE29: =SUM(AE30:AE33) -> 156332.06
A30: Long term Debt | D30: 13932 | E30: 14817 | F30: 14701 | G30: ='Q - BS'!C29 -> 13697 | H30: ='Q - BS'!D29 -> 13705 | I30: ='Q - BS'!E29 -> 13781 | J30: ='Q - BS'!F29 -> 13253 | K30: 13253 | L30: ='Q - BS'!G29 -> 13228 | M30: ='Q - BS'!H29 -> 13238 | N30: ='Q - BS'!I29 -> 12297 | O30: ='Q - BS'!J29 -> 10883 | P30: 10883 | Q30: ='Q - BS'!K29 -> 10886 | R30: ='Q - BS'!L29 -> 23607 | S30: ='Q - BS'!M29 -> 21607 | T30: ='Q - BS'!N29 -> 46547 | U30: 46547 | V30: ='Q - BS'!O29 -> 77501 | W30: ='Debt Schedule'!W12 -> 81376.05 | X30: ='Debt Schedule'!X12 -> 85444.853 | Y30: ='Debt Schedule'!Y12 -> 89717.095 | Z30: ='Debt Schedule'!Z12 -> 89717.095 | AA30: ='Debt Schedule'!AA12 -> 98688.805 | AB30: ='Debt Schedule'!AB12 -> 106583.91 | AC30: ='Debt Schedule'!AC12 -> 112978.94 | AD30: ='Debt Schedule'!AD12 -> 117498.1 | AE30: ='Debt Schedule'!AE12 -> 119848.06
A31: Lease | D31: 11146 | E31: 11389 | F31: 12501 | G31: ='Q - BS'!C30 -> 12799 | H31: ='Q - BS'!D30 -> 12746 | I31: ='Q - BS'!E30 -> 12550 | J31: ='Q - BS'!F30 -> 12460 | K31: 12460 | L31: ='Q - BS'!G30 -> 11957 | M31: ='Q - BS'!H30 -> 11708 | N31: ='Q - BS'!I30 -> 11654 | O31: ='Q - BS'!J30 -> 11691 | P31: 11691 | Q31: ='Q - BS'!K30 -> 11678 | R31: ='Q - BS'!L30 -> 11952 | S31: ='Q - BS'!M30 -> 12106 | T31: ='Q - BS'!N30 -> 12744 | U31: 12744 | V31: ='Q - BS'!O30 -> 12983 | W31: ='Debt Schedule'!W23 -> 12983 | X31: ='Debt Schedule'!X23 -> 12983 | Y31: ='Debt Schedule'!Y23 -> 12983 | Z31: ='Debt Schedule'!Z23 -> 12983 | AA31: ='Debt Schedule'!AA23 -> 12983 | AB31: ='Debt Schedule'!AB23 -> 12983 | AC31: ='Debt Schedule'!AC23 -> 12983 | AD31: ='Debt Schedule'!AD23 -> 12983 | AE31: ='Debt Schedule'!AE23 -> 12983
A32: Taxes | D32: 8849 | E32: 9176 | F32: 9258 | G32: ='Q - BS'!C31 -> 9722 | H32: ='Q - BS'!D31 -> 8753 | I32: ='Q - BS'!E31 -> 8038 | J32: ='Q - BS'!F31 -> 8474 | K32: 8474 | L32: ='Q - BS'!G31 -> 9234 | M32: ='Q - BS'!H31 -> 7703 | N32: ='Q - BS'!I31 -> 8219 | O32: ='Q - BS'!J31 -> 8782 | P32: 8782 | Q32: ='Q - BS'!K31 -> 9773 | R32: ='Q - BS'!L31 -> 10027 | S32: ='Q - BS'!M31 -> 10072 | T32: ='Q - BS'!N31 -> 9531 | U32: 9531 | V32: ='Q - BS'!O31 -> 12457 | W32: =V32 -> 12457 | X32: =W32 -> 12457 | Y32: =X32 -> 12457 | Z32: =Y32 -> 12457 | AA32: =Z32 -> 12457 | AB32: =AA32 -> 12457 | AC32: =AB32 -> 12457 | AD32: =AC32 -> 12457 | AE32: =AD32 -> 12457
A33: Other Non Current Liabilities | D33: 6311 | E33: 7997 | F33: 3360 | G33: ='Q - BS'!C32 -> 3525 | H33: ='Q - BS'!D32 -> 2990 | I33: ='Q - BS'!E32 -> 2845 | J33: ='Q - BS'!F32 -> 3012 | K33: 3012 | L33: ='Q - BS'!G32 -> 3090 | M33: ='Q - BS'!H32 -> 3455 | N33: ='Q - BS'!I32 -> 3174 | O33: ='Q - BS'!J32 -> 4694 | P33: 4694 | Q33: ='Q - BS'!K32 -> 6116 | R33: ='Q - BS'!L32 -> 6241 | S33: ='Q - BS'!M32 -> 6267 | T33: ='Q - BS'!N32 -> 8449 | U33: 8449 | V33: ='Q - BS'!O32 -> 11044 | W33: =V33 -> 11044 | X33: =W33 -> 11044 | Y33: =X33 -> 11044 | Z33: =Y33 -> 11044 | AA33: =Z33 -> 11044 | AB33: =AA33 -> 11044 | AC33: =AB33 -> 11044 | AD33: =AC33 -> 11044 | AE33: =AD33 -> 11044
A35: Equity | D35: =D36+D37 -> 222544 | E35: =E36+E37 -> 251635 | F35: =F36+F37 -> 256144 | G35: =G36+G37 -> 260894 | H35: =H36+H37 -> 267141 | I35: =I36+I37 -> 273202 | J35: =J36+J37 -> 283379 | K35: =K36+K37 -> 283379 | ... V35: =V36+V37 -> 478746 | W35: =SUM(W36:W38) -> 594780.76 | X35: =SUM(X36:X38) -> 629049.18 | Y35: =SUM(Y36:Y38) -> 670663.14 | Z35: =SUM(Z36:Z38) -> 670663.14 | AA35: =SUM(AA36:AA38) -> 816385.57 | AB35: =SUM(AB36:AB38) -> 979042.57 | AC35: =SUM(AC36:AC38) -> 1146792.1 | AD35: =SUM(AD36:AD38) -> 1317162.1 | AE35: =SUM(AE36:AE38) -> 1461100.6
A36: Share Capital | D36: 58510 | E36: 61774 | F36: 68184 | G36: ='Q - BS'!C35 -> 70269 | H36: ='Q - BS'!D35 -> 72248 | I36: ='Q - BS'!E35 -> 74591 | J36: ='Q - BS'!F35 -> 76534 | K36: 76534 | L36: ='Q - BS'!G35 -> 77913 | M36: ='Q - BS'!H35 -> 79732 | N36: ='Q - BS'!I35 -> 82030 | O36: ='Q - BS'!J35 -> 84800 | P36: 84800 | Q36: ='Q - BS'!K35 -> 86725 | R36: ='Q - BS'!L35 -> 89283 | S36: ='Q - BS'!M35 -> 91695 | T36: ='Q - BS'!N35 -> 93126 | U36: 93126 | V36: ='Q - BS'!O35 -> 96902 | W36: =V36+84750 -> 181652 | X36: =W36 -> 181652 | Y36: =X36 -> 181652 | Z36: =Y36 -> 181652 | AA36: =Z36 -> 181652 | AB36: =AA36 -> 181652 | AC36: =AB36 -> 181652 | AD36: =AC36 -> 181652 | AE36: =AD36 -> 181652
A37: Income Reserves | D37: 164034 | E37: 189861 | F37: 187960 | G37: ='Q - BS'!C36 -> 190625 | H37: ='Q - BS'!D36 -> 194893 | I37: ='Q - BS'!E36 -> 198611 | J37: ='Q - BS'!F36 -> 206845 | K37: 206845 | L37: ='Q - BS'!G36 -> 214931 | M37: ='Q - BS'!H36 -> 221021 | N37: ='Q - BS'!I36 -> 232089 | O37: ='Q - BS'!J36 -> 240284 | P37: 240284 | Q37: ='Q - BS'!K36 -> 258542 | R37: ='Q - BS'!L36 -> 273633 | S37: ='Q - BS'!M36 -> 295172 | T37: ='Q - BS'!N36 -> 322139 | U37: 322139 | V37: ='Q - BS'!O36 -> 381844 | W37: =V37+'Income Statement'!AA35 -> 409730.97 | X37: =W37+'Income Statement'!AB35 -> 440165.96 | Y37: =X37+'Income Statement'!AC35 -> 477418.39 | Z37: =Y37 -> 477418.39 | AA37: =Z37+'Income Statement'!AE35 -> 605146.27 | AB37: =AA37+'Income Statement'!AF35 -> 746486.21 | AC37: =AB37+'Income Statement'!AG35 -> 889758.93 | AD37: =AC37+'Income Statement'!AH35 -> 1032578.6 | AE37: =AD37+'Income Statement'!AI35 -> 1146155.6 | AG37: =BS!Z30+BS!Z31-BS!Y30-BS!Y31 -> 0
A38: SBC | W38: ='CFS - Estimates'!W11+'CFS - Estimates'!W25 -> 3397.7932 | X38: =W38+'CFS - Estimates'!X11+'CFS - Estimates'!X25 -> 7231.219 | Y38: =X38+'CFS - Estimates'!Y11+'CFS - Estimates'!Y25 -> 11592.749 | Z38: =Y38 -> 11592.749 | AA38: =Z38+'CFS - Estimates'!AA11+'CFS - Estimates'!AA25 -> 29587.306 | AB38: =AA38+'CFS - Estimates'!AB11+'CFS - Estimates'!AB25 -> 50904.357 | AC38: =AB38+'CFS - Estimates'!AC11+'CFS - Estimates'!AC25 -> 75381.128 | AD38: =AC38+'CFS - Estimates'!AD11+'CFS - Estimates'!AD25 -> 102931.48 | AE38: =AD38+'CFS - Estimates'!AE11+'CFS - Estimates'!AE25 -> 133292.96
A40: Liabilities+Equity | D40: =D35+D21 -> 319616 | E40: =E35+E21 -> 359268 | F40: =F35+F21 -> 365264 | G40: =G35+G21 -> 369491 | H40: =H35+H21 -> 383044 | I40: =I35+I21 -> 396711 | J40: =J35+J21 -> 402392 | K40: =K35+K21 -> 402392 | ... AE40: =AE35+AE21 -> 1837821.8
A42: OWC | D42: =D11+D12-D24-D25-D26-D27 -> -19232 | E42: =E11+E12-E24-E25-E26-E27 -> -15760 | F42: =F11+F12-F24-F25-F26-F27 -> -18267 | G42: ='Q - BS'!C40 -> -21971 | H42: ='Q - BS'!D40 -> -27253 | I42: ='Q - BS'!E40 -> -29920 | J42: ='Q - BS'!F40 -> -21200 | K42: =K11+K12-K24-K25-K26-K27 -> -21200 | L42: ='Q - BS'!G40 -> -19616 | M42: ='Q - BS'!H40 -> -16643 | N42: ='Q - BS'!I40 -> -16492 | O42: ='Q - BS'!J40 -> -21068 | P42: =P11+P12-P24-P25-P26-P27 -> -21068 | Q42: =Q11+Q12-Q24-Q25-Q26-Q27 -> -24930 | R42: =R11+R12-R24-R25-R26-R27 -> -16242 | S42: =S11+S12-S24-S25-S26-S27 -> -24099 | T42: =T11+T12-T24-T25-T26-T27 -> -23550 | U42: =U11+U12-U24-U25-U26-U27 -> -23550 | V42: =V11+V12-V24-V25-V26-V27 -> -24275 | W42: =W50+W53-W58-W61-W64-W67 -> -16109.364 | X42: =X50+X53-X58-X61-X64-X67 -> -18361.503 | Y42: =Y50+Y53-Y58-Y61-Y64-Y67 -> -20831.611 | Z42: =Z50+Z53-Z58-Z61-Z64-Z67 -> -20831.611 | AA42: =AA50+AA53-AA58-AA61-AA64-AA67 -> -21745.371 | AB42: =AB50+AB53-AB58-AB61-AB64-AB67 -> -23381.672 | AC42: =AC50+AC53-AC58-AC61-AC64-AC67 -> -23901.159 | AD42: =AD50+AD53-AD58-AD61-AD64-AD67 -> -26114.637 | AE42: =AE50+AE53-AE58-AE61-AE64-AE67 -> -27826.17
A43: Δ OWC | E43: =E42-D42 -> 3472 | F43: =F42-E42 -> -2507 | G43: ='Q - BS'!C41 -> -3704 | H43: ='Q - BS'!D41 -> -5282 | I43: ='Q - BS'!E41 -> -2667 | J43: ='Q - BS'!F41 -> 8720 | K43: =K42-F42 -> -2933 | L43: ='Q - BS'!G41 -> 1584 | M43: ='Q - BS'!H41 -> 2973 | N43: ='Q - BS'!I41 -> 151 | O43: ='Q - BS'!J41 -> -4576 | P43: =P42-K42 -> 132 | Q43: ='Q - BS'!K41 -> -3862 | R43: ='Q - BS'!L41 -> 8688 | S43: ='Q - BS'!M41 -> -7857 | T43: ='Q - BS'!N41 -> 549 | U43: =U42-P42 -> -2482 | V43: ='Q - BS'!O41 -> -725 | W43: =W42-V42 -> 8165.6362 | X43: =X42-W42 -> -2252.1392 | Y43: =Y42-X42 -> -2470.1081 | Z43: =SUM(V43:Y43) -> 2718.389 | AA43: =AA42-Z42 -> -913.76001 | AB43: =AB42-AA42 -> -1636.3012 | AC43: =AC42-AB42 -> -519.48722 | AD43: =AD42-AC42 -> -2213.4781 | AE43: =AE42-AD42 -> -1711.5321
A45: Revenue | D45: ='Income Statement'!D6 -> 182527 | E45: ='Income Statement'!E6 -> 257637 | F45: ='Income Statement'!J6 -> 282836 | G45: ='Income Statement'!K6 -> 69787 | H45: ='Income Statement'!L6 -> 74604 | I45: ='Income Statement'!M6 -> 76693 | J45: ='Income Statement'!N6 -> 86310 | K45: ='Income Statement'!O6 -> 307394 | L45: ='Income Statement'!P6 -> 80539 | M45: ='Income Statement'!Q6 -> 84742 | ... AE45: ='Income Statement'!AI6 -> 1067907.9
A46: COGS | D46: ='Income Statement'!D8 -> 84732 | E46: ='Income Statement'!E8 -> 110939 | F46: ='Income Statement'!J8 -> 126203 | G46: ='Income Statement'!K8 -> 30612 | H46: ='Income Statement'!L8 -> 31916 | I46: ='Income Statement'!M8 -> 33229 | J46: ='Income Statement'!N8 -> 37575 | K46: ='Income Statement'!O8 -> 133332 | L46: ='Income Statement'!P8 -> 33712 | M46: ='Income Statement'!Q8 -> 35507 | ... AE46: ='Income Statement'!AI8 -> 374216.09
A47: SG&A | D47: ='Income Statement'!D12 -> 56571 | E47: ='Income Statement'!E12 -> 67984 | F47: ='Income Statement'!J12 -> 81791 | G47: ='Income Statement'!K12 -> 21760 | H47: ='Income Statement'!L12 -> 20850 | I47: ='Income Statement'!M12 -> 22121 | J47: ='Income Statement'!N12 -> 25038 | K47: ='Income Statement'!O12 -> 89769 | L47: ='Income Statement'!P12 -> 21355 | M47: ='Income Statement'!Q12 -> 21810 | ... AE47: ='Income Statement'!AI12 -> 258387.3
A48: Days | D48: =IF(ISNUMBER(D5),360,90) -> 360 | E48: =IF(ISNUMBER(E5),360,90) -> 360 | F48: =IF(ISNUMBER(F5),360,90) -> 360 | G48: =IF(ISNUMBER(G5),360,90) -> 90 | H48: =IF(ISNUMBER(H5),360,90) -> 90 | I48: =IF(ISNUMBER(I5),360,90) -> 90 | J48: =IF(ISNUMBER(J5),360,90) -> 90 | K48: =IF(ISNUMBER(K5),360,90) -> 360 | ... AE48: =IF(ISNUMBER(AE5),360,90) -> 360
A49: Current Assets
A50: Accounts Receivible | D50: =D11 -> 30930 | E50: =E11 -> 39304 | F50: =F11 -> 40258 | G50: =G11 -> 36036 | H50: =H11 -> 38804 | I50: =I11 -> 41020 | J50: =J11 -> 47964 | K50: =K11 -> 47964 | ... V50: =V11 -> 62999 | W50: =W51*W$45/W48 -> 66732.58 | X50: =X51*X$45/X48 -> 75288.394 | Y50: =Y51*Y$45/Y48 -> 85660.347 | Z50: =Y50 -> 85660.347 | AA50: =AA51*AA$45/AA48 -> 88353.171 | AB50: =AB51*AB$45/AB48 -> 104666.6 | AC50: =AC51*AC$45/AC48 -> 120180.8 | AD50: =AD51*AD$45/AD48 -> 135272.07 | AE50: =AE51*AE$45/AE48 -> 149074.71
B51: Days Of Revenue | D51: =(D50/D$45)*360 -> 61.003578 | E51: =(E50/E$45)*360 -> 54.920062 | F51: =(F50/F$45)*360 -> 51.241285 | G51: =(G50/G$45)*90 -> 46.473412 | H51: =(H50/H$45)*90 -> 46.811967 | I51: =(I50/I$45)*90 -> 48.137379 | J51: =(J50/J$45)*90 -> 50.014599 | K51: =(K50/K$45)*360 -> 56.172339 | L51: =(L50/L$45)*90 -> 49.78557 | M51: =(M50/M$45)*90 -> 50.008614 | N51: =(N50/N$45)*90 -> 50.067522 | O51: =(O50/O$45)*90 -> 48.830194 | P51: =(P50/P$45)*360 -> 53.83266 | Q51: =(Q50/Q$45)*90 -> 50.867744 | R51: =(R50/R$45)*90 -> 51.378438 | S51: =(S50/S$45)*90 -> 50.254236 | T51: =(T50/T$45)*90 -> 49.721861 | U51: =(U50/U$45)*360 -> 56.198949 | V51: =(V50/V$45)*90 -> 51.593416 | W51: =MEDIAN(D51:V51) -> 50.254236 | X51: =W51 -> 50.254236 | Y51: =X51 -> 50.254236 | AA51: =W51 -> 50.254236 | AB51: =X51 -> 50.254236 | AC51: =Y51 -> 50.254236 | AD51: =W51 -> 50.254236 | AE51: =AA51 -> 50.254236
A53: Others Assets | D53: =D12 -> 6672 | E53: =E12 -> 9190 | F53: =F12 -> 10775 | G53: =G12 -> 10847 | H53: =H12 -> 11652 | I53: =I12 -> 15355 | J53: =J12 -> 12650 | K53: =K12 -> 12650 | ... V53: =V12 -> 23914 | W53: =W54*W$45/W48 -> 19467.345 | X53: =X54*X$45/X48 -> 21963.262 | Y53: =Y54*Y$45/Y48 -> 24988.986 | Z53: =Y53 -> 24988.986 | AA53: =AA54*AA$45/AA48 -> 25774.542 | AB53: =AB54*AB$45/AB48 -> 30533.523 | AC53: =AC54*AC$45/AC48 -> 35059.354 | AD53: =AD54*AD$45/AD48 -> 39461.804 | AE53: =AE54*AE$45/AE48 -> 43488.334
B54: Days Of Revenue | D54: =(D53/D$45)*360 -> 13.159259 | E54: =(E53/E$45)*360 -> 12.841323 | F54: =(F53/F$45)*360 -> 13.714661 | G54: =(G53/G$45)*90 -> 13.988708 | H54: =(H53/H$45)*90 -> 14.056619 | I54: =(I53/I$45)*90 -> 18.019246 | J54: =(J53/J$45)*90 -> 13.190824 | K54: =(K53/K$45)*360 -> 14.814863 | L54: =(L53/L$45)*90 -> 14.336036 | M54: =(M53/M$45)*90 -> 15.063015 | N54: =(N53/N$45)*90 -> 15.505393 | O54: =(O53/O$45)*90 -> 14.660254 | P54: =(P53/P$45)*360 -> 16.16214 | Q54: =(Q53/Q$45)*90 -> 15.683224 | R54: =(R53/R$45)*90 -> 14.952089 | S54: =(S53/S$45)*90 -> 16.095109 | T54: =(T53/T$45)*90 -> 12.894982 | U54: =(U53/U$45)*360 -> 14.574765 | V54: =(V53/V$45)*90 -> 19.584516 | W54: =MEDIAN(D54:V54) -> 14.660254 | X54: =W54 -> 14.660254 | Y54: =X54 -> 14.660254 | AA54: =W54 -> 14.660254 | AB54: =X54 -> 14.660254 | AC54: =Y54 -> 14.660254 | AD54: =W54 -> 14.660254 | AE54: =AA54 -> 14.660254
A57: Current Liabilities
A58: Salary | D58: =D25 -> 11086 | E58: =E25 -> 13889 | F58: =F25 -> 14028 | G58: =G25 -> 9954 | H58: =H25 -> 11260 | I58: =I25 -> 12562 | J58: =J25 -> 15140 | K58: =K25 -> 15140 | ... V58: =V25 -> 13947 | W58: =W59*W47/W48 -> 15832.395 | X58: =X59*X47/X48 -> 17891.173 | Y58: =Y59*Y47/Y48 -> 20346.718 | Z58: =Y58 -> 20346.718 | AA58: =AA59*AA47/AA48 -> 20766.995 | AB58: =AB59*AB47/AB48 -> 24237.819 | AC58: =AC59*AC47/AC48 -> 27380.16 | AD58: =AD59*AD47/AD48 -> 30697.911 | AE58: =AE59*AE47/AE48 -> 33684.534
B59: Days Of SG&A | D59: =(D58/D47)*360 -> 70.547807 | E59: =(E58/E47)*360 -> 73.547305 | F59: =(F58/F47)*360 -> 61.743713 | G59: =(G58/G$46)*90 -> 29.264994 | H59: =(H58/H$46)*90 -> 31.752099 | I59: =(I58/I$46)*90 -> 34.023895 | J59: =(J58/J$46)*90 -> 36.263473 | K59: =(K58/K47)*360 -> 60.715837 | L59: =(L58/L47)*90 -> 40.892999 | M59: =(M58/M47)*90 -> 46.931224 | N59: =(N58/N47)*90 -> 49.917071 | O59: =(O58/O47)*90 -> 54.501286 | P59: =(P58/P47)*360 -> 59.40343 | Q59: =(Q58/Q47)*90 -> 38.619504 | R59: =(R58/R47)*90 -> 41.929704 | S59: =(S58/S47)*90 -> 42.184947 | T59: =(T58/T47)*90 -> 49.151519 | U59: =(U58/U47)*360 -> 56.771944 | V59: =(V58/V47)*90 -> 43.390024 | W59: =MEDIAN(D59:V59) -> 46.931224 | X59: =W59 -> 46.931224 | Y59: =X59 -> 46.931224 | AA59: =W59 -> 46.931224 | AB59: =X59 -> 46.931224 | AC59: =Y59 -> 46.931224 | AD59: =W59 -> 46.931224 | AE59: =AA59 -> 46.931224
A61: Accrued Revunue Shares | D61: =D26 -> 7500 | E61: =E26 -> 8996 | F61: =F26 -> 8370 | G61: =G26 -> 7816 | H61: =H26 -> 7990 | I61: =I26 -> 8025 | J61: =J26 -> 8876 | K61: =K26 -> 8876 | ... V61: =V26 -> 10208 | W61: =W$46*W62/W48 -> 10951.218 | X61: =X$46*X62/X48 -> 12375.268 | Y61: =Y$46*Y62/Y48 -> 14073.761 | Z61: =Y61 -> 14073.761 | AA61: =AA$46*AA62/AA48 -> 14576.748 | AB61: =AB$46*AB62/AB48 -> 17012.985 | AC61: =AC$46*AC62/AC48 -> 19218.654 | AD61: =AD$46*AD62/AD48 -> 21547.447 | AE61: =AE$46*AE62/AE48 -> 23643.814
B62: Days Of COGS | D62: =(D61/D$46)*360 -> 31.865175 | E62: =(E61/E$46)*360 -> 29.192259 | F62: =(F61/F$46)*360 -> 23.875819 | G62: =(G61/G$46)*90 -> 22.979224 | H62: =(H61/H$46)*90 -> 22.531019 | I62: =(I61/I$46)*90 -> 21.735532 | J62: =(J61/J$46)*90 -> 21.25988 | K62: =(K61/K$46)*360 -> 23.96544 | L62: =(L61/L$46)*90 -> 22.74561 | M62: =(M61/M$46)*90 -> 22.556397 | N62: =(N61/N$46)*90 -> 23.108241 | O62: =(O61/O$46)*90 -> 21.721616 | P62: =(P61/P$46)*360 -> 24.118765 | Q62: =(Q61/Q$46)*90 -> 24.665163 | R62: =(R61/R$46)*90 -> 22.562822 | S62: =(S61/S$46)*90 -> 21.93164 | T62: =(T61/T$46)*90 -> 21.364332 | U62: =(U61/U$46)*360 -> 24.062756 | V62: =(V61/V$46)*90 -> 22.260667 | W62: =MEDIAN(D62:V62) -> 22.74561 | X62: =W62 -> 22.74561 | Y62: =X62 -> 22.74561 | AA62: =W62 -> 22.74561 | AB62: =X62 -> 22.74561 | AC62: =Y62 -> 22.74561 | AD62: =W62 -> 22.74561 | AE62: =AA62 -> 22.74561
A64: Accounts Payable | D64: =D24 -> 5589 | E64: =E24 -> 6037 | F64: =F24 -> 5128 | G64: =G24 -> 4184 | H64: =H24 -> 5313 | I64: =I24 -> 5803 | J64: =J24 -> 7493 | K64: =K24 -> 7493 | ... V64: =V24 -> 16852 | W64: =W$46*W65/W$48 -> 9264.8646 | X64: =X$46*X65/X$48 -> 10469.629 | Y64: =Y$46*Y65/Y$48 -> 11906.574 | Z64: =Y64 -> 11906.574 | AA64: =AA$46*AA65/AA$48 -> 12332.107 | AB64: =AB$46*AB65/AB$48 -> 14393.194 | AC64: =AC$46*AC65/AC$48 -> 16259.217 | AD64: =AD$46*AD65/AD$48 -> 18229.404 | AE64: =AE$46*AE65/AE$48 -> 20002.957
B65: Days Of COGS | D65: =(D64/D$46)*360 -> 23.745928 | E65: =(E64/E$46)*360 -> 19.590225 | F65: =(F64/F$46)*360 -> 14.627861 | G65: =(G64/G$46)*90 -> 12.301058 | H65: =(H64/H$46)*90 -> 14.982141 | I65: =(I64/I$46)*90 -> 15.717295 | J65: =(J64/J$46)*90 -> 17.947305 | K65: =(K64/K$46)*360 -> 20.231302 | L65: =(L64/L$46)*90 -> 16.54663 | M65: =(M64/M$46)*90 -> 15.441462 | N65: =(N64/N$46)*90 -> 17.393486 | O65: =(O64/O$46)*90 -> 17.699505 | P65: =(P64/P$46)*360 -> 19.652783 | Q65: =(Q64/Q$46)*90 -> 21.0316 | R65: =(R64/R$46)*90 -> 19.243065 | S65: =(S64/S$46)*90 -> 22.943267 | T65: =(T64/T$46)*90 -> 23.991609 | U65: =(U64/U$46)*360 -> 27.021872 | V65: =(V64/V$46)*90 -> 36.749291 | W65: =MEDIAN(D65:V65) -> 19.243065 | X65: =W65 -> 19.243065 | Y65: =X65 -> 19.243065 | AA65: =W65 -> 19.243065 | AB65: =X65 -> 19.243065 | AC65: =Y65 -> 19.243065 | AD65: =W65 -> 19.243065 | AE65: =AA65 -> 19.243065
A67: Others | D67: =D27 -> 32659 | E67: =E27 -> 35332 | F67: =F27 -> 41774 | G67: =G27 -> 46900 | H67: =H27 -> 53146 | I67: =I27 -> 59905 | J67: =J27 -> 50305 | K67: =K27 -> 50305 | ... V67: =V27 -> 70181 | W67: =W$46*W68/W$48 -> 66260.811 | X67: =X$46*X68/X$48 -> 74877.089 | Y67: =Y$46*Y68/Y$48 -> 85153.891 | Z67: =Y67 -> 85153.891 | AA67: =AA$46*AA68/AA$48 -> 88197.234 | AB67: =AB$46*AB68/AB$48 -> 102937.79 | AC67: =AC$46*AC68/AC$48 -> 116283.29 | AD67: =AD$46*AD68/AD$48 -> 130373.75 | AE67: =AE$46*AE68/AE$48 -> 143057.91
B68: Days Of COGS | D68: =(D67/D$46)*360 -> 138.75797 | E68: =(E67/E$46)*360 -> 114.65328 | F68: =(F67/F$46)*360 -> 119.1623 | G68: =(G67/G$46)*90 -> 137.8871 | H68: =(H67/H$46)*90 -> 149.86652 | I68: =(I67/I$46)*90 -> 162.25135 | J68: =(J67/J$46)*90 -> 120.49102 | K68: =(K67/K$46)*360 -> 135.82486 | L68: =(L67/L$46)*90 -> 140.3607 | M68: =(M67/M$46)*90 -> 130.66184 | N68: =(N67/N$46)*90 -> 127.02994 | O68: =(O67/O$46)*90 -> 124.68323 | P68: =(P67/P$46)*360 -> 138.44299 | Q68: =(Q67/Q$46)*90 -> 156.45114 | R68: =(R67/R$46)*90 -> 131.4255 | S68: =(S67/S$46)*90 -> 141.36455 | T68: =(T67/T$46)*90 -> 122.19005 | U68: =(U67/U$46)*360 -> 137.62328 | V68: =(V67/V$46)*90 -> 153.04427 | W68: =MEDIAN(D68:V68) -> 137.62328 | X68: =W68 -> 137.62328 | Y68: =X68 -> 137.62328 | AA68: =W68 -> 137.62328 | AB68: =X68 -> 137.62328 | AC68: =Y68 -> 137.62328 | AD68: =W68 -> 137.62328 | AE68: =AA68 -> 137.62328

Sheet Comps
E1: Hardcode
E2: Formula
E3: Assumption
B5: COMPARABLE COMPANY ANALYSIS | S5: Tabela Auxiliar
B6: Trading Multiples | F6: P/E | J6: EV/SALES | N6: EV/EBITDA | S6: {=F9:H15} -> 19.01 | T6: 17.82 | U6: 15.19 | W6: {=J9:L15} -> 6.2 | X6: 5.17 | Y6: 4.4 | AA6: {=N9:P15} -> 10.99 | AB6: 9.01 | AC6: 7.31
S7: 27.29 | T7: 23.58 | U7: 18.43 | W7: 3.2 | X7: 2.83 | Y7: 2.48 | AA7: 12.41 | AB7: 9.76 | AC7: 7.7
C8: Company | F8: FY26 | G8: FY27 | H8: FY28 | J8: FY26 | K8: FY27 | L8: FY28 | N8: FY26 | O8: FY27 | P8: FY28 | S8: 7.01 | T8: 5.91 | U8: 4.86 | W8: 1.23 | X8: 1.12 | Y8: 1.03 | AA8: 6.55 | AB8: 5.28 | AC8: 4.85
C9: Meta Platforms | F9: ='Multiplos base'!O8 -> 19.01 | G9: ='Multiplos base'!P8 -> 17.82 | H9: ='Multiplos base'!Q8 -> 15.19 | J9: ='Multiplos base'!K8 -> 6.2 | K9: ='Multiplos base'!L8 -> 5.17 | L9: ='Multiplos base'!M8 -> 4.4 | N9: ='Multiplos base'!G8 -> 10.99 | O9: ='Multiplos base'!H8 -> 9.01 | P9: ='Multiplos base'!I8 -> 7.31 | S9: 19.1 | T9: 17.92 | U9: 14.97 | W9: 5.67 | X9: 5.09 | Y9: 4.62 | AA9: 17 | AB9: 14.44 | AC9: 12.49
C10: Amazon.com | F10: ='Multiplos base'!O9 -> 27.29 | G10: ='Multiplos base'!P9 -> 23.58 | H10: ='Multiplos base'!Q9 -> 18.43 | J10: ='Multiplos base'!K9 -> 3.2 | K10: ='Multiplos base'!L9 -> 2.83 | L10: ='Multiplos base'!M9 -> 2.48 | N10: ='Multiplos base'!G9 -> 12.41 | O10: ='Multiplos base'!H9 -> 9.76 | P10: ='Multiplos base'!I9 -> 7.7 | S10: 18.15 | T10: 16.61 | U10: 14.87 | W10: 4.29 | X10: 4.07 | Y10: 3.88 | AA10: 14.09 | AB10: 13 | AC10: 12.01
C11: Snap | F11: ='Multiplos base'!O10 -> 7.01 | G11: ='Multiplos base'!P10 -> 5.91 | H11: ='Multiplos base'!Q10 -> 4.86 | J11: ='Multiplos base'!K10 -> 1.23 | K11: ='Multiplos base'!L10 -> 1.12 | L11: ='Multiplos base'!M10 -> 1.03 | N11: ='Multiplos base'!G10 -> 6.55 | O11: ='Multiplos base'!H10 -> 5.28 | P11: ='Multiplos base'!I10 -> 4.85 | S11: 23.14 | T11: 20.09 | U11: 17.09 | W11: 8.88 | X11: 7.61 | Y11: 6.41 | AA11: 14.79 | AB11: 12.3 | AC11: 9.98
C12: Netflix | F12: ='Multiplos base'!O11 -> 19.1 | G12: ='Multiplos base'!P11 -> 17.92 | H12: ='Multiplos base'!Q11 -> 14.97 | J12: ='Multiplos base'!K11 -> 5.67 | K12: ='Multiplos base'!L11 -> 5.09 | L12: ='Multiplos base'!M11 -> 4.62 | N12: ='Multiplos base'!G11 -> 17 | O12: ='Multiplos base'!H11 -> 14.44 | P12: ='Multiplos base'!I11 -> 12.49 | S12: 36.99 | T12: 33.33 | U12: 29.98 | W12: 10.05 | X12: 9.18 | Y12: 8.57 | AA12: 28.33 | AB12: 26.06 | AC12: 23.81
C13: eBay | F13: ='Multiplos base'!O12 -> 18.15 | G13: ='Multiplos base'!P12 -> 16.61 | H13: ='Multiplos base'!Q12 -> 14.87 | J13: ='Multiplos base'!K12 -> 4.29 | K13: ='Multiplos base'!L12 -> 4.07 | L13: ='Multiplos base'!M12 -> 3.88 | N13: ='Multiplos base'!G12 -> 14.09 | O13: ='Multiplos base'!H12 -> 13 | P13: ='Multiplos base'!I12 -> 12.01
C14: Microsoft | F14: ='Multiplos base'!O13 -> 23.14 | G14: ='Multiplos base'!P13 -> 20.09 | H14: ='Multiplos base'!Q13 -> 17.09 | J14: ='Multiplos base'!K13 -> 8.88 | K14: ='Multiplos base'!L13 -> 7.61 | L14: ='Multiplos base'!M13 -> 6.41 | N14: ='Multiplos base'!G13 -> 14.79 | O14: ='Multiplos base'!H13 -> 12.3 | P14: ='Multiplos base'!I13 -> 9.98
C15: Apple | F15: ='Multiplos base'!O14 -> 36.99 | G15: ='Multiplos base'!P14 -> 33.33 | H15: ='Multiplos base'!Q14 -> 29.98 | J15: ='Multiplos base'!K14 -> 10.05 | K15: ='Multiplos base'!L14 -> 9.18 | L15: ='Multiplos base'!M14 -> 8.57 | N15: ='Multiplos base'!G14 -> 28.33 | O15: ='Multiplos base'!H14 -> 26.06 | P15: ='Multiplos base'!I14 -> 23.81
B19: TRADING MULTIPLES STATISTICS
G20: P/E | K20: EV/SALES | O20: EV/EBITDA
G21: FY26 | H21: FY27 | I21: FY28 | K21: FY26 | L21: FY27 | M21: FY28 | O21: FY26 | P21: FY27 | Q21: FY28
C22: Minimum | G22: =MIN(F9:F15) -> 7.01 | H22: =MIN(G9:G15) -> 5.91 | I22: =MIN(H9:H15) -> 4.86 | K22: =MIN(J9:J15) -> 1.23 | L22: =MIN(K9:K15) -> 1.12 | M22: =MIN(L9:L15) -> 1.03 | O22: =MIN(N9:N15) -> 6.55 | P22: =MIN(O9:O15) -> 5.28 | Q22: =MIN(P9:P15) -> 4.85 | T22: Implied Share Price
C23: Valuation | G23: =G22*G$50 -> 1395781 | H23: =H22*H$50 -> 1161341.1 | I23: =I22*I$50 -> 1144853.6 | K23: =K22*K$50-K$52 -> 850461.36 | L23: =L22*L$50-L$52 -> 922628.54 | M23: =M22*M$50-M$52 -> 986033.65 | O23: =O22*O$50-O$52 -> 1672061.8 | P23: =P22*P$50-P$52 -> 1651009.4 | Q23: =Q22*Q$50-Q$52 -> 1811036.9 | T23: Metric | V23: Share Price
T24: Minimum
C25: 25th percentile | G25: =_xlfn.QUARTILE.INC(F9:F15,1) -> 18.58 | H25: =_xlfn.QUARTILE.INC(G9:G15,1) -> 17.215 | I25: =_xlfn.QUARTILE.INC(H9:H15,1) -> 14.92 | K25: =_xlfn.QUARTILE.INC(J9:J15,1) -> 3.745 | L25: =_xlfn.QUARTILE.INC(K9:K15,1) -> 3.45 | M25: =_xlfn.QUARTILE.INC(L9:L15,1) -> 3.18 | O25: =_xlfn.QUARTILE.INC(N9:N15,1) -> 11.7 | P25: =_xlfn.QUARTILE.INC(O9:O15,1) -> 9.385 | Q25: =_xlfn.QUARTILE.INC(P9:P15,1) -> 7.505 | T25: 25th Percentile | V25: =AVERAGE(G27:I27,K27:M27,O27:Q27) -> 236.37031
C26: Valuation | G26: =G25*G$50 -> 3699516.6 | H26: =H25*H$50 -> 3382823.7 | I26: =I25*I$50 -> 3514653.4 | K26: =K25*K$50-K$52 -> 2152348.8 | L26: =L25*L$50-L$52 -> 2397342.8 | M26: =M25*M$50-M$52 -> 2598075.8 | O26: =O25*O$50-O$52 -> 2818671 | P26: =P25*P$50-P$52 -> 2768421.8 | Q26: =Q25*Q$50-Q$52 -> 2685426.3 | T26: Median | V26: =AVERAGE(G32:I32,K32:M32,O32:Q32) -> 285.39001
C27: Share Price | G27: =G26/G$51 -> 302.49523 | H27: =H26/H$51 -> 276.60046 | I27: =I26/I$51 -> 287.37967 | K27: =K26/K$51 -> 175.98927 | L27: =L26/L$51 -> 196.02149 | M27: =M26/M$51 -> 212.43465 | O27: =O26/O$51 -> 230.47187 | P27: =P26/P$51 -> 226.36319 | Q27: =Q26/Q$51 -> 219.57697 | T27: Average | V27: =AVERAGE(G36:I36,K36:M36,O36:Q36) -> 301.52126
T28: 75th Percentile | V28: =AVERAGE(G41:I41,K41:M41,O41:Q41) -> 346.76108
T29: Maximum
C30: Median | G30: =_xlfn.QUARTILE.INC(F9:F15,2) -> 19.1 | H30: =_xlfn.QUARTILE.INC(G9:G15,2) -> 17.92 | I30: =_xlfn.QUARTILE.INC(H9:H15,2) -> 15.19 | K30: =_xlfn.QUARTILE.INC(J9:J15,2) -> 5.67 | L30: =_xlfn.QUARTILE.INC(K9:K15,2) -> 5.09 | M30: =_xlfn.QUARTILE.INC(L9:L15,2) -> 4.4 | O30: =_xlfn.QUARTILE.INC(N9:N15,2) -> 14.09 | P30: =_xlfn.QUARTILE.INC(O9:O15,2) -> 12.3 | Q30: =_xlfn.QUARTILE.INC(P9:P15,2) -> 9.98
C31: Valuation | G31: =G30*G$50 -> 3803055.3 | H31: =H30*H$50 -> 3521359.3 | I31: =I30*I$50 -> 3578256.4 | K31: =K30*K$50-K$52 -> 3148823.2 | L31: =L30*L$50-L$52 -> 3435339.2 | M31: =M30*M$50-M$52 -> 3512816 | O31: =O30*O$50-O$52 -> 3350786.8 | P31: =P30*P$50-P$52 -> 3561907.1 | Q31: =Q30*Q$50-Q$52 -> 3500535.1
C32: Share Price | G32: =G31/G$51 -> 310.96119 | H32: =H31/H$51 -> 287.92799 | I32: =I31/I$51 -> 292.58024 | K32: =K31/K$51 -> 257.46715 | L32: =L31/L$51 -> 280.89445 | M32: =M31/M$51 -> 287.22943 | O32: =O31/O$51 -> 273.98093 | P32: =P31/P$51 -> 291.24343 | Q32: =Q31/Q$51 -> 286.22527
T33: Valuation Range
C34: Average | G34: =AVERAGE(F9:F15) -> 21.527143 | H34: =AVERAGE(G9:G15) -> 19.322857 | I34: =AVERAGE(H9:H15) -> 16.484286 | K34: =AVERAGE(J9:J15) -> 5.6457143 | L34: =AVERAGE(K9:K15) -> 5.01 | M34: =AVERAGE(L9:L15) -> 4.4842857 | O34: =AVERAGE(N9:N15) -> 14.88 | P34: =AVERAGE(O9:O15) -> 12.835714 | Q34: =AVERAGE(P9:P15) -> 11.164286 | T34: Low | U34: =MIN(K27:M27,G27,H27,I27,O27,P27,Q27,Q32,P32,O32,M32,L32,K32,I32,H32,G32,G36,H36,I36,K36,L36,M36,O36,P36,Q36,G41,H41,I41,K41,L41,M41,O41,P41,Q41) -> 175.98927
C35: Valuation | G35: =G34*G$50 -> 4286330.6 | H35: =H34*H$50 -> 3797026.9 | I35: =I34*I$50 -> 3883146.8 | K35: =K34*K$50-K$52 -> 3136251.8 | L35: =L34*L$50-L$52 -> 3384705.2 | M35: =M34*M$50-M$52 -> 3576012.3 | O35: =O34*O$50-O$52 -> 3526674.4 | P35: =P34*P$50-P$52 -> 3707732.7 | Q35: =Q34*Q$50-Q$52 -> 3890564 | T35: Mid | U35: =MEDIAN(K27:M27,G27,H27,I27,O27,P27,Q27,Q32,P32,O32,M32,L32,K32,I32,H32,G32,G36,H36,I36,K36,L36,M36,O36,P36,Q36,G41,H41,I41,K41,L41,M41,O41,P41,Q41) -> 291.82009
C36: Share Price | G36: =G35/G$51 -> 350.47675 | H36: =H35/H$51 -> 310.46827 | I36: =I35/I$51 -> 317.50996 | K36: =K35/K$51 -> 256.43923 | L36: =L35/L$51 -> 276.75431 | M36: =M35/M$51 -> 292.39676 | O36: =O35/O$51 -> 288.36258 | P36: =P35/P$51 -> 303.16702 | Q36: =Q35/Q$51 -> 318.11644 | T36: High | U36: =MAX(K27:M27,G27,H27,I27,O27,P27,Q27,Q32,P32,O32,M32,L32,K32,I32,H32,G32,G36,H36,I36,K36,L36,M36,O36,P36,Q36,G41,H41,I41,K41,L41,M41,O41,P41,Q41) -> 410.51761
C39: 75th percentile | G39: =_xlfn.QUARTILE.INC(F9:F15,3) -> 25.215 | H39: =_xlfn.QUARTILE.INC(G9:G15,3) -> 21.835 | I39: =_xlfn.QUARTILE.INC(H9:H15,3) -> 17.76 | K39: =_xlfn.QUARTILE.INC(J9:J15,3) -> 7.54 | L39: =_xlfn.QUARTILE.INC(K9:K15,3) -> 6.39 | M39: =_xlfn.QUARTILE.INC(L9:L15,3) -> 5.515 | O39: =_xlfn.QUARTILE.INC(N9:N15,3) -> 15.895 | P39: =_xlfn.QUARTILE.INC(O9:O15,3) -> 13.72 | Q39: =_xlfn.QUARTILE.INC(P9:P15,3) -> 12.25
C40: Valuation | G40: =G39*G$50 -> 5020630.3 | H40: =H39*H$50 -> 4290674.1 | I40: =I39*I$50 -> 4183662.5 | K40: =K39*K$50-K$52 -> 4116827 | L40: =L39*L$50-L$52 -> 4258141.1 | M40: =M39*M$50-M$52 -> 4348828.5 | O40: =O39*O$50-O$52 -> 3752656.6 | P40: =P39*P$50-P$52 -> 3948442 | Q40: =Q39*Q$50-Q$52 -> 4248129.8
C41: Share Price | G41: =G40/G$51 -> 410.51761 | H41: =H40/H$51 -> 350.8319 | I41: =I40/I$51 -> 342.08197 | K41: =K40/K$51 -> 336.61709 | L41: =L40/L$51 -> 348.1718 | M41: =M40/M$51 -> 355.58696 | O41: =O40/O$51 -> 306.84028 | P41: =P40/P$51 -> 322.8489 | Q41: =Q40/Q$51 -> 347.35321
C44: Maximum | G44: =MAX(F9:F15) -> 36.99 | H44: =MAX(G9:G15) -> 33.33 | I44: =MAX(H9:H15) -> 29.98 | K44: =MAX(J9:J15) -> 10.05 | L44: =MAX(K9:K15) -> 9.18 | M44: =MAX(L9:L15) -> 8.57 | O44: =MAX(N9:N15) -> 28.33 | P44: =MAX(O9:O15) -> 26.06 | Q44: =MAX(P9:P15) -> 23.81
C45: Valuation | G45: =G44*G$50 -> 7365184.1 | H45: =H44*H$50 -> 6549492.4 | I45: =I44*I$50 -> 7062286.1 | K45: =K44*K$50-K$52 -> 5416126.2 | L45: =L44*L$50-L$52 -> 6024000.8 | M45: =M44*M$50-M$52 -> 6639427.9 | O45: =O44*O$50-O$52 -> 6521216.9 | P45: =P44*P$50-P$52 -> 7307484.5 | Q45: =Q44*Q$50-Q$52 -> 8055264.1
B48: GOOGL Denominators | G48: P/E | K48: EV/Sales | O48: EV/EBITDA
G49: FY26 | H49: FY27 | I49: FY28 | K49: FY26 | L49: FY27 | M49: FY28 | O49: FY26 | P49: FY27 | Q49: FY28
B50: Denominator | G50: ='Income Statement'!AD29 -> 199112.84 | H50: ='Income Statement'!AE29 -> 196504.42 | I50: ='Income Statement'!AF29 -> 235566.58 | K50: ='Income Statement'!AD6 -> 517649.07 | L50: ='Income Statement'!AE6 -> 632924.59 | M50: ='Income Statement'!AF6 -> 749787.04 | O50: ='Income Statement'!AD43 -> 222642.57 | P50: ='Income Statement'!AE43 -> 272207.65 | Q50: ='Income Statement'!AF43 -> 329336.88
B51: Shares Outstanding | G51: =DCF!$G$5 -> 12230 | H51: =DCF!$G$5 -> 12230 | I51: =DCF!$G$5 -> 12230 | K51: =DCF!$G$5 -> 12230 | L51: =DCF!$G$5 -> 12230 | M51: =DCF!$G$5 -> 12230 | O51: =DCF!$G$5 -> 12230 | P51: =DCF!$G$5 -> 12230 | Q51: =DCF!$G$5 -> 12230
B52: Net Debt | G52: =DCF!$G$6 -> -213753 | H52: =DCF!$G$6 -> -213753 | I52: =DCF!$G$6 -> -213753 | K52: =DCF!$G$6 -> -213753 | L52: =DCF!$G$6 -> -213753 | M52: =DCF!$G$6 -> -213753 | O52: =DCF!$G$6 -> -213753 | P52: =DCF!$G$6 -> -213753 | Q52: =DCF!$G$6 -> -213753

Sheet CFS - Historical
N1: Hardcode
N2: Formula
N3: Assumption
A5: Cash Flow Statement (Mn USD) | D5: 2020 | E5: 2021 | F5: 2022 | G5: 1Q23 | H5: 2Q23 | I5: 3Q23 | J5: 4Q23 | K5: 2023 | L5: 1Q24 | M5: 2Q24 | N5: 3Q24 | O5: 4Q24 | P5: 2024 | Q5: 1Q25 | R5: 2Q25 | S5: 3Q25 | T5: 4Q25 | U5: 2025 | V5: 1Q26 | W5: 2026 | X5: 2027 | Y5: 2028 | Z5: 2029 | AA5: 2030
A7: Operating Activities
A8: Net Income | D8: 40269 | E8: 76033 | F8: 59972 | G8: ='Q - CFS Historical'!C6 -> 15051 | H8: ='Q - CFS Historical'!D6 -> 18368 | I8: ='Q - CFS Historical'!E6 -> 19689 | J8: ='Q - CFS Historical'!F6 -> 20687 | K8: 73795 | L8: ='Q - CFS Historical'!H6 -> 23662 | M8: ='Q - CFS Historical'!I6 -> 23619 | N8: ='Q - CFS Historical'!J6 -> 26301 | O8: ='Q - CFS Historical'!K6 -> 26536 | P8: 100118 | Q8: ='Q - CFS Historical'!M6 -> 34540 | R8: ='Q - CFS Historical'!N6 -> 28196 | S8: ='Q - CFS Historical'!O6 -> 34979 | T8: ='Q - CFS Historical'!P6 -> 34455 | U8: 132170 | V8: ='Q - CFS Historical'!R6 -> 62578
A9: Adjustments: | D9: =SUM(D10:D14) -> 23028 | E9: =SUM(E10:E14) -> 17142 | F9: =SUM(F10:F14) -> 33758 | G9: =SUM(G10:G14) -> 7085 | H9: =SUM(H10:H14) -> 7362 | I9: =SUM(I10:I14) -> 8850 | J9: =SUM(J10:J14) -> 8499 | K9: =SUM(K10:K14) -> 31796 | ... V9: =SUM(V10:V14) -> -15386
A10: Depreciation & Amortization | D10: =12905+792 -> 13697 | E10: =11555+886 -> 12441 | F10: =15287+641 -> 15928 | G10: ='Q - CFS Historical'!C8 -> 3186 | H10: ='Q - CFS Historical'!D8 -> 3397 | I10: ='Q - CFS Historical'!E8 -> 3800 | J10: ='Q - CFS Historical'!F8 -> 1563 | K10: 11946 | L10: ='Q - CFS Historical'!H8 -> 3413 | M10: ='Q - CFS Historical'!I8 -> 3708 | N10: ='Q - CFS Historical'!J8 -> 3985 | O10: ='Q - CFS Historical'!K8 -> 4205 | P10: 15311 | Q10: ='Q - CFS Historical'!M8 -> 4487 | R10: ='Q - CFS Historical'!N8 -> 4998 | S10: ='Q - CFS Historical'!O8 -> 5611 | T10: ='Q - CFS Historical'!P8 -> 6040 | U10: 21136 | V10: ='Q - CFS Historical'!R8 -> 6482
A11: Stock-based compensation | D11: 12991 | E11: 15376 | F11: 19362 | G11: ='Q - CFS Historical'!C9 -> 5284 | H11: ='Q - CFS Historical'!D9 -> 5774 | I11: ='Q - CFS Historical'!E9 -> 5743 | J11: ='Q - CFS Historical'!F9 -> 5659 | K11: 22460 | L11: ='Q - CFS Historical'!H9 -> 5264 | M11: ='Q - CFS Historical'!I9 -> 5865 | N11: ='Q - CFS Historical'!J9 -> 5846 | O11: ='Q - CFS Historical'!K9 -> 5810 | P11: 22785 | Q11: ='Q - CFS Historical'!M9 -> 5516 | R11: ='Q - CFS Historical'!N9 -> 5998 | S11: ='Q - CFS Historical'!O9 -> 6368 | T11: ='Q - CFS Historical'!P9 -> 7071 | U11: 24953 | V11: ='Q - CFS Historical'!R9 -> 6751
A12: Defered income taxes | D12: 1390 | E12: 1808 | F12: -8081 | G12: ='Q - CFS Historical'!C10 -> -1854 | H12: ='Q - CFS Historical'!D10 -> -2415 | I12: ='Q - CFS Historical'!E10 -> -1824 | J12: ='Q - CFS Historical'!F10 -> -1670 | K12: -7763 | L12: ='Q - CFS Historical'!H10 -> 419 | M12: ='Q - CFS Historical'!I10 -> -3157 | N12: ='Q - CFS Historical'!J10 -> -1071 | O12: ='Q - CFS Historical'!K10 -> -1448 | P12: -5257 | Q12: ='Q - CFS Historical'!M10 -> -1152 | R12: ='Q - CFS Historical'!N10 -> -444 | S12: ='Q - CFS Historical'!O10 -> 8726 | T12: ='Q - CFS Historical'!P10 -> 1218 | U12: 8348 | V12: ='Q - CFS Historical'!R10 -> 6920
A13: Loss (gain) on debt and equity securities | D13: -6317 | E13: -12270 | F13: 5519 | G13: ='Q - CFS Historical'!C11 -> -84 | H13: ='Q - CFS Historical'!D11 -> 509 | I13: ='Q - CFS Historical'!E11 -> 869 | J13: ='Q - CFS Historical'!F11 -> -471 | K13: 823 | L13: ='Q - CFS Historical'!H11 -> -1781 | M13: ='Q - CFS Historical'!I11 -> 1024 | N13: ='Q - CFS Historical'!J11 -> -1981 | O13: ='Q - CFS Historical'!K11 -> 67 | P13: -2671 | Q13: ='Q - CFS Historical'!M11 -> -9960 | R13: ='Q - CFS Historical'!N11 -> -1451 | S13: ='Q - CFS Historical'!O11 -> -10855 | T13: ='Q - CFS Historical'!P11 -> -2354 | U13: -24620 | V13: ='Q - CFS Historical'!R11 -> -36804
A14: Other | D14: 1267 | E14: -213 | F14: 1030 | G14: ='Q - CFS Historical'!C12 -> 553 | H14: ='Q - CFS Historical'!D12 -> 97 | I14: ='Q - CFS Historical'!E12 -> 262 | J14: ='Q - CFS Historical'!F12 -> 3418 | K14: 4330 | L14: ='Q - CFS Historical'!H12 -> 334 | M14: ='Q - CFS Historical'!I12 -> 851 | N14: ='Q - CFS Historical'!J12 -> 1407 | O14: ='Q - CFS Historical'!K12 -> 827 | P14: 3419 | Q14: ='Q - CFS Historical'!M12 -> 481 | R14: ='Q - CFS Historical'!N12 -> 560 | S14: ='Q - CFS Historical'!O12 -> -198 | T14: ='Q - CFS Historical'!P12 -> 1265 | U14: 2108 | V14: ='Q - CFS Historical'!R12 -> 1265
A15: Changes in assets and liabilities, net of effects of acquisitions: | D15: =SUM(D16:D22) -> 1827 | E15: =SUM(E16:E22) -> -1523 | F15: =SUM(F16:F22) -> -2235 | G15: =SUM(G16:G22) -> 1373 | H15: =SUM(H16:H22) -> 2936 | I15: =SUM(I16:I22) -> 2117 | J15: =SUM(J16:J22) -> -10271 | K15: =SUM(K16:K22) -> -3845 | ... V15: =SUM(V16:V22) -> -1402
A16: Accounts receivable, net | D16: -6524 | E16: -9095 | F16: -2317 | G16: ='Q - CFS Historical'!C14 -> 4454 | H16: ='Q - CFS Historical'!D14 -> -2948 | I16: ='Q - CFS Historical'!E14 -> -2821 | J16: ='Q - CFS Historical'!F14 -> -6518 | K16: -7833 | L16: ='Q - CFS Historical'!H14 -> 3167 | M16: ='Q - CFS Historical'!I14 -> -3057 | N16: ='Q - CFS Historical'!J14 -> -1431 | O16: ='Q - CFS Historical'!K14 -> -4570 | P16: -5891 | Q16: ='Q - CFS Historical'!M14 -> 1638 | R16: ='Q - CFS Historical'!N14 -> -2839 | S16: ='Q - CFS Historical'!O14 -> -2381 | T16: ='Q - CFS Historical'!P14 -> -5197 | U16: -8779 | V16: ='Q - CFS Historical'!R14 -> -363
A17: Income taxes, net | D17: 1209 | E17: -625 | F17: 584 | G17: ='Q - CFS Historical'!C15 -> 4069 | H17: ='Q - CFS Historical'!D15 -> 4451 | I17: ='Q - CFS Historical'!E15 -> 1872 | J17: ='Q - CFS Historical'!F15 -> -9869 | K17: 523 | L17: ='Q - CFS Historical'!H15 -> 3011 | M17: ='Q - CFS Historical'!I15 -> -3900 | N17: ='Q - CFS Historical'!J15 -> -1908 | O17: ='Q - CFS Historical'!K15 -> 379 | P17: -2418 | Q17: ='Q - CFS Historical'!M15 -> 7197 | R17: ='Q - CFS Historical'!N15 -> -9631 | S17: ='Q - CFS Historical'!O15 -> -858 | T17: ='Q - CFS Historical'!P15 -> 66 | U17: -3226 | V17: ='Q - CFS Historical'!R15 -> 8101
A18: Other assets | D18: -1330 | E18: -1846 | F18: -5046 | G18: ='Q - CFS Historical'!C16 -> -746 | H18: ='Q - CFS Historical'!D16 -> -513 | I18: ='Q - CFS Historical'!E16 -> -1624 | J18: ='Q - CFS Historical'!F16 -> 740 | K18: -2143 | L18: ='Q - CFS Historical'!H16 -> -1000 | M18: ='Q - CFS Historical'!I16 -> -532 | N18: ='Q - CFS Historical'!J16 -> -802 | O18: ='Q - CFS Historical'!K16 -> 937 | P18: -1397 | Q18: ='Q - CFS Historical'!M16 -> -1288 | R18: ='Q - CFS Historical'!N16 -> -1479 | S18: ='Q - CFS Historical'!O16 -> -1293 | T18: ='Q - CFS Historical'!P16 -> -482 | U18: -4542 | V18: ='Q - CFS Historical'!R16 -> -3403
A19: Accounts payable | D19: 694 | E19: 283 | F19: 707 | G19: ='Q - CFS Historical'!C17 -> -1105 | H19: ='Q - CFS Historical'!D17 -> 1119 | I19: ='Q - CFS Historical'!E17 -> 223 | J19: ='Q - CFS Historical'!F17 -> 427 | K19: 664 | L19: ='Q - CFS Historical'!H17 -> -2124 | M19: ='Q - CFS Historical'!I17 -> 1561 | N19: ='Q - CFS Historical'!J17 -> 521 | O19: ='Q - CFS Historical'!K17 -> 401 | P19: 359 | Q19: ='Q - CFS Historical'!M17 -> -880 | R19: ='Q - CFS Historical'!N17 -> 553 | S19: ='Q - CFS Historical'!O17 -> -444 | T19: ='Q - CFS Historical'!P17 -> 1678 | U19: 907 | V19: ='Q - CFS Historical'!R17 -> -240
A20: Accrued expenses and other liabilities | D20: 5504 | E20: 7304 | F20: 3915 | G20: ='Q - CFS Historical'!C18 -> -4496 | H20: ='Q - CFS Historical'!D18 -> 459 | I20: ='Q - CFS Historical'!E18 -> 3657 | J20: ='Q - CFS Historical'!F18 -> 4317 | K20: 3937 | L20: ='Q - CFS Historical'!H18 -> -5054 | M20: ='Q - CFS Historical'!I18 -> -122 | N20: ='Q - CFS Historical'!J18 -> -1190 | O20: ='Q - CFS Historical'!K18 -> 5205 | P20: -1161 | Q20: ='Q - CFS Historical'!M18 -> -5045 | R20: ='Q - CFS Historical'!N18 -> 3485 | S20: ='Q - CFS Historical'!O18 -> 7759 | T20: ='Q - CFS Historical'!P18 -> 6740 | U20: 12939 | V20: ='Q - CFS Historical'!R18 -> -6002
A21: Accrued revenue share | D21: 1639 | E21: 1682 | F21: -445 | G21: ='Q - CFS Historical'!C19 -> -602 | H21: ='Q - CFS Historical'!D19 -> 184 | I21: ='Q - CFS Historical'!E19 -> 103 | J21: ='Q - CFS Historical'!F19 -> 797 | K21: 482 | L21: ='Q - CFS Historical'!H19 -> -322 | M21: ='Q - CFS Historical'!I19 -> 419 | N21: ='Q - CFS Historical'!J19 -> 381 | O21: ='Q - CFS Historical'!K19 -> 581 | P21: 1059 | Q21: ='Q - CFS Historical'!M19 -> 116 | R21: ='Q - CFS Historical'!N19 -> -335 | S21: ='Q - CFS Historical'!O19 -> 319 | T21: ='Q - CFS Historical'!P19 -> 799 | U21: 899 | V21: ='Q - CFS Historical'!R19 -> 0
A22: Deferred revenue | D22: 635 | E22: 774 | F22: 367 | G22: ='Q - CFS Historical'!C20 -> -201 | H22: ='Q - CFS Historical'!D20 -> 184 | I22: ='Q - CFS Historical'!E20 -> 707 | J22: ='Q - CFS Historical'!F20 -> -165 | K22: 525 | L22: ='Q - CFS Historical'!H20 -> -141 | M22: ='Q - CFS Historical'!I20 -> 361 | N22: ='Q - CFS Historical'!J20 -> 640 | O22: ='Q - CFS Historical'!K20 -> 183 | P22: 1043 | Q22: ='Q - CFS Historical'!M20 -> 500 | R22: ='Q - CFS Historical'!N20 -> 136 | S22: ='Q - CFS Historical'!O20 -> 681 | T22: ='Q - CFS Historical'!P20 -> 1103 | U22: 2420 | V22: ='Q - CFS Historical'!R20 -> 505
A23: Net cash from operating activities | D23: =D8+D9+D15 -> 65124 | E23: =E8+E9+E15 -> 91652 | F23: =F8+F9+F15 -> 91495 | G23: =G8+G9+G15 -> 23509 | H23: =H8+H9+H15 -> 28666 | I23: =I8+I9+I15 -> 30656 | J23: =J8+J9+J15 -> 18915 | K23: =K8+K9+K15 -> 101746 | ... V23: =V8+V9+V15 -> 45790
A25: Investing activities
A26: Purchases of property and equipment | D26: -22281 | E26: -24640 | F26: -31485 | G26: ='Q - CFS Historical'!C24 -> -6289 | H26: ='Q - CFS Historical'!D24 -> -6888 | I26: ='Q - CFS Historical'!E24 -> -8055 | J26: ='Q - CFS Historical'!F24 -> -11019 | K26: -32251 | L26: ='Q - CFS Historical'!H24 -> -12012 | M26: ='Q - CFS Historical'!I24 -> -13186 | N26: ='Q - CFS Historical'!J24 -> -13061 | O26: ='Q - CFS Historical'!K24 -> -14276 | P26: -52535 | Q26: ='Q - CFS Historical'!M24 -> -17197 | R26: ='Q - CFS Historical'!N24 -> -22446 | S26: ='Q - CFS Historical'!O24 -> -23953 | T26: ='Q - CFS Historical'!P24 -> -27851 | U26: -91447 | V26: ='Q - CFS Historical'!R24 -> -35674
A27: Purchases of marketable securities | D27: -136576 | E27: -135196 | F27: -78874 | G27: ='Q - CFS Historical'!C25 -> -14227 | H27: ='Q - CFS Historical'!D25 -> -21362 | I27: ='Q - CFS Historical'!E25 -> -13833 | J27: ='Q - CFS Historical'!F25 -> -28436 | K27: -77858 | L27: ='Q - CFS Historical'!H25 -> -20684 | M27: ='Q - CFS Historical'!I25 -> -22327 | N27: ='Q - CFS Historical'!J25 -> -22023 | O27: ='Q - CFS Historical'!K25 -> -21645 | P27: -86679 | Q27: ='Q - CFS Historical'!M25 -> -18453 | R27: ='Q - CFS Historical'!N25 -> -21417 | S27: ='Q - CFS Historical'!O25 -> -20964 | T27: ='Q - CFS Historical'!P25 -> -42939 | U27: -103773 | V27: ='Q - CFS Historical'!R25 -> -31041
A28: Maturities and sales of marketable securities | D28: 132906 | E28: 128294 | F28: 97822 | G28: ='Q - CFS Historical'!C26 -> 18327 | H28: ='Q - CFS Historical'!D26 -> 18722 | I28: ='Q - CFS Historical'!E26 -> 15593 | J28: ='Q - CFS Historical'!F26 -> 34030 | K28: 86672 | L28: ='Q - CFS Historical'!H26 -> 24985 | M28: ='Q - CFS Historical'!I26 -> 33592 | N28: ='Q - CFS Historical'!J26 -> 23202 | O28: ='Q - CFS Historical'!K26 -> 21649 | P28: 103428 | Q28: ='Q - CFS Historical'!M26 -> 20345 | R28: ='Q - CFS Historical'!N26 -> 20585 | S28: ='Q - CFS Historical'!O26 -> 20371 | T28: ='Q - CFS Historical'!P26 -> 21939 | U28: 83240 | V28: ='Q - CFS Historical'!R26 -> 38001
A29: Purchases of non-marketable securities | D29: -7175 | E29: -2838 | F29: -2531 | G29: ='Q - CFS Historical'!C27 -> -626 | H29: ='Q - CFS Historical'!D27 -> -887 | I29: ='Q - CFS Historical'!E27 -> -663 | J29: ='Q - CFS Historical'!F27 -> -851 | K29: -3027 | L29: ='Q - CFS Historical'!H27 -> -1206 | M29: ='Q - CFS Historical'!I27 -> -993 | N29: ='Q - CFS Historical'!J27 -> -1035 | O29: ='Q - CFS Historical'!K27 -> -1800 | P29: -5034 | Q29: ='Q - CFS Historical'!M27 -> -958 | R29: ='Q - CFS Historical'!N27 -> -1354 | S29: ='Q - CFS Historical'!O27 -> -1000 | T29: ='Q - CFS Historical'!P27 -> -2404 | U29: -5716 | V29: ='Q - CFS Historical'!R27 -> -906
A30: Maturities and sales of non-marketable securities | D30: 1023 | E30: 934 | F30: 150 | G30: ='Q - CFS Historical'!C28 -> 36 | H30: ='Q - CFS Historical'!D28 -> 145 | I30: ='Q - CFS Historical'!E28 -> 562 | J30: ='Q - CFS Historical'!F28 -> 204 | K30: 947 | L30: ='Q - CFS Historical'!H28 -> 313 | M30: ='Q - CFS Historical'!I28 -> 292 | N30: ='Q - CFS Historical'!J28 -> 127 | O30: ='Q - CFS Historical'!K28 -> 150 | P30: 882 | Q30: ='Q - CFS Historical'!M28 -> 259 | R30: ='Q - CFS Historical'!N28 -> 614 | S30: ='Q - CFS Historical'!O28 -> 323 | T30: ='Q - CFS Historical'!P28 -> 171 | U30: 1367 | V30: ='Q - CFS Historical'!R28 -> 848
A31: Acquisitions, net of cash acquired, and purchases of intangible assets | D31: -738 | E31: -2618 | F31: -6969 | G31: ='Q - CFS Historical'!C29 -> -42 | H31: ='Q - CFS Historical'!D29 -> -298 | I31: ='Q - CFS Historical'!E29 -> -126 | J31: ='Q - CFS Historical'!F29 -> -29 | K31: -495 | L31: ='Q - CFS Historical'!H29 -> -61 | M31: ='Q - CFS Historical'!I29 -> -26 | N31: ='Q - CFS Historical'!J29 -> -2753 | O31: ='Q - CFS Historical'!K29 -> -91 | P31: -2931 | Q31: ='Q - CFS Historical'!M29 -> -340 | R31: ='Q - CFS Historical'!N29 -> -13 | S31: ='Q - CFS Historical'!O29 -> -1072 | T31: ='Q - CFS Historical'!P29 -> -167 | U31: -1592 | V31: ='Q - CFS Historical'!R29 -> -33621
A32: Other investing activities | D32: 68 | E32: 541 | F32: 1589 | G32: ='Q - CFS Historical'!C30 -> -125 | H32: ='Q - CFS Historical'!D30 -> -232 | I32: ='Q - CFS Historical'!E30 -> -628 | J32: ='Q - CFS Historical'!F30 -> -66 | K32: -1051 | L32: ='Q - CFS Historical'!H30 -> 101 | M32: ='Q - CFS Historical'!I30 -> -133 | N32: ='Q - CFS Historical'!J30 -> -2468 | O32: ='Q - CFS Historical'!K30 -> -167 | P32: -2667 | Q32: ='Q - CFS Historical'!M30 -> 150 | R32: ='Q - CFS Historical'!N30 -> -513 | S32: ='Q - CFS Historical'!O30 -> -1482 | T32: ='Q - CFS Historical'!P30 -> -525 | U32: -2370 | V32: ='Q - CFS Historical'!R30 -> -996
A33: Net cash from investing activities | D33: =SUM(D26:D32) -> -32773 | E33: =SUM(E26:E32) -> -35523 | F33: =SUM(F26:F32) -> -20298 | G33: =SUM(G26:G32) -> -2946 | H33: =SUM(H26:H32) -> -10800 | I33: =SUM(I26:I32) -> -7150 | J33: =SUM(J26:J32) -> -6167 | K33: =SUM(K26:K32) -> -27063 | ... V33: =SUM(V26:V32) -> -63389
A35: Financing activities
A36: Net payments related to stock-based award activities | D36: -5720 | E36: -10162 | F36: -9300 | G36: ='Q - CFS Historical'!C34 -> -1989 | H36: ='Q - CFS Historical'!D34 -> -2736 | I36: ='Q - CFS Historical'!E34 -> -2432 | J36: ='Q - CFS Historical'!F34 -> -2680 | K36: -9837 | L36: ='Q - CFS Historical'!H34 -> -2929 | M36: ='Q - CFS Historical'!I34 -> -3209 | N36: ='Q - CFS Historical'!J34 -> -3003 | O36: ='Q - CFS Historical'!K34 -> -3049 | P36: -12190 | Q36: ='Q - CFS Historical'!M34 -> -3110 | R36: ='Q - CFS Historical'!N34 -> -2621 | S36: ='Q - CFS Historical'!O34 -> -3270 | T36: ='Q - CFS Historical'!P34 -> -5166 | U36: -14167 | V36: ='Q - CFS Historical'!R34 -> -5483
A37: Repurchases of stock | D37: -31149 | E37: -50274 | F37: -59296 | G37: ='Q - CFS Historical'!C35 -> -14557 | H37: ='Q - CFS Historical'!D35 -> -14969 | I37: ='Q - CFS Historical'!E35 -> -15787 | J37: ='Q - CFS Historical'!F35 -> -16191 | K37: -61504 | L37: ='Q - CFS Historical'!H35 -> -15696 | M37: ='Q - CFS Historical'!I35 -> -15684 | N37: ='Q - CFS Historical'!J35 -> -15291 | O37: ='Q - CFS Historical'!K35 -> -15551 | P37: -62222 | Q37: ='Q - CFS Historical'!M35 -> -15068 | R37: ='Q - CFS Historical'!N35 -> -13638 | S37: ='Q - CFS Historical'!O35 -> -11504 | T37: ='Q - CFS Historical'!P35 -> -5499 | U37: -45709 | V37: ='Q - CFS Historical'!R35 -> 0
A38: Dividend payments | D38: 0 | E38: 0 | F38: 0 | G38: ='Q - CFS Historical'!C36 -> 0 | H38: ='Q - CFS Historical'!D36 -> 0 | I38: ='Q - CFS Historical'!E36 -> 0 | J38: ='Q - CFS Historical'!F36 -> 0 | K38: 0 | L38: ='Q - CFS Historical'!H36 -> 0 | M38: ='Q - CFS Historical'!I36 -> -2466 | N38: ='Q - CFS Historical'!J36 -> -2455 | O38: ='Q - CFS Historical'!K36 -> -2442 | P38: -7363 | Q38: ='Q - CFS Historical'!M36 -> -2434 | R38: ='Q - CFS Historical'!N36 -> -2543 | S38: ='Q - CFS Historical'!O36 -> -2536 | T38: ='Q - CFS Historical'!P36 -> -2536 | U38: -10049 | V38: ='Q - CFS Historical'!R36 -> -2542
A39: Proceeds from issuance of debt, net of costs | D39: 11761 | E39: 20199 | F39: 52872 | G39: ='Q - CFS Historical'!C37 -> 6927 | H39: ='Q - CFS Historical'!D37 -> 1123 | I39: ='Q - CFS Historical'!E37 -> 1248 | J39: ='Q - CFS Historical'!F37 -> 1492 | K39: 10790 | L39: ='Q - CFS Historical'!H37 -> 1982 | M39: ='Q - CFS Historical'!I37 -> 2893 | N39: ='Q - CFS Historical'!J37 -> 3819 | O39: ='Q - CFS Historical'!K37 -> 4895 | P39: 13589 | Q39: ='Q - CFS Historical'!M37 -> 4532 | R39: ='Q - CFS Historical'!N37 -> 26846 | S39: ='Q - CFS Historical'!O37 -> 6624 | T39: ='Q - CFS Historical'!P37 -> 26562 | U39: 64564 | V39: ='Q - CFS Historical'!R37 -> 31379
A40: Repayments of debt | D40: -2100 | E40: -21435 | F40: -54068 | G40: ='Q - CFS Historical'!C38 -> -6952 | H40: ='Q - CFS Historical'!D38 -> -1255 | I40: ='Q - CFS Historical'!E38 -> -1414 | J40: ='Q - CFS Historical'!F38 -> -1929 | K40: -11550 | L40: ='Q - CFS Historical'!H38 -> -3079 | M40: ='Q - CFS Historical'!I38 -> -2423 | N40: ='Q - CFS Historical'!J38 -> -3449 | O40: ='Q - CFS Historical'!K38 -> -3750 | P40: -12701 | Q40: ='Q - CFS Historical'!M38 -> -4521 | R40: ='Q - CFS Historical'!N38 -> -13876 | S40: ='Q - CFS Historical'!O38 -> -7697 | T40: ='Q - CFS Historical'!P38 -> -6333 | U40: -32427 | V40: ='Q - CFS Historical'!R38 -> -1477
A41: Proceeds from sale of interest in consolidated entities, net | D41: 2800 | E41: 310 | F41: 35 | G41: ='Q - CFS Historical'!C39 -> 3 | H41: ='Q - CFS Historical'!D39 -> 2 | I41: ='Q - CFS Historical'!E39 -> 3 | J41: ='Q - CFS Historical'!F39 -> 0 | K41: 8 | L41: ='Q - CFS Historical'!H39 -> 8 | M41: ='Q - CFS Historical'!I39 -> 0 | N41: ='Q - CFS Historical'!J39 -> 285 | O41: ='Q - CFS Historical'!K39 -> 861 | P41: 1154 | Q41: ='Q - CFS Historical'!M39 -> 400 | R41: ='Q - CFS Historical'!N39 -> 0 | S41: ='Q - CFS Historical'!O39 -> 0 | T41: ='Q - CFS Historical'!P39 -> 0 | U41: 400 | V41: ='Q - CFS Historical'!R39 -> 3200
A42: Net cash used in financing activities | D42: =SUM(D36:D41) -> -24408 | E42: =SUM(E36:E41) -> -61362 | F42: =SUM(F36:F41) -> -69757 | G42: =SUM(G36:G41) -> -16568 | H42: =SUM(H36:H41) -> -17835 | I42: =SUM(I36:I41) -> -18382 | J42: =SUM(J36:J41) -> -19308 | K42: =SUM(K36:K41) -> -72093 | ... V42: =SUM(V36:V41) -> 25077
A43: Effect of exchange rate changes on cash and cash equivalents | D43: 24 | E43: -287 | F43: -506 | G43: ='Q - CFS Historical'!C41 -> 50 | H43: ='Q - CFS Historical'!D41 -> -26 | I43: ='Q - CFS Historical'!E41 -> -351 | J43: ='Q - CFS Historical'!F41 -> -94 | K43: -421 | L43: ='Q - CFS Historical'!H41 -> -125 | M43: ='Q - CFS Historical'!I41 -> -238 | N43: ='Q - CFS Historical'!J41 -> 141 | O43: ='Q - CFS Historical'!K41 -> -390 | P43: -612 | Q43: ='Q - CFS Historical'!M41 -> 43 | R43: ='Q - CFS Historical'!N41 -> 401 | S43: ='Q - CFS Historical'!O41 -> -200 | T43: ='Q - CFS Historical'!P41 -> -36 | U43: 208 | V43: ='Q - CFS Historical'!R41 -> -123
A45: Cash and Cash Equivalents
B46: Changes in Cash | D46: =D23+D33+D42+D43 -> 7967 | E46: =E23+E33+E42+E43 -> -5520 | F46: =F23+F33+F42+F43 -> 934 | G46: =G23+G33+G42+G43 -> 4045 | H46: =H23+H33+H42+H43 -> 5 | I46: =I23+I33+I42+I43 -> 4773 | J46: =J23+J33+J42+J43 -> -6654 | K46: =K23+K33+K42+K43 -> 2169 | ... V46: =V23+V33+V42+V43 -> 7355
B47: Cash BoP | D47: 18498 | E47: =D48 -> 26465 | F47: =E48 -> 20945 | G47: ='Q - CFS Historical'!C44 -> 21879 | H47: ='Q - CFS Historical'!D44 -> 25924 | I47: ='Q - CFS Historical'!E44 -> 25929 | J47: ='Q - CFS Historical'!F44 -> 30702 | K47: =F48 -> 21879 | L47: ='Q - CFS Historical'!H44 -> 24048 | M47: ='Q - CFS Historical'!I44 -> 24493 | N47: ='Q - CFS Historical'!J44 -> 27225 | O47: ='Q - CFS Historical'!K44 -> 19959 | P47: =K48 -> 24048 | Q47: ='Q - CFS Historical'!M44 -> 23466 | R47: ='Q - CFS Historical'!N44 -> 23264 | S47: ='Q - CFS Historical'!O44 -> 21036 | T47: ='Q - CFS Historical'!P44 -> 23090 | U47: =P48 -> 23466 | V47: ='Q - CFS Historical'!R44 -> 30708
A48: Cash EoP | D48: =D47+D46 -> 26465 | E48: =E47+E46 -> 20945 | F48: =F47+F46 -> 21879 | G48: =G47+G46 -> 25924 | H48: =H47+H46 -> 25929 | I48: =I47+I46 -> 30702 | J48: =J47+J46 -> 24048 | K48: =K47+K46 -> 24048 | ... V48: =V47+V46 -> 38063

Sheet CFS - Estimates
U1: Hardcode
U2: Formula
U3: Assumption
A5: Cash Flow Statement (Mn USD) | D5: 2020 | E5: 2021 | F5: 2022 | G5: 1Q23 | H5: 2Q23 | I5: 3Q23 | J5: 4Q23 | K5: 2023 | L5: 1Q24 | M5: 2Q24 | N5: 3Q24 | O5: 4Q24 | P5: 2024 | Q5: 1Q25 | R5: 2Q25 | S5: 3Q25 | T5: 4Q25 | U5: 2025 | V5: 1Q26 | W5: 2Q26 | X5: 3Q26 | Y5: 4Q26 | Z5: 2026 | AA5: 2027 | AB5: 2028 | AC5: 2029 | AD5: 2030 | AE5: 2031
A7: CFO | D7: =D8+D9+D10+D11 -> 66957 | E7: =E8+E9+E10+E11 -> 100378 | F7: =F8+F9+F10+F11 -> 97769 | G7: =G8+G9+G10+G11 -> 27225 | H7: =H8+H9+H10+H11 -> 32821 | I7: =I8+I9+I10+I11 -> 31899 | J7: =J8+J9+J10+J11 -> 130580.86 | K7: =K8+K9+K10+K11 -> 111134 | ... U7: =U8+U9+U10+U11 -> 180741 | V7: =V8+V9+V10+V11+V13 -> 76536 | W7: =W8+W9+W10+W11+W13 -> 44990.095 | X7: =X8+X9+X10+X11+X13 -> 60755.305 | Y7: =Y8+Y9+Y10+Y11+Y13 -> 72782.308 | Z7: =Z8+Z9+Z10+Z11+Z13 -> 255063.71 | AA7: =AA8+AA9+AA10+AA11+AA13 -> 267945.48 | AB7: =AB8+AB9+AB10+AB11+AB13 -> 320752.26 | AC7: =AC8+AC9+AC10+AC11+AC13 -> 382998.41 | ... AE7: =AE8+AE9+AE10+AE11+AE13 -> 470177.12
A8: Net Income | D8: ='Income Statement'!D29 -> 40269 | E8: ='Income Statement'!E29 -> 76033 | F8: ='Income Statement'!J29 -> 59972 | G8: ='Q - CFS Indirect'!C6 -> 15051 | H8: ='Q - CFS Indirect'!D6 -> 18368 | I8: ='Q - CFS Indirect'!E6 -> 19689 | J8: ='Q - CFS Indirect'!F6 -> 20687 | K8: ='Income Statement'!O29 -> 73795 | L8: ='Q - CFS Indirect'!H6 -> 23662 | M8: ='Q - CFS Indirect'!I6 -> 23619 | N8: ='Q - CFS Indirect'!J6 -> 26301 | O8: ='Q - CFS Indirect'!K6 -> 26536 | P8: ='Income Statement'!T29 -> 100118 | Q8: ='Q - CFS Indirect'!M6 -> 34540 | R8: ='Q - CFS Indirect'!N6 -> 28196 | S8: ='Q - CFS Indirect'!O6 -> 34979 | T8: ='Q - CFS Indirect'!P6 -> 34455 | U8: ='Income Statement'!Y29 -> 132170 | V8: ='Q - CFS Indirect'!R6 -> 62578 | W8: ='Income Statement'!AA29 -> 39838.528 | X8: ='Income Statement'!AB29 -> 43478.558 | Y8: ='Income Statement'!AC29 -> 53217.758 | Z8: ='Income Statement'!AD29 -> 199112.84 | AA8: ='Income Statement'!AE29 -> 196504.42 | AB8: ='Income Statement'!AF29 -> 235566.58 | AC8: ='Income Statement'!AG29 -> 286545.44 | AD8: ='Income Statement'!AH29 -> 317377.02 | AE8: ='Income Statement'!AI29 -> 349467.75
A9: (+) D&A | D9: =12905+792 -> 13697 | E9: =11555+886 -> 12441 | F9: =15287+641 -> 15928 | G9: ='Q - CFS Indirect'!C7 -> 3186 | H9: ='Q - CFS Indirect'!D7 -> 3397 | I9: ='Q - CFS Indirect'!E7 -> 3800 | J9: ='Q - CFS Indirect'!F7 -> 1563 | K9: 11946 | L9: ='Q - CFS Indirect'!H7 -> 3413 | M9: ='Q - CFS Indirect'!I7 -> 3708 | N9: ='Q - CFS Indirect'!J7 -> 3985 | O9: ='Q - CFS Indirect'!K7 -> 4205 | P9: 15311 | Q9: ='Q - CFS Indirect'!M7 -> 4487 | R9: ='Q - CFS Indirect'!N7 -> 4998 | S9: ='Q - CFS Indirect'!O7 -> 5611 | T9: ='Q - CFS Indirect'!P7 -> 6040 | U9: 21136 | V9: ='Q - CFS Indirect'!R7 -> 6482 | W9: ='CapEx & D&A '!W6 -> 5975.5482 | X9: ='CapEx & D&A '!X6 -> 6741.676 | Y9: ='CapEx & D&A '!Y6 -> 7670.4293 | Z9: ='CapEx & D&A '!Z6 -> 26869.654 | AA9: ='CapEx & D&A '!AA6 -> 31646.23 | AB9: ='CapEx & D&A '!AB6 -> 37489.352 | AC9: ='CapEx & D&A '!AC6 -> 43046.212 | AD9: ='CapEx & D&A '!AD6 -> 48451.581 | AE9: ='CapEx & D&A '!AE6 -> 53395.394
A10: (+/-) OWC | D10: =BS!D43 -> 0 | E10: =-BS!E43 -> -3472 | F10: =-BS!F43 -> 2507 | G10: ='Q - CFS Indirect'!C8 -> 3704 | H10: ='Q - CFS Indirect'!D8 -> 5282 | I10: ='Q - CFS Indirect'!E8 -> 2667 | J10: ='CFS - Estimates'!W9+'CFS - Estimates'!X8+'CFS - Estimates'!Y8 -> 102671.86 | K10: =-BS!K43 -> 2933 | L10: ='Q - CFS Indirect'!H8 -> -1584 | M10: ='Q - CFS Indirect'!I8 -> -2973 | N10: ='Q - CFS Indirect'!J8 -> -151 | O10: ='Q - CFS Indirect'!K8 -> 4576 | P10: =-BS!P43 -> -132 | Q10: ='Q - CFS Indirect'!M8 -> 3862 | R10: ='Q - CFS Indirect'!N8 -> -8688 | S10: ='Q - CFS Indirect'!O8 -> 7857 | T10: ='Q - CFS Indirect'!P8 -> -549 | U10: =-BS!U43 -> 2482 | V10: ='Q - CFS Indirect'!R8 -> 725 | W10: =-BS!W43 -> -8165.6362 | X10: =-BS!X43 -> 2252.1392 | Y10: =-BS!Y43 -> 2470.1081 | Z10: =-BS!Z43 -> -2718.389 | AA10: =-BS!AA43 -> 913.76001 | AB10: =-BS!AB43 -> 1636.3012 | AC10: =-BS!AC43 -> 519.48722 | AD10: =-BS!AD43 -> 2213.4781 | AE10: =-BS!AE43 -> 1711.5321
A11: (+) Stock Based Compensation | D11: 12991 | E11: 15376 | F11: 19362 | G11: ='Q - CFS Indirect'!C9 -> 5284 | H11: ='Q - CFS Indirect'!D9 -> 5774 | I11: ='Q - CFS Indirect'!E9 -> 5743 | J11: ='Q - CFS Indirect'!F9 -> 5659 | K11: 22460 | L11: ='Q - CFS Indirect'!H9 -> 5264 | M11: ='Q - CFS Indirect'!I9 -> 5865 | N11: ='Q - CFS Indirect'!J9 -> 5846 | O11: ='Q - CFS Indirect'!K9 -> 5810 | P11: 22785 | Q11: ='Q - CFS Indirect'!M9 -> 5516 | R11: ='Q - CFS Indirect'!N9 -> 5998 | S11: ='Q - CFS Indirect'!O9 -> 6368 | T11: ='Q - CFS Indirect'!P9 -> 7071 | U11: 24953 | V11: ='Q - CFS Indirect'!R9 -> 6751 | W11: =W12*'Income Statement'!AA6 -> 7341.655 | X11: =X12*'Income Statement'!AB6 -> 8282.932 | Y11: =Y12*'Income Statement'!AC6 -> 9424.0133 | Z11: =Z12*'Income Statement'!AD6 -> 31799.6 | AA11: =AA12*'Income Statement'!AE6 -> 38881.069 | AB11: =AB12*'Income Statement'!AF6 -> 46060.023 | AC11: =AC12*'Income Statement'!AG6 -> 52887.271 | AD11: =AD12*'Income Statement'!AH6 -> 59528.395 | AE11: =AE12*'Income Statement'!AI6 -> 65602.444
B12: As % of Revenue | D12: =D11/'Income Statement'!D6 -> 0.071173032 | E12: =E11/'Income Statement'!E6 -> 0.059680869 | F12: =F11/'Income Statement'!J6 -> 0.068456632 | G12: =G11/'Q - Income Statement'!H5 -> 0.075716108 | H12: =H11/'Q - Income Statement'!I5 -> 0.077395314 | I12: =I11/'Q - Income Statement'!J5 -> 0.074882975 | J12: =J11/'Q - Income Statement'!K5 -> 0.065565983 | K12: =K11/'Income Statement'!O6 -> 0.073065837 | L12: =L11/'Q - Income Statement'!M5 -> 0.065359639 | M12: =M11/'Q - Income Statement'!N5 -> 0.069210073 | N12: =N11/'Q - Income Statement'!O5 -> 0.066230117 | O12: =O11/'Q - Income Statement'!P5 -> 0.060226601 | P12: =P11/'Income Statement'!T6 -> 0.065096652 | Q12: =Q11/'Q - Income Statement'!R5 -> 0.061129951 | R12: =R11/'Q - Income Statement'!S5 -> 0.06220185 | S12: =S11/'Q - Income Statement'!T5 -> 0.062220311 | T12: =T11/'Q - Income Statement'!U5 -> 0.062120041 | U12: =U11/'Income Statement'!Y6 -> 0.061943322 | V12: =V11/'Q - Income Statement'!W5 -> 0.061430807 | W12: =V12 -> 0.061430807 | X12: =W12 -> 0.061430807 | Y12: =X12 -> 0.061430807 | Z12: =Y12 -> 0.061430807 | AA12: =Z12 -> 0.061430807 | AB12: =AA12 -> 0.061430807 | AC12: =AB12 -> 0.061430807 | AD12: =AC12 -> 0.061430807 | AE12: =AD12 -> 0.061430807
A15: CFI | D15: =D16+D17+D18 -> 0 | E15: =E16+E17+E18 -> -21696 | F15: =F16+F17+F18 -> -16012 | G15: =G16+G17+G18 -> -5613 | H15: =H16+H17+H18 -> -3659 | I15: =I16+I17+I18 -> -4180 | J15: =J16+J17+J18 -> -8741 | K15: =K16+K17+K18 -> -22193 | ... V15: =V16+V17+V18 -> -72682 | W15: =SUM(W16:W17) -> -44219.057 | X15: =SUM(X16:X17) -> -53933.408 | Y15: =SUM(Y16:Y17) -> -73636.121 | Z15: =SUM(Z16:Z17) -> -212693.59 | AA15: =SUM(AA16:AA17) -> -253169.84 | AB15: =SUM(AB16:AB17) -> -262425.46 | AC15: =SUM(AC16:AC17) -> -258277.27 | AD15: =SUM(AD16:AD17) -> -193806.33 | AE15: =SUM(AE16:AE17) -> -160186.18
A16: (-) Investments | E16: =-(BS!E15-BS!D15) -> -8846 | F16: =-(BS!F15-BS!E15) -> -943 | G16: ='Q - CFS Indirect'!C12 -> -721 | H16: ='Q - CFS Indirect'!D12 -> -11 | I16: ='Q - CFS Indirect'!E12 -> 317 | J16: ='Q - CFS Indirect'!F12 -> -101 | K16: =-(BS!K15-BS!F15) -> -516 | L16: ='Q - CFS Indirect'!H12 -> -2986 | M16: ='Q - CFS Indirect'!I12 -> -178 | N16: ='Q - CFS Indirect'!J12 -> -2005 | O16: ='Q - CFS Indirect'!K12 -> -1805 | P16: =-(BS!P15-BS!K15) -> -6974 | Q16: ='Q - CFS Indirect'!M12 -> -13047 | R16: ='Q - CFS Indirect'!N12 -> -1545 | S16: ='Q - CFS Indirect'!O12 -> -11226 | T16: ='Q - CFS Indirect'!P12 -> -4887 | U16: =-(BS!U15-BS!P15) -> -30705 | V16: ='Q - CFS Indirect'!R12 -> -38259 | W16: 0 | X16: 0 | Y16: 0 | Z16: 0 | AA16: 0 | AB16: 0 | AC16: 0 | AD16: 0 | AE16: 0
A17: (-) CapEx | E17: =-(BS!E16-BS!D16) -> -12850 | F17: =-(BS!F16-BS!E16) -> -15069 | G17: ='Q - CFS Indirect'!C13 -> -4892 | H17: ='Q - CFS Indirect'!D13 -> -3648 | I17: ='Q - CFS Indirect'!E13 -> -4497 | J17: ='Q - CFS Indirect'!F13 -> -8640 | K17: =-(BS!K16-BS!F16) -> -21677 | L17: ='Q - CFS Indirect'!H13 -> -8837 | M17: ='Q - CFS Indirect'!I13 -> -7973 | N17: ='Q - CFS Indirect'!J13 -> -10115 | O17: ='Q - CFS Indirect'!K13 -> -9766 | P17: =-(BS!P16-BS!K16) -> -36691 | Q17: ='Q - CFS Indirect'!M13 -> -14026 | R17: ='Q - CFS Indirect'!N13 -> -18169 | S17: ='Q - CFS Indirect'!O13 -> -20556 | T17: ='Q - CFS Indirect'!P13 -> -22810 | U17: =-(BS!U16-BS!P16) -> -75561 | V17: ='Q - CFS Indirect'!R13 -> -34423 | W17: =-'CapEx & D&A '!W13 -> -44219.057 | X17: =-'CapEx & D&A '!X13 -> -53933.408 | Y17: =-'CapEx & D&A '!Y13 -> -73636.121 | Z17: =-'CapEx & D&A '!Z13 -> -212693.59 | AA17: =-'CapEx & D&A '!AA13 -> -253169.84 | AB17: =-'CapEx & D&A '!AB13 -> -262425.46 | AC17: =-'CapEx & D&A '!AC13 -> -258277.27 | AD17: =-'CapEx & D&A '!AD13 -> -193806.33 | AE17: =-'CapEx & D&A '!AE13 -> -160186.18
A18: (+/-) Others
A20: CFF | D20: =D21+D22+D23+D24+D28+D25 -> -36845 | E20: =E21+E22+E23+E24+E28+E25 -> -56331 | F20: =F21+F22+F23+F24+F28+F25 -> -61696 | G20: =G21+G22+G23+G24+G28+G25 -> -15117 | H20: =H21+H22+H23+H24+H28+H25 -> -15797 | I20: =I21+I22+I23+I24+I28+I25 -> -16347 | J20: =J21+J22+J23+J24+J28+J25 -> -17640 | K20: =K21+K22+K23+K24+K28+K25 -> -64901 | ... Y20: =Y21+Y22+Y23+Y24+Y28+Y25 -> -16755.568 | Z20: =SUM(Z21:Z25) -> -33407.177 | AA20: =AA21+AA22+AA23+AA24+AA28+AA25 -> -80691.35 | AB20: =AB21+AB22+AB23+AB24+AB28+AB25 -> -111074.5 | AC20: =AC21+AC22+AC23+AC24+AC28+AC25 -> -165288.18 | AD20: =AD21+AD22+AD23+AD24+AD28+AD25 -> -202016.25 | AE20: =AE21+AE22+AE23+AE24+AE28+AE25 -> -268781.73
A21: (+) Capital Increase | E21: =BS!E36-BS!D36 -> 3264 | F21: =BS!F36-BS!E36 -> 6410 | G21: ='Q - CFS Indirect'!C16 -> 2085 | H21: ='Q - CFS Indirect'!D16 -> 1979 | I21: ='Q - CFS Indirect'!E16 -> 2343 | J21: ='Q - CFS Indirect'!F16 -> 1943 | K21: =BS!K36-BS!F36 -> 8350 | L21: ='Q - CFS Indirect'!H16 -> 1379 | M21: ='Q - CFS Indirect'!I16 -> 1819 | N21: ='Q - CFS Indirect'!J16 -> 2298 | O21: ='Q - CFS Indirect'!K16 -> 2770 | P21: =BS!P36-BS!K36 -> 8266 | Q21: ='Q - CFS Indirect'!M16 -> 1925 | R21: ='Q - CFS Indirect'!N16 -> 2558 | S21: ='Q - CFS Indirect'!O16 -> 2412 | T21: ='Q - CFS Indirect'!P16 -> 1431 | U21: =BS!U36-BS!P36 -> 8326 | V21: ='Q - CFS Indirect'!R16 -> 3776 | W21: =BS!W36-BS!V36 -> 84750 | X21: =BS!X36-BS!W36 -> 0 | Y21: =BS!Y36-BS!X36 -> 0 | Z21: =BS!Z36-BS!Y36 -> 0 | AA21: =BS!AA36-BS!Z36 -> 0 | AB21: =BS!AB36-BS!AA36 -> 0 | AC21: =BS!AC36-BS!AB36 -> 0 | AD21: =BS!AD36-BS!AC36 -> 0 | AE21: =BS!AE36-BS!AD36 -> 0
A22: (+) Loans & Bonds | E22: =(BS!E30+BS!E31)-(BS!D30+BS!D31) -> 1128 | F22: =(BS!F30+BS!F31)-(BS!E30+BS!E31) -> 996 | G22: ='Q - CFS Indirect'!C17 -> -706 | H22: ='Q - CFS Indirect'!D17 -> -45 | I22: ='Q - CFS Indirect'!E17 -> -120 | J22: ='Q - CFS Indirect'!F17 -> -618 | K22: =(BS!K30+BS!K31)-(BS!F30+BS!F31) -> -1489 | L22: ='Q - CFS Indirect'!H17 -> -528 | M22: ='Q - CFS Indirect'!I17 -> -239 | N22: ='Q - CFS Indirect'!J17 -> -995 | O22: ='Q - CFS Indirect'!K17 -> -1377 | P22: =(BS!P30+BS!P31)-(BS!K30+BS!K31) -> -3139 | Q22: ='Q - CFS Indirect'!M17 -> -10 | R22: ='Q - CFS Indirect'!N17 -> 12995 | S22: ='Q - CFS Indirect'!O17 -> -1846 | T22: ='Q - CFS Indirect'!P17 -> 25578 | U22: =(BS!U30+BS!U31)-(BS!P30+BS!P31) -> 36717 | V22: ='Q - CFS Indirect'!R17 -> 31193 | W22: =BS!W30+BS!W31-BS!V30-BS!V31 -> 3875.05 | X22: =BS!X30+BS!X31-BS!W30-BS!W31 -> 4068.8025 | Y22: =BS!Y30+BS!Y31-BS!X30-BS!X31 -> 4272.2426 | Z22: =SUM(V22:Y22) -> 43409.095 | AA22: =BS!AA30+BS!AA31-BS!Z30-BS!Z31 -> 8971.7095 | AB22: =BS!AB30+BS!AB31-BS!AA30-BS!AA31 -> 7895.1044 | AC22: =BS!AC30+BS!AC31-BS!AB30-BS!AB31 -> 6395.0345 | AD22: =BS!AD30+BS!AD31-BS!AC30-BS!AC31 -> 4519.1577 | AE22: =BS!AE30+BS!AE31-BS!AD30-BS!AD31 -> 2349.962
A23: (-) Dividends | D23: 0 | E23: 0 | F23: 0 | G23: ='Q - CFS Indirect'!C18 -> 0 | H23: ='Q - CFS Indirect'!D18 -> 0 | I23: ='Q - CFS Indirect'!E18 -> 0 | J23: ='Q - CFS Indirect'!F18 -> 0 | K23: 0 | L23: ='Q - CFS Indirect'!H18 -> 0 | M23: ='Q - CFS Indirect'!I18 -> -2466 | N23: ='Q - CFS Indirect'!J18 -> -2455 | O23: ='Q - CFS Indirect'!K18 -> -2442 | P23: -7363 | Q23: ='Q - CFS Indirect'!M18 -> -2434 | R23: ='Q - CFS Indirect'!N18 -> -2543 | S23: ='Q - CFS Indirect'!O18 -> -2536 | T23: ='Q - CFS Indirect'!P18 -> -2536 | U23: -10049 | V23: ='Q - CFS Indirect'!R18 -> -2542 | W23: =-'Income Statement'!AA37 -> -2390.3117 | X23: =-'Income Statement'!AB37 -> -2608.7135 | Y23: =-'Income Statement'!AC37 -> -3193.0655 | Z23: =-'Income Statement'!AD37 -> -11946.771 | AA23: =-'Income Statement'!AE37 -> -13755.31 | AB23: =-'Income Statement'!AF37 -> -18845.326 | AC23: =-'Income Statement'!AG37 -> -28654.544 | AD23: =-'Income Statement'!AH37 -> -34911.473 | AE23: =-'Income Statement'!AI37 -> -47178.146
A24: (-) Repurchases of stock | D24: -31149 | E24: -50274 | F24: -59296 | G24: ='Q - CFS Indirect'!C19 -> -14557 | H24: ='Q - CFS Indirect'!D19 -> -14969 | I24: ='Q - CFS Indirect'!E19 -> -15787 | J24: ='Q - CFS Indirect'!F19 -> -16191 | K24: -61504 | L24: ='Q - CFS Indirect'!H19 -> -15696 | M24: ='Q - CFS Indirect'!I19 -> -15684 | N24: ='Q - CFS Indirect'!J19 -> -15291 | O24: ='Q - CFS Indirect'!K19 -> -15551 | P24: -62222 | Q24: ='Q - CFS Indirect'!M19 -> -15068 | R24: ='Q - CFS Indirect'!N19 -> -13638 | S24: ='Q - CFS Indirect'!O19 -> -11504 | T24: ='Q - CFS Indirect'!P19 -> -5499 | U24: -45709 | V24: ='Q - CFS Indirect'!R19 -> 0 | W24: =-'Income Statement'!AA40 -> -9561.2466 | X24: =-'Income Statement'!AB40 -> -10434.854 | Y24: =-'Income Statement'!AC40 -> -12772.262 | Z24: =-'Income Statement'!AD40 -> -47787.082 | AA24: =-'Income Statement'!AE40 -> -55021.239 | AB24: =-'Income Statement'!AF40 -> -75381.306 | AC24: =-'Income Statement'!AG40 -> -114618.18 | AD24: =-'Income Statement'!AH40 -> -139645.89 | AE24: =-'Income Statement'!AI40 -> -188712.58
A25: (-) Stock-based award | D25: -5720 | E25: -10162 | F25: -9300 | G25: ='Q - CFS Indirect'!C20 -> -1989 | H25: ='Q - CFS Indirect'!D20 -> -2736 | I25: ='Q - CFS Indirect'!E20 -> -2432 | J25: ='Q - CFS Indirect'!F20 -> -2680 | K25: -9837 | L25: ='Q - CFS Indirect'!H20 -> -2929 | M25: ='Q - CFS Indirect'!I20 -> -3209 | N25: ='Q - CFS Indirect'!J20 -> -3003 | O25: ='Q - CFS Indirect'!K20 -> -3049 | P25: -12190 | Q25: ='Q - CFS Indirect'!M20 -> -3110 | R25: ='Q - CFS Indirect'!N20 -> -2621 | S25: ='Q - CFS Indirect'!O20 -> -3270 | T25: ='Q - CFS Indirect'!P20 -> -5166 | U25: -14167 | V25: ='Q - CFS Indirect'!R20 -> -5483 | W25: =-W26*'Income Statement'!AA6 -> -3943.8618 | X25: =-X26*'Income Statement'!AB6 -> -4449.5062 | Y25: =-Y26*'Income Statement'!AC6 -> -5062.4833 | Z25: =-Z26*'Income Statement'!AD6 -> -17082.419 | AA25: =-AA26*'Income Statement'!AE6 -> -20886.512 | AB25: =-AB26*'Income Statement'!AF6 -> -24742.972 | AC25: =-AC26*'Income Statement'!AG6 -> -28410.5 | AD25: =-AD26*'Income Statement'!AH6 -> -31978.044 | AE25: =-AE26*'Income Statement'!AI6 -> -35240.96
B26: As % of Revenue | D26: =-D25/'Income Statement'!D6 -> 0.031337829 | E26: =-E25/'Income Statement'!E6 -> 0.039443092 | F26: =-F25/'Income Statement'!J6 -> 0.032881246 | G26: =-G25/'Q - Income Statement'!H5 -> 0.02850101 | H26: =-H25/'Q - Income Statement'!I5 -> 0.036673637 | I26: =-I25/'Q - Income Statement'!J5 -> 0.031710847 | J26: =-J25/'Q - Income Statement'!K5 -> 0.031050863 | K26: =-K25/'Income Statement'!O6 -> 0.032001275 | L26: =-L25/'Q - Income Statement'!M5 -> 0.036367474 | M26: =-M25/'Q - Income Statement'!N5 -> 0.037867881 | N26: =-N25/'Q - Income Statement'!O5 -> 0.034021389 | O26: =-O25/'Q - Income Statement'!P5 -> 0.031606008 | P26: =-P25/'Income Statement'!T6 -> 0.03482678 | Q26: =-Q25/'Q - Income Statement'!R5 -> 0.034465944 | R26: =-R25/'Q - Income Statement'!S5 -> 0.027180902 | S26: =-S25/'Q - Income Statement'!T5 -> 0.031950443 | T26: =-T25/'Q - Income Statement'!U5 -> 0.045384264 | U26: =-U25/'Income Statement'!Y6 -> 0.035168158 | V26: =-V25/'Q - Income Statement'!W5 -> 0.049892626 | W26: 0.033 | X26: 0.033 | Y26: 0.033 | Z26: 0.033 | AA26: 0.033 | AB26: 0.033 | AC26: 0.033 | AD26: 0.033 | AE26: 0.033
A28: (+/-) Effect of Exchange Rate | D28: 24 | E28: -287 | F28: -506 | G28: ='Q - CFS Indirect'!C22 -> 50 | H28: ='Q - CFS Indirect'!D22 -> -26 | I28: ='Q - CFS Indirect'!E22 -> -351 | J28: ='Q - CFS Indirect'!F22 -> -94 | K28: -421 | L28: ='Q - CFS Indirect'!H22 -> -125 | M28: ='Q - CFS Indirect'!I22 -> -238 | N28: ='Q - CFS Indirect'!J22 -> 141 | O28: ='Q - CFS Indirect'!K22 -> -390 | P28: -612 | Q28: ='Q - CFS Indirect'!M22 -> 43 | R28: ='Q - CFS Indirect'!N22 -> 401 | S28: ='Q - CFS Indirect'!O22 -> -200 | T28: ='Q - CFS Indirect'!P22 -> -36 | U28: 208 | V28: ='Q - CFS Indirect'!R22 -> -123 | W28: 0 | X28: 0 | Y28: 0 | Z28: 0 | AA28: 0 | AB28: 0 | AC28: 0 | AD28: 0 | AE28: 0
A30: Cash and Cash Equivalents
B31: Changes in Cash | D31: =D20+D15+D7 -> 30112 | E31: =E20+E15+E7 -> 22351 | F31: =F20+F15+F7 -> 20061 | G31: =G20+G15+G7 -> 6495 | H31: =H20+H15+H7 -> 13365 | I31: =I20+I15+I7 -> 11372 | J31: =J20+J15+J7 -> 104199.86 | K31: =K20+K15+K7 -> 24040 | ... Y31: =Y20+Y15+Y7 -> -17609.381 | Z31: =SUM(V31:Y31) -> 79963.913 | AA31: =AA20+AA15+AA7 -> -65915.705 | AB31: =AB20+AB15+AB7 -> -52747.708 | AC31: =AC20+AC15+AC7 -> -40567.046 | AD31: =AD20+AD15+AD7 -> 31747.903 | AE31: =AE20+AE15+AE7 -> 41209.207
B32: Cash BoP | D32: 119675 | E32: =D32+D31 -> 149787 | F32: =E32+E31 -> 172138 | G32: ='Q - CFS Indirect'!C25 -> 113762 | H32: ='Q - CFS Indirect'!D25 -> 120257 | I32: ='Q - CFS Indirect'!E25 -> 133622 | J32: ='Q - CFS Indirect'!F25 -> 144994 | K32: =F32+F31 -> 192199 | L32: ='Q - CFS Indirect'!H25 -> 137802 | M32: ='Q - CFS Indirect'!I25 -> 138835 | N32: ='Q - CFS Indirect'!J25 -> 140886 | O32: ='Q - CFS Indirect'!K25 -> 145442 | P32: =K32+K31 -> 216239 | Q32: ='Q - CFS Indirect'!M25 -> 154959 | R32: ='Q - CFS Indirect'!N25 -> 157637 | S32: ='Q - CFS Indirect'!O25 -> 165579 | T32: ='Q - CFS Indirect'!P25 -> 171668 | U32: =P32+P31 -> 233396 | V32: =U33 -> 126843 | W32: =BS!V10 -> 126840 | X32: =W33 -> 200340.67 | Y32: =X33 -> 193738.29 | Z32: =V33 -> 126843 | AA32: =Z33 -> 176128.91 | AB32: =AA33 -> 110213.21 | AC32: =AB33 -> 57465.5 | AD32: =AC33 -> 16898.453 | AE32: =AD33 -> 48646.356
A33: Cash EoP | D33: =BS!D10 -> 136694 | E33: =BS!E10 -> 139649 | F33: =BS!F10 -> 113762 | G33: =G32+G31 -> 120257 | H33: =H32+H31 -> 133622 | I33: =I32+I31 -> 144994 | J33: =J32+J31 -> 249193.86 | K33: =BS!K10 -> 110916 | L33: =L32+L31 -> 138835 | M33: =M32+M31 -> 140886 | N33: =N32+N31 -> 145442 | O33: =O32+O31 -> 154959 | P33: =BS!P10 -> 95657 | Q33: =Q32+Q31 -> 157637 | R33: =R32+R31 -> 165579 | S33: =S32+S31 -> 171668 | T33: =T32+T31 -> 204760 | U33: =BS!U10 -> 126843 | V33: =V32 -> 126843 | W33: =W31+W32 -> 200340.67 | X33: =X31+X32 -> 193738.29 | Y33: =Y31+Y32 -> 176128.91 | Z33: =Y33 -> 176128.91 | AA33: =AA31+AA32 -> 110213.21 | AB33: =AB31+AB32 -> 57465.5 | AC33: =AC31+AC32 -> 16898.453 | AD33: =AD31+AD32 -> 48646.356 | AE33: =AE31+AE32 -> 89855.563

Sheet Build Up
O1: Hardcode
O2: Formula
O3: Assumption
A5: Build Up | D5: 2020 | E5: 2021 | F5: 1Q22 | G5: 2Q22 | H5: 3Q22 | I5: 4Q22 | J5: 2022 | K5: 1Q23 | L5: 2Q23 | M5: 3Q23 | N5: 4Q23 | O5: 2023 | P5: 1Q24 | Q5: 2Q24 | R5: 3Q24 | S5: 4Q24 | T5: 2024 | U5: 1Q25 | V5: 2Q25 | W5: 3Q25 | X5: 4Q25 | Y5: 2025 | Z5: 1Q26 | AA5: 2Q26 | AB5: 3Q26 | AC5: 4Q26 | AD5: 2026 | AE5: 2027 | AF5: 2028 | AG5: 2029 | AH5: 2030 | AI5: 2031
A6: Revenues | D6: =SUM(D8,D11,D14,D17,D22,D25,D28) -> 182527 | E6: =SUM(E8,E11,E14,E17,E22,E25,E28) -> 257637 | F6: =SUM(F8,F11,F14,F17,F22,F25,F28) -> 68011 | G6: =SUM(G8,G11,G14,G17,G22,G25,G28) -> 69685 | H6: =SUM(H8,H11,H14,H17,H22,H25,H28) -> 69092 | I6: =SUM(I8,I11,I14,I17,I22,I25,I28) -> 76048 | J6: =SUM(J8,J11,J14,J17,J22,J25,J28) -> 282836 | K6: =SUM(K8,K11,K14,K17,K22,K25,K28) -> 69787 | ... AI6: =SUM(AI8,AI11,AI14,AI17,AI22,AI25,AI28) -> 1067907.9
A8: Google Search | D8: 104062 | E8: 148951 | F8: ='Q - Build Up'!C5 -> 39618 | G8: ='Q - Build Up'!D5 -> 40689 | H8: ='Q - Build Up'!E5 -> 39539 | I8: ='Q - Build Up'!F5 -> 42604 | J8: 162450 | K8: ='Q - Build Up'!H5 -> 40359 | L8: ='Q - Build Up'!I5 -> 42628 | M8: ='Q - Build Up'!J5 -> 44026 | N8: ='Q - Build Up'!K5 -> 48020 | O8: 175033 | P8: ='Q - Build Up'!M5 -> 46156 | Q8: ='Q - Build Up'!N5 -> 48509 | R8: ='Q - Build Up'!O5 -> 49385 | S8: ='Q - Build Up'!P5 -> 54034 | T8: 198084 | U8: ='Q - Build Up'!R5 -> 50702 | V8: ='Q - Build Up'!S5 -> 54190 | W8: ='Q - Build Up'!T5 -> 56567 | X8: ='Q - Build Up'!U5 -> 63073 | Y8: 224532 | Z8: ='Q - Build Up'!W5 -> 60399 | AA8: =Z8*(AA9+1) -> 69458.85 | AB8: =AA8*(AB9+1) -> 79877.677 | AC8: =AB8*(AC9+1) -> 91859.329 | AD8: =SUM(Z8:AC8) -> 301594.86 | AE8: =AD8*(AE9+1) -> 361913.83 | AF8: =AE8*(AF9+1) -> 423439.18 | AG8: =AF8*(AG9+1) -> 482720.66 | AH8: =AG8*(AH9+1) -> 540647.14 | AI8: =AH8*(AI9+1) -> 594711.86
B9: y/y (%) | E9: =E8/D8-1 -> 0.43136784 | J9: =J8/E8-1 -> 0.090627119 | K9: =K8/F8-1 -> 0.01870362 | L9: =L8/G8-1 -> 0.047654157 | M9: =M8/H8-1 -> 0.11348289 | N9: =N8/I8-1 -> 0.12712421 | O9: =O8/J8-1 -> 0.077457679 | P9: =P8/K8-1 -> 0.14363587 | Q9: =Q8/L8-1 -> 0.13796096 | ... Z9: =Z8/U8-1 -> 0.19125478 | AA9: =Scenarios!D11 -> 0.15 | AB9: =Scenarios!E11 -> 0.15 | AC9: =Scenarios!F11 -> 0.15 | AE9: =Scenarios!G11 -> 0.2 | AF9: =Scenarios!H11 -> 0.17 | AG9: =Scenarios!I11 -> 0.14 | AH9: =Scenarios!J11 -> 0.12 | AI9: =Scenarios!K11 -> 0.1
A11: Youtube ads | D11: 19772 | E11: 28845 | F11: ='Q - Build Up'!C6 -> 6869 | G11: ='Q - Build Up'!D6 -> 7340 | H11: ='Q - Build Up'!E6 -> 7071 | I11: ='Q - Build Up'!F6 -> 7963 | J11: 29243 | K11: ='Q - Build Up'!H6 -> 6693 | L11: ='Q - Build Up'!I6 -> 7665 | M11: ='Q - Build Up'!J6 -> 7952 | N11: ='Q - Build Up'!K6 -> 9200 | O11: 31510 | P11: ='Q - Build Up'!M6 -> 8090 | Q11: ='Q - Build Up'!N6 -> 8663 | R11: ='Q - Build Up'!O6 -> 8921 | S11: ='Q - Build Up'!P6 -> 10473 | T11: 36147 | U11: ='Q - Build Up'!R6 -> 8927 | V11: ='Q - Build Up'!S6 -> 9796 | W11: ='Q - Build Up'!T6 -> 10261 | X11: ='Q - Build Up'!U6 -> 11383 | Y11: 40367 | Z11: ='Q - Build Up'!W6 -> 9883 | AA11: =Z11*(AA12+1) -> 10772.47 | AB11: =AA11*(AB12+1) -> 11741.992 | AC11: =AB11*(AC12+1) -> 12798.772 | AD11: =SUM(Z11:AC11) -> 45196.234 | AE11: =AD11*(AE12+1) -> 50619.782 | AF11: =AE11*(AF12+1) -> 56187.958 | AG11: =AF11*(AG12+1) -> 62368.633 | AH11: =AG11*(AH12+1) -> 68605.497 | AI11: =AH11*(AI12+1) -> 74779.991
B12: y/y (%) | E12: =E11/D11-1 -> 0.45888125 | J12: =J11/E11-1 -> 0.013797885 | K12: =K11/F11-1 -> -0.025622361 | L12: =L11/G11-1 -> 0.044277929 | M12: =M11/H11-1 -> 0.12459341 | N12: =N11/I11-1 -> 0.15534346 | O12: =O11/J11-1 -> 0.077522826 | P12: =P11/K11-1 -> 0.20872553 | Q12: =Q11/L11-1 -> 0.13020222 | ... Z12: =Z11/U11-1 -> 0.10709085 | AA12: =Scenarios!D19 -> 0.09 | AB12: =Scenarios!E19 -> 0.09 | AC12: =Scenarios!F19 -> 0.09 | AE12: =Scenarios!G19 -> 0.12 | AF12: =Scenarios!H19 -> 0.11 | AG12: =Scenarios!I19 -> 0.11 | AH12: =Scenarios!J19 -> 0.1 | AI12: =Scenarios!K19 -> 0.09
A14: Google Network | D14: 23090 | E14: 31701 | F14: ='Q - Build Up'!C7 -> 8174 | G14: ='Q - Build Up'!D7 -> 8259 | H14: ='Q - Build Up'!E7 -> 7872 | I14: ='Q - Build Up'!F7 -> 8475 | J14: 32780 | K14: ='Q - Build Up'!H7 -> 7496 | L14: ='Q - Build Up'!I7 -> 7850 | M14: ='Q - Build Up'!J7 -> 7669 | N14: ='Q - Build Up'!K7 -> 8297 | O14: 31312 | P14: ='Q - Build Up'!M7 -> 7413 | Q14: ='Q - Build Up'!N7 -> 7444 | R14: ='Q - Build Up'!O7 -> 7548 | S14: ='Q - Build Up'!P7 -> 7954 | T14: 30359 | U14: ='Q - Build Up'!R7 -> 7256 | V14: ='Q - Build Up'!S7 -> 7354 | W14: ='Q - Build Up'!T7 -> 7354 | X14: ='Q - Build Up'!U7 -> 7828 | Y14: 29792 | Z14: ='Q - Build Up'!W7 -> 6971 | AA14: =Z14*(AA15+1) -> 6950.087 | AB14: =AA14*(AB15+1) -> 6929.2367 | AC14: =AB14*(AC15+1) -> 6908.449 | AD14: =SUM(Z14:AC14) -> 27758.773 | AE14: =AD14*(AE15+1) -> 27481.185 | AF14: =AE14*(AF15+1) -> 27261.336 | AG14: =AF14*(AG15+1) -> 27097.768 | AH14: =AG14*(AH15+1) -> 26989.376 | AI14: =AH14*(AI15+1) -> 26935.398
B15: y/y (%) | E15: =E14/D14-1 -> 0.37293201 | J15: =J14/E14-1 -> 0.034036781 | K15: =K14/F14-1 -> -0.082945926 | L15: =L14/G14-1 -> -0.049521734 | M15: =M14/H14-1 -> -0.025787602 | N15: =N14/I14-1 -> -0.02100295 | O15: =O14/J14-1 -> -0.044783405 | P15: =P14/K14-1 -> -0.011072572 | Q15: =Q14/L14-1 -> -0.051719745 | ... Z15: =Z14/U14-1 -> -0.039277839 | AA15: =Scenarios!D67 -> -0.003 | AB15: =Scenarios!E67 -> -0.003 | AC15: =Scenarios!F67 -> -0.003 | AE15: =Scenarios!G67 -> -0.01 | AF15: =Scenarios!H67 -> -0.008 | AG15: =Scenarios!I67 -> -0.006 | AH15: =Scenarios!J67 -> -0.004 | AI15: =Scenarios!K67 -> -0.002
A17: Google Subscriptions | D17: 21711 | E17: 28032 | F17: ='Q - Build Up'!C8 -> 6811 | G17: ='Q - Build Up'!D8 -> 6553 | H17: ='Q - Build Up'!E8 -> 6895 | I17: ='Q - Build Up'!F8 -> 8796 | J17: 29055 | K17: ='Q - Build Up'!H8 -> 7413 | L17: ='Q - Build Up'!I8 -> 8142 | M17: ='Q - Build Up'!J8 -> 8339 | N17: ='Q - Build Up'!K8 -> 10794 | O17: 34688 | P17: ='Q - Build Up'!M8 -> 8739 | Q17: ='Q - Build Up'!N8 -> 9312 | R17: ='Q - Build Up'!O8 -> 10656 | S17: ='Q - Build Up'!P8 -> 11633 | T17: 40340 | U17: ='Q - Build Up'!R8 -> 10379 | V17: ='Q - Build Up'!S8 -> 11203 | W17: ='Q - Build Up'!T8 -> 12870 | X17: ='Q - Build Up'!U8 -> 13578 | Y17: 48030 | Z17: ='Q - Build Up'!W8 -> 12384 | AA17: =Z17*(AA18+1) -> 14117.76 | AB17: =AA17*(AB18+1) -> 16094.246 | AC17: =AB17*(AC18+1) -> 18347.441 | AD17: =SUM(Z17:AC17) -> 60943.447 | AE17: =AD17*(AE18+1) -> 70084.964 | AF17: =AE17*(AF18+1) -> 81298.559 | AG17: =AF17*(AG18+1) -> 95119.314 | AH17: =AG17*(AH18+1) -> 110338.4 | AI17: =AH17*(AI18+1) -> 126889.16
E18: =E17/D17-1 -> 0.29114274 | J18: =J17/E17-1 -> 0.036494007 | K18: =K17/F17-1 -> 0.088386434 | L18: =L17/G17-1 -> 0.24248436 | M18: =M17/H17-1 -> 0.20942712 | N18: =N17/I17-1 -> 0.2271487 | O18: =O17/J17-1 -> 0.19387369 | P18: =P17/K17-1 -> 0.17887495 | Q18: =Q17/L17-1 -> 0.14369934 | ... Z18: =Z17/U17-1 -> 0.19317853 | AA18: =Scenarios!D27 -> 0.14 | AB18: =Scenarios!E27 -> 0.14 | AC18: =Scenarios!F27 -> 0.14 | AE18: =Scenarios!G27 -> 0.15 | AF18: =Scenarios!H27 -> 0.16 | AG18: =Scenarios!I27 -> 0.17 | AH18: =Scenarios!J27 -> 0.16 | AI18: =Scenarios!K27 -> 0.15
A20: Google Services | D20: =SUM(D17,D14,D11,D8) -> 168635 | E20: =SUM(E17,E14,E11,E8) -> 237529 | F20: =SUM(F17,F14,F11,F8) -> 61472 | G20: =SUM(G17,G14,G11,G8) -> 62841 | H20: =SUM(H17,H14,H11,H8) -> 61377 | I20: =SUM(I17,I14,I11,I8) -> 67838 | J20: =SUM(J17,J14,J11,J8) -> 253528 | K20: =SUM(K17,K14,K11,K8) -> 61961 | ... Z20: =SUM(Z17,Z14,Z11,Z8) -> 89637 | AA20: =SUM(AA8,AA11,AA14,AA17) -> 101299.17 | AB20: =SUM(AB8,AB11,AB14,AB17) -> 114643.15 | AC20: =SUM(AC8,AC11,AC14,AC17) -> 129913.99 | AD20: =SUM(AD8,AD11,AD14,AD17) -> 435493.31 | AE20: =SUM(AE8,AE11,AE14,AE17) -> 510099.76 | AF20: =SUM(AF8,AF11,AF14,AF17) -> 588187.03 | AG20: =SUM(AG8,AG11,AG14,AG17) -> 667306.38 | AH20: =SUM(AH8,AH11,AH14,AH17) -> 746580.42 | AI20: =SUM(AI8,AI11,AI14,AI17) -> 823316.41
A22: Google Cloud | D22: 13059 | E22: 19206 | F22: ='Q - Build Up'!C10 -> 5821 | G22: ='Q - Build Up'!D10 -> 6276 | H22: ='Q - Build Up'!E10 -> 6868 | I22: ='Q - Build Up'!F10 -> 7315 | J22: 26280 | K22: ='Q - Build Up'!H10 -> 7454 | L22: ='Q - Build Up'!I10 -> 8031 | M22: ='Q - Build Up'!J10 -> 8411 | N22: ='Q - Build Up'!K10 -> 9192 | O22: 33088 | P22: ='Q - Build Up'!M10 -> 9574 | Q22: ='Q - Build Up'!N10 -> 10347 | R22: ='Q - Build Up'!O10 -> 11353 | S22: ='Q - Build Up'!P10 -> 11955 | T22: 43229 | U22: ='Q - Build Up'!R10 -> 12260 | V22: ='Q - Build Up'!S10 -> 13624 | W22: ='Q - Build Up'!T10 -> 15157 | X22: ='Q - Build Up'!U10 -> 17664 | Y22: 58705 | Z22: ='Q - Build Up'!W10 -> 20028 | AA22: =V22*(1+AA23) -> 17711.2 | AB22: =W22*(1+AB23) -> 19704.1 | AC22: =X22*(1+AC23) -> 22963.2 | AD22: =SUM(Z22:AC22) -> 80406.5 | AE22: =AD22*(1+AE23) -> 120609.75 | AF22: =AE22*(1+AF23) -> 159204.87 | AG22: =AF22*(1+AG23) -> 191045.84 | AH22: =AG22*(1+AH23) -> 219702.72 | AI22: =AH22*(1+AI23) -> 241672.99
A23: y/y(%) | E23: =E22/D22-1 -> 0.47070986 | J23: =J22/E22-1 -> 0.3683224 | K23: =K22/F22-1 -> 0.28053599 | L23: =L22/G22-1 -> 0.27963671 | M23: =M22/H22-1 -> 0.22466511 | N23: =N22/I22-1 -> 0.25659604 | O23: =O22/J22-1 -> 0.25905632 | P23: =P22/K22-1 -> 0.28441105 | Q23: =Q22/L22-1 -> 0.28838252 | ... Z23: =Z22/U22-1 -> 0.63360522 | AA23: =Scenarios!D35 -> 0.3 | AB23: =Scenarios!E35 -> 0.3 | AC23: =Scenarios!F35 -> 0.3 | AE23: =Scenarios!G35 -> 0.5 | AF23: =Scenarios!H35 -> 0.32 | AG23: =Scenarios!I35 -> 0.2 | AH23: =Scenarios!J35 -> 0.15 | AI23: =Scenarios!K35 -> 0.1
A25: Other Bets | D25: 657 | E25: 753 | F25: ='Q - Build Up'!C11 -> 440 | G25: ='Q - Build Up'!D11 -> 193 | H25: ='Q - Build Up'!E11 -> 209 | I25: ='Q - Build Up'!F11 -> 226 | J25: 1068 | K25: ='Q - Build Up'!H11 -> 288 | L25: ='Q - Build Up'!I11 -> 285 | M25: ='Q - Build Up'!J11 -> 297 | N25: ='Q - Build Up'!K11 -> 657 | O25: 1527 | P25: ='Q - Build Up'!M11 -> 495 | Q25: ='Q - Build Up'!N11 -> 365 | R25: ='Q - Build Up'!O11 -> 388 | S25: ='Q - Build Up'!P11 -> 400 | T25: 1648 | U25: ='Q - Build Up'!R11 -> 450 | V25: ='Q - Build Up'!S11 -> 373 | W25: ='Q - Build Up'!T11 -> 344 | X25: ='Q - Build Up'!U11 -> 370 | Y25: 1537 | Z25: ='Q - Build Up'!W11 -> 411 | AA25: =V25*(1+AA26) -> 381.206 | AB25: =W25*(1+AB26) -> 351.568 | AC25: =X25*(1+AC26) -> 378.14 | AD25: =SUM(Z25:AC25) -> 1521.914 | AE25: =AD25*(1+AE26) -> 1582.7906 | AF25: =AE25*(1+AF26) -> 1646.1022 | AG25: =AF25*(1+AG26) -> 1711.9463 | AH25: =AG25*(1+AH26) -> 1780.4241 | AI25: =AH25*(1+AI26) -> 1851.6411
B26: y/y (%) | E26: =E25/D25-1 -> 0.14611872 | J26: =J25/E25-1 -> 0.41832669 | K26: =K25/F25-1 -> -0.34545455 | L26: =L25/G25-1 -> 0.47668394 | M26: =M25/H25-1 -> 0.42105263 | N26: =N25/I25-1 -> 1.9070796 | O26: =O25/J25-1 -> 0.42977528 | P26: =P25/K25-1 -> 0.71875 | Q26: =Q25/L25-1 -> 0.28070175 | ... Z26: =Z25/U25-1 -> -0.086666667 | AA26: 0.022 | AB26: 0.022 | AC26: 0.022 | AE26: 0.04 | AF26: 0.04 | AG26: 0.04 | AH26: 0.04 | AI26: 0.04
A28: Hedging | D28: 176 | E28: 149 | F28: ='Q - Build Up'!C12 -> 278 | G28: ='Q - Build Up'!D12 -> 375 | H28: ='Q - Build Up'!E12 -> 638 | I28: ='Q - Build Up'!F12 -> 669 | J28: 1960 | K28: ='Q - Build Up'!H12 -> 84 | L28: ='Q - Build Up'!I12 -> 3 | M28: ='Q - Build Up'!J12 -> -1 | N28: ='Q - Build Up'!K12 -> 150 | O28: 236 | P28: ='Q - Build Up'!M12 -> 72 | Q28: ='Q - Build Up'!N12 -> 102 | R28: ='Q - Build Up'!O12 -> 17 | S28: ='Q - Build Up'!P12 -> 20 | T28: 211 | U28: ='Q - Build Up'!R12 -> 260 | V28: ='Q - Build Up'!S12 -> -112 | W28: ='Q - Build Up'!T12 -> -207 | X28: ='Q - Build Up'!U12 -> -68 | Y28: -127 | Z28: ='Q - Build Up'!W12 -> -180 | AA28: =AA29*(AA20+AA22+AA25) -> 119.39157 | AB28: =AB29*(AB20+AB22+AB25) -> 134.69882 | AC28: =AC29*(AC20+AC22+AC25) -> 153.25533 | AD28: =SUM(Z28:AC28) -> 227.34572 | AE28: =AE29*(AE20+AE22+AE25) -> 632.2923 | AF28: =AF29*(AF20+AF22+AF25) -> 749.038 | AG28: =AG29*(AG20+AG22+AG25) -> 860.06417 | AH28: =AH29*(AH20+AH22+AH25) -> 968.06357 | AI28: =AI29*(AI20+AI22+AI25) -> 1066.841
B29: As % of Revenue | D29: =D28/D6 -> 0.00096424091 | E29: =E28/E6 -> 0.00057833308 | F29: =F28/F6 -> 0.0040875741 | G29: =G28/G6 -> 0.005381359 | H29: =H28/H6 -> 0.0092340647 | I29: =I28/I6 -> 0.0087970755 | J29: =J28/J6 -> 0.0069298109 | K29: =K28/K6 -> 0.0012036626 | ... Z29: =Z28/Z6 -> -0.0016379122 | AA29: 0.001 | AB29: 0.001 | AC29: 0.001 | AE29: 0.001 | AF29: =AE29 -> 0.001 | AG29: =AF29 -> 0.001 | AH29: =AG29 -> 0.001 | AI29: =AH29 -> 0.001
A31: Operating Income
A32: Operating Income | D32: =SUM(D35,D38,D41,D45) -> 41224 | E32: =SUM(E35,E38,E41,E45) -> 78714 | F32: =SUM(F35,F38,F41,F45) -> 20094 | G32: =SUM(G35,G38,G41,G45) -> 19453 | H32: =SUM(H35,H38,H41,H45) -> 17135 | I32: =SUM(I35,I38,I41,I45) -> 18160 | J32: =SUM(J35,J38,J41,J45) -> 74842 | K32: =SUM(K35,K38,K41,K45) -> 17415 | ... AC32: =SUM(AC35,AC38,AC41,AC45) -> 58702.525 | AD32: =SUM(Z32:AC32) -> 195772.91 | AE32: =SUM(AE35,AE38,AE41,AE45) -> 240561.42 | AF32: =SUM(AF35,AF38,AF41,AF45) -> 291847.53 | AG32: =SUM(AG35,AG38,AG41,AG45) -> 343614.6 | AH32: =SUM(AH35,AH38,AH41,AH45) -> 389037.75 | AI32: =SUM(AI35,AI38,AI41,AI45) -> 431485.97
B33: Margin (%) | D33: =D32/D6 -> 0.22585152 | E33: =E32/E6 -> 0.30552289 | F33: =F32/F6 -> 0.29545221 | G33: =G32/G6 -> 0.2791562 | H33: =H32/H6 -> 0.24800266 | I33: =I32/I6 -> 0.23879655 | J33: =J32/J6 -> 0.26461271 | K33: =K32/K6 -> 0.24954504 | ... Z33: =Z32/Z6 -> 0.36121424
B35: Google Services | D35: 54606 | E35: 91855 | F35: ='Q - Build Up'!C16 -> 21973 | G35: ='Q - Build Up'!D16 -> 21621 | H35: ='Q - Build Up'!E16 -> 18883 | I35: ='Q - Build Up'!F16 -> 20222 | J35: 82699 | K35: ='Q - Build Up'!H16 -> 21737 | L35: ='Q - Build Up'!I16 -> 23454 | M35: ='Q - Build Up'!J16 -> 23937 | N35: ='Q - Build Up'!K16 -> 26730 | O35: 95858 | P35: ='Q - Build Up'!M16 -> 27897 | Q35: ='Q - Build Up'!N16 -> 29674 | R35: ='Q - Build Up'!O16 -> 30856 | S35: ='Q - Build Up'!P16 -> 32836 | T35: 121263 | U35: ='Q - Build Up'!R16 -> 32682 | V35: ='Q - Build Up'!S16 -> 33063 | W35: ='Q - Build Up'!T16 -> 33527 | X35: ='Q - Build Up'!U16 -> 40132 | Y35: 139404 | Z35: ='Q - Build Up'!W16 -> 40589 | AA35: =AA36*AA20 -> 45584.625 | AB35: =AB36*AB20 -> 51589.419 | AC35: =AC36*AC20 -> 58461.296 | AD35: =SUM(Z35:AC35) -> 196224.34 | AE35: =AE36*AE20 -> 229544.89 | AF35: =AF36*AF20 -> 270566.03 | AG35: =AG36*AG20 -> 313634 | AH35: =AH36*AH20 -> 350892.8 | AI35: =AI36*AI20 -> 386958.71
C36: Margin (%) | D36: =D35/D20 -> 0.32381178 | E36: =E35/E20 -> 0.38671068 | F36: =F35/F20 -> 0.35744729 | G36: =G35/G20 -> 0.34405882 | H36: =H35/H20 -> 0.30765596 | I36: =I35/I20 -> 0.29809251 | J36: =J35/J20 -> 0.32619277 | K36: =K35/K20 -> 0.35081745 | ... Z36: =Z35/Z20 -> 0.45281524 | AA36: =Scenarios!D51 -> 0.45 | AB36: =Scenarios!E51 -> 0.45 | AC36: =Scenarios!F51 -> 0.45 | AE36: =Scenarios!G51 -> 0.45 | AF36: =Scenarios!H51 -> 0.46 | AG36: =Scenarios!I51 -> 0.47 | AH36: =Scenarios!J51 -> 0.47 | AI36: =Scenarios!K51 -> 0.47
B38: Google Cloud | D38: -5607 | E38: -3099 | F38: ='Q - Build Up'!C18 -> -706 | G38: ='Q - Build Up'!D18 -> -590 | H38: ='Q - Build Up'!E18 -> -440 | I38: ='Q - Build Up'!F18 -> -186 | J38: -1922 | K38: ='Q - Build Up'!H18 -> 191 | L38: ='Q - Build Up'!I18 -> 395 | M38: ='Q - Build Up'!J18 -> 266 | N38: ='Q - Build Up'!K18 -> 864 | O38: 1716 | P38: ='Q - Build Up'!M18 -> 900 | Q38: ='Q - Build Up'!N18 -> 1172 | R38: ='Q - Build Up'!O18 -> 1947 | S38: ='Q - Build Up'!P18 -> 2093 | T38: 6112 | U38: ='Q - Build Up'!R18 -> 2177 | V38: ='Q - Build Up'!S18 -> 2826 | W38: ='Q - Build Up'!T18 -> 3594 | X38: ='Q - Build Up'!U18 -> 5313 | Y38: 13910 | Z38: ='Q - Build Up'!W18 -> 6598 | AA38: =AA39*AA22 -> 6198.92 | AB38: =AB39*AB22 -> 6699.394 | AC38: =AC39*AC22 -> 7807.488 | AD38: =SUM(Z38:AC38) -> 27303.802 | AE38: =AE39*AE22 -> 41007.315 | AF38: =AF39*AF22 -> 55721.704 | AG38: =AG39*AG22 -> 68776.504 | AH38: =AH39*AH22 -> 81290.007 | AI38: =AI39*AI22 -> 91835.737
C39: Margin (%) | D39: =D38/D22 -> -0.42935906 | E39: =E38/E22 -> -0.16135583 | F39: =F38/F22 -> -0.121285 | G39: =G38/G22 -> -0.094008923 | H39: =H38/H22 -> -0.06406523 | I39: =I38/I22 -> -0.025427204 | J39: =J38/J22 -> -0.073135464 | K39: =K38/K22 -> 0.025623826 | ... Z39: =Z38/Z22 -> 0.32943879 | AA39: =Scenarios!D43 -> 0.35 | AB39: =Scenarios!E43 -> 0.34 | AC39: =Scenarios!F43 -> 0.34 | AE39: =Scenarios!G43 -> 0.34 | AF39: =Scenarios!H43 -> 0.35 | AG39: =Scenarios!I43 -> 0.36 | AH39: =Scenarios!J43 -> 0.37 | AI39: =Scenarios!K43 -> 0.38
B41: Other Bets | D41: -4476 | E41: -5281 | F41: ='Q - Build Up'!C20 -> -835 | G41: ='Q - Build Up'!D20 -> -1339 | H41: ='Q - Build Up'!E20 -> -1225 | I41: ='Q - Build Up'!F20 -> -1237 | J41: -4636 | K41: ='Q - Build Up'!H20 -> -1225 | L41: ='Q - Build Up'!I20 -> -813 | M41: ='Q - Build Up'!J20 -> -1194 | N41: ='Q - Build Up'!K20 -> -863 | O41: -4095 | P41: ='Q - Build Up'!M20 -> -1020 | Q41: ='Q - Build Up'!N20 -> -1134 | R41: ='Q - Build Up'!O20 -> -1116 | S41: ='Q - Build Up'!P20 -> -1174 | T41: -4444 | U41: ='Q - Build Up'!R20 -> -1226 | V41: ='Q - Build Up'!S20 -> -1246 | W41: ='Q - Build Up'!T20 -> -1426 | X41: ='Q - Build Up'!U20 -> -3617 | Y41: -7515 | Z41: ='Q - Build Up'!W20 -> -2100 | AA41: =AA25-AA42 -> -2380.894 | AB41: =AB25-AB42 -> -2686.742 | AC41: =AC25-AC42 -> -2964.001 | AD41: =SUM(Z41:AC41) -> -10131.637 | AE41: =AE25-AE42 -> -11003.045 | AF41: =AF25-AF42 -> -11946.6 | AG41: =AG25-AG42 -> -12968.172 | AH41: =AH25-AH42 -> -14074.103 | AI41: =AI25-AI42 -> -15271.249
C42: Expenses | D42: 5133 | E42: 6034 | F42: =F25-F41 -> 1275 | G42: =G25-G41 -> 1532 | H42: =H25-H41 -> 1434 | I42: =I25-I41 -> 1463 | J42: 5704 | K42: =K25-K41 -> 1513 | L42: =L25-L41 -> 1098 | M42: =M25-M41 -> 1491 | N42: =N25-N41 -> 1520 | O42: 5622 | P42: =P25-P41 -> 1515 | Q42: =Q25-Q41 -> 1499 | R42: =R25-R41 -> 1504 | S42: =S25-S41 -> 1574 | T42: 6092 | U42: =U25-U41 -> 1676 | V42: =V25-V41 -> 1619 | W42: =W25-W41 -> 1770 | X42: =X25-X41 -> 3987 | Y42: 8952 | Z42: =Z25-Z41 -> 2511 | AA42: =Z42*(1+AA43) -> 2762.1 | AB42: =AA42*(1+AB43) -> 3038.31 | AC42: =AB42*(1+AC43) -> 3342.141 | AD42: =SUM(Z42:AC42) -> 11653.551 | AE42: =AD42*(1+AE43) -> 12585.835 | AF42: =AE42*(1+AF43) -> 13592.702 | AG42: =AF42*(1+AG43) -> 14680.118 | AH42: =AG42*(1+AH43) -> 15854.527 | AI42: =AH42*(1+AI43) -> 17122.89
C43: y/y(%) | E43: =E42/D42-1 -> 0.17553088 | J43: =J42/E42-1 -> -0.054690089 | K43: =K42/F42-1 -> 0.18666667 | L43: =L42/G42-1 -> -0.28328982 | M43: =M42/H42-1 -> 0.039748954 | N43: =N42/I42-1 -> 0.038961039 | O43: =O42/J42-1 -> -0.014375877 | P43: =P42/K42-1 -> 0.0013218771 | Q43: =Q42/L42-1 -> 0.36520947 | ... Z43: =Z42/U42-1 -> 0.49821002 | AA43: 0.1 | AB43: 0.1 | AC43: 0.1 | AE43: 0.08 | AF43: 0.08 | AG43: 0.08 | AH43: 0.08 | AI43: 0.08
B45: Alphabet Level | D45: -3299 | E45: -4761 | F45: ='Q - Build Up'!C21 -> -338 | G45: ='Q - Build Up'!D21 -> -239 | H45: ='Q - Build Up'!E21 -> -83 | I45: ='Q - Build Up'!F21 -> -639 | J45: -1299 | K45: ='Q - Build Up'!H21 -> -3288 | L45: ='Q - Build Up'!I21 -> -1198 | M45: ='Q - Build Up'!J21 -> -1666 | N45: ='Q - Build Up'!K21 -> -3034 | O45: -9186 | P45: ='Q - Build Up'!M21 -> -2305 | Q45: ='Q - Build Up'!N21 -> -2287 | R45: ='Q - Build Up'!O21 -> -3166 | S45: ='Q - Build Up'!P21 -> -2783 | T45: -10541 | U45: ='Q - Build Up'!R21 -> -3027 | V45: ='Q - Build Up'!S21 -> -3372 | W45: ='Q - Build Up'!T21 -> -4467 | X45: ='Q - Build Up'!U21 -> -5894 | Y45: -16760 | Z45: ='Q - Build Up'!W21 -> -5391 | AA45: =-AA46*AA6 -> -3585.3289 | AB45: =-AB46*AB6 -> -4045.0056 | AC45: =-AC46*AC6 -> -4602.2576 | AD45: =SUM(Z45:AC45) -> -17623.592 | AE45: =-AE46*AE6 -> -18987.738 | AF45: =-AF46*AF6 -> -22493.611 | AG45: =-AG46*AG6 -> -25827.727 | AH45: =-AH46*AH6 -> -29070.949 | AI45: =-AI46*AI6 -> -32037.237
C46: As % Revenue | D46: =-D45/D6 -> 0.018074038 | E46: =-E45/E6 -> 0.018479489 | F46: =-F45/F6 -> 0.0049697843 | G46: =-G45/G6 -> 0.0034297195 | H46: =-H45/H6 -> 0.0012012968 | I46: =-I45/I6 -> 0.0084025878 | J46: =-J45/J6 -> 0.0045927675 | K46: =-K45/K6 -> 0.047114792 | ... Z46: =-Z45/Z6 -> 0.049055471 | AA46: 0.03 | AB46: 0.03 | AC46: 0.03 | AE46: 0.03 | AF46: 0.03 | AG46: 0.03 | AH46: 0.03 | AI46: 0.03
A48: Total Expenses | D48: =D6-D32 -> 141303 | E48: =E6-E32 -> 178923 | F48: =F6-F32 -> 47917 | G48: =G6-G32 -> 50232 | H48: =H6-H32 -> 51957 | I48: =I6-I32 -> 57888 | J48: =J6-J32 -> 207994 | K48: =K6-K32 -> 52372 | ... AI48: =AI6-AI32 -> 636421.92
B50: Cost of Revenue | D50: ='Income Statement'!D8 -> 84732 | E50: ='Income Statement'!E8 -> 110939 | F50: ='Q - Build Up'!C26 -> 29599 | G50: ='Q - Build Up'!D26 -> 30104 | H50: ='Q - Build Up'!E26 -> 31158 | I50: ='Q - Build Up'!F26 -> 35342 | J50: ='Income Statement'!J8 -> 126203 | K50: ='Q - Build Up'!H26 -> 30612 | L50: ='Q - Build Up'!I26 -> 31916 | M50: ='Q - Build Up'!J26 -> 33229 | N50: ='Q - Build Up'!K26 -> 37575 | O50: ='Income Statement'!O8 -> 133332 | P50: ='Q - Build Up'!M26 -> 33712 | Q50: ='Q - Build Up'!N26 -> 35507 | R50: ='Q - Build Up'!O26 -> 36474 | S50: ='Q - Build Up'!P26 -> 40613 | T50: ='Income Statement'!T8 -> 146306 | U50: ='Q - Build Up'!R26 -> 36361 | V50: ='Q - Build Up'!S26 -> 39039 | W50: ='Q - Build Up'!T26 -> 41369 | X50: ='Q - Build Up'!U26 -> 45766 | Y50: ='Income Statement'!Y8 -> 162535 | Z50: ='Q - Build Up'!W26 -> 41271 | AA50: =AA51*AA48 -> 43331.862 | AB50: =AB51*AB48 -> 48966.555 | AC50: =AC51*AC48 -> 55687.164 | AD50: =AD51*AD48 -> 189263.18 | AE50: =AE51*AE48 -> 230709.54 | AF50: =AF51*AF48 -> 269268.43 | AG50: =AG51*AG48 -> 304178.06 | AH50: =AH51*AH48 -> 341036.4 | AI50: =AI51*AI48 -> 374216.09
C51: As % of Total Expenses | D51: =D50/D48 -> 0.59964757 | E51: =E50/E48 -> 0.62003767 | F51: =F50/F48 -> 0.61771396 | G51: =G50/G48 -> 0.59929925 | H51: =H50/H48 -> 0.5996882 | I51: =I50/I48 -> 0.61052377 | J51: =J50/J48 -> 0.6067627 | K51: =K50/K48 -> 0.58451081 | ... Z51: =Z50/Z48 -> 0.58790598 | AA51: 0.588 | AB51: 0.588 | AC51: 0.588 | AD51: 0.588 | AE51: 0.588 | AF51: 0.588 | AG51: 0.588 | AH51: 0.588 | AI51: 0.588
B53: SG&A | D53: ='Income Statement'!D12 -> 56571 | E53: ='Income Statement'!E12 -> 67984 | F53: ='Q - Build Up'!C27 -> 18318 | G53: ='Q - Build Up'!D27 -> 20128 | H53: ='Q - Build Up'!E27 -> 20799 | I53: ='Q - Build Up'!F27 -> 22546 | J53: ='Income Statement'!J12 -> 81791 | K53: ='Q - Build Up'!H27 -> 21760 | L53: ='Q - Build Up'!I27 -> 20850 | M53: ='Q - Build Up'!J27 -> 22121 | N53: ='Q - Build Up'!K27 -> 25038 | O53: ='Income Statement'!O12 -> 89769 | P53: ='Q - Build Up'!M27 -> 21355 | Q53: ='Q - Build Up'!N27 -> 21810 | R53: ='Q - Build Up'!O27 -> 23273 | S53: ='Q - Build Up'!P27 -> 24884 | T53: ='Income Statement'!T12 -> 91322 | U53: ='Q - Build Up'!R27 -> 23267 | V53: ='Q - Build Up'!S27 -> 26118 | W53: ='Q - Build Up'!T27 -> 29749 | X53: ='Q - Build Up'!U27 -> 32128 | Y53: ='Income Statement'!Y12 -> 111262 | Z53: ='Q - Build Up'!W27 -> 28929 | AA53: =AA54*AA48 -> 30361.781 | AB53: =AB54*AB48 -> 34309.899 | AC53: =AC54*AC48 -> 39018.897 | AD53: =SUM(Z53:AC53) -> 132619.58 | AE53: =AE54*AE48 -> 159299.45 | AF53: =AF54*AF48 -> 185923.44 | AG53: =AG54*AG48 -> 210027.71 | AH53: =AH54*AH48 -> 235477.51 | AI53: =AI54*AI48 -> 258387.3
C54: As % of Total Expenses | D54: =D53/D48 -> 0.40035243 | E54: =E53/E48 -> 0.37996233 | F54: =F53/F48 -> 0.38228604 | G54: =G53/G48 -> 0.40070075 | H54: =H53/H48 -> 0.4003118 | I54: =I53/I48 -> 0.38947623 | J54: =J53/J48 -> 0.3932373 | K54: =K53/K48 -> 0.41548919 | ... Z54: =Z53/Z48 -> 0.41209402 | AA54: 0.412 | AB54: 0.412 | AC54: 0.412 | AE54: 0.406 | AF54: 0.406 | AG54: 0.406 | AH54: 0.406 | AI54: 0.406

Sheet DCF
D1: #VALUE!
D2: Closing Date | E2: =TODAY() -> 46248
I3: DCF Valuation | J3: 2026 | K3: 2027 | L3: 2028 | M3: 2029 | N3: 2030 | O3: 2031 | R3: =G18 -> -0.35436801 | S3: 0.09455 | T3: 0.09955 | U3: 0.10455 | V3: 0.10955 | W3: 0.11455
D4: Current Share Price | G4: {=_FV(D1,"price")} -> 346.36 | I4: Net Revenue | J4: ='Income Statement'!AA6+'Income Statement'!AB6+'Income Statement'!AC6 -> 407753.07 | K4: ='Income Statement'!AE6 -> 632924.59 | L4: ='Income Statement'!AF6 -> 749787.04 | M4: ='Income Statement'!AG6 -> 860924.23 | N4: ='Income Statement'!AH6 -> 969031.63 | O4: ='Income Statement'!AI6 -> 1067907.9 | R4: 0.06
D5: Shares Outstanidng (Mn) | G5: {=_FV(D1,"Shares outstanding",TRUE)/1000000} -> 12230 | I5: % (y/y) | L5: =L4/K4 -> 1.1846388 | M5: =M4/L4 -> 1.148225 | N5: =N4/M4 -> 1.1255713 | O5: =O4/N4 -> 1.1020362 | R5: 0.065
D6: (-) Net Debt (2026e) | G6: ='Debt Schedule'!V9-BS!V9 -> -213753 | R6: 0.07
I7: EBIT | J7: ='Income Statement'!AA17+'Income Statement'!AB17+'Income Statement'!AC17 -> 156076.91 | K7: ='Income Statement'!AE17 -> 240561.42 | L7: ='Income Statement'!AF17 -> 291847.53 | M7: ='Income Statement'!AG17 -> 343614.6 | N7: ='Income Statement'!AH17 -> 389037.75 | O7: ='Income Statement'!AI17 -> 431485.97 | R7: 0.075
D8: FCFF Target Price | I8: (%) Tax | J8: ='Income Statement'!AD28 -> 0.19162404 | K8: ='Income Statement'!AE28 -> 0.19162404 | L8: ='Income Statement'!AF28 -> 0.19162404 | M8: ='Income Statement'!AG28 -> 0.19162404 | N8: ='Income Statement'!AH28 -> 0.19162404 | O8: ='Income Statement'!AI28 -> 0.19162404 | R8: 0.08
D9: Target Price | G9: =G14/G5 -> 251.04979 | I9: NOPAT | J9: =J7*(1-J8) -> 126168.82 | K9: =K7*(1-K8) -> 194464.07 | L9: =L7*(1-L8) -> 235922.53 | M9: =M7*(1-M8) -> 277769.79 | N9: =N7*(1-N8) -> 314488.77 | O9: =O7*(1-O8) -> 348802.88
D10: Upside (%) | G10: =G9/G4-1 -> -0.27517673 | I10: (+) D&A | J10: ='CFS - Estimates'!W9+'CFS - Estimates'!X9+'CFS - Estimates'!Y9 -> 20387.654 | K10: ='CFS - Estimates'!AA9 -> 31646.23 | L10: ='CFS - Estimates'!AB9 -> 37489.352 | M10: ='CFS - Estimates'!AC9 -> 43046.212 | N10: ='CFS - Estimates'!AD9 -> 48451.581 | O10: ='CFS - Estimates'!AE9 -> 53395.394 | R10: =G18 -> -0.35436801 | X10: Referenciar o build up no crescimento da Cloude
I11: (-) CapEx | J11: ='CFS - Estimates'!W17+'CFS - Estimates'!X17+'CFS - Estimates'!Y17 -> -171788.59 | K11: ='CFS - Estimates'!AA17 -> -253169.84 | L11: ='CFS - Estimates'!AB17 -> -262425.46 | M11: ='CFS - Estimates'!AC17 -> -258277.27 | N11: ='CFS - Estimates'!AD17 -> -193806.33 | O11: ='CFS - Estimates'!AE17 -> -160186.18 | R11: 0.06
I12: (+/-) ΔOWC | J12: ='CFS - Estimates'!W10+'CFS - Estimates'!X10+'CFS - Estimates'!Y10 -> -3443.389 | K12: ='CFS - Estimates'!AA10 -> 913.76001 | L12: ='CFS - Estimates'!AB10 -> 1636.3012 | M12: ='CFS - Estimates'!AC10 -> 519.48722 | N12: ='CFS - Estimates'!AD10 -> 2213.4781 | O12: ='CFS - Estimates'!AE10 -> 1711.5321 | P12: TV - PGM | R12: 0.065
D13: Total Enterprise Value | G13: =SUM(J19:P19) -> 2856585.9 | I13: Free Cash Flow to Firm | J13: =SUM(J9:J12) -> -28675.497 | K13: =SUM(K9:K12) -> -26145.774 | L13: =SUM(L9:L12) -> 12622.715 | M13: =SUM(M9:M12) -> 63058.214 | N13: =SUM(N9:N12) -> 171347.5 | O13: =SUM(O9:O12) -> 243723.63 | P13: =G28 -> 4441192.7 | R13: 0.07
D14: Total Equity Value | G14: =G13-G6 -> 3070338.9 | I14: Date | J14: =TODAY() -> 46248 | K14: 46752 | L14: 47118 | M14: 47483 | N14: 47848 | O14: 48213 | R14: 0.075
I15: Discount Year (FCFF) | J15: 0.5 | K15: 1.5 | L15: 2.5 | M15: 3.5 | N15: 4.5 | O15: 5.5 | R15: 0.08
D16: FCFE Target Price | I16: Discount Factor (FCFF) | J16: =1/(1+J33)^J15 -> 0.95223618 | K16: =1/(1+K33)^K15 -> 0.86361515 | L16: =1/(1+L33)^L15 -> 0.78341713 | M16: =1/(1+M33)^M15 -> 0.7107759 | N16: =1/(1+N33)^N15 -> 0.64491084 | O16: =1/(1+O33)^O15 -> 0.58512437 | P16: =O16 -> 0.58512437
D17: Target Price | G17: =G21/G5 -> 223.6211 | I17: Discount Year (FCFE) | J17: 0.5 | K17: 1.5 | L17: 2.5 | M17: 3.5 | N17: 4.5 | O17: 5.5
D18: Upside (%) | G18: =(G17/G4)-1 -> -0.35436801 | I18: Discount Factor (FCFE) | J18: =1/(1+J31)^J17 -> 0.95149675 | K18: =1/(1+K31)^K17 -> 0.86143384 | L18: =1/(1+L31)^L17 -> 0.77989574 | M18: =1/(1+M31)^M17 -> 0.70607555 | N18: =1/(1+N31)^N17 -> 0.63924272 | O18: =1/(1+O31)^O17 -> 0.57873588 | P18: =1/(1+O31)^O17 -> 0.57873588
I19: DCF (FCFF) | J19: =J16*J13 -> -27305.846 | K19: =K16*K13 -> -22579.887 | L19: =L16*L13 -> 9888.8511 | M19: =M16*M13 -> 44820.259 | N19: =N16*N13 -> 110503.86 | O19: =O16*O13 -> 142608.63 | P19: =P13*P16 -> 2598650
I20: (+/-) Net Borrowings | J20: ='CFS - Estimates'!W22+'CFS - Estimates'!X22+'CFS - Estimates'!Y22 -> 12216.095 | K20: ='CFS - Estimates'!AA22 -> 8971.7095 | L20: ='CFS - Estimates'!AB22 -> 7895.1044 | M20: ='CFS - Estimates'!AC22 -> 6395.0345 | N20: ='CFS - Estimates'!AD22 -> 4519.1577 | O20: ='CFS - Estimates'!AE22 -> 2349.962
D21: Total Equity Value | G21: =SUM(J23:P23) -> 2734886 | I21: (-) Financial Expenses | J21: =('Income Statement'!AA20+'Income Statement'!AB20+'Income Statement'!AC20)*(1-'Discount Factor'!L6) -> -2029.312 | K21: ='Income Statement'!AE20*(1-'Discount Factor'!L6) -> -3168.7971 | L21: ='Income Statement'!AF20*(1-'Discount Factor'!L6) -> -3422.3009 | M21: ='Income Statement'!AG20*(1-'Discount Factor'!L6) -> -3627.639 | N21: ='Income Statement'!AH20*(1-'Discount Factor'!L6) -> -3772.7445 | O21: ='Income Statement'!AI20*(1-'Discount Factor'!L6) -> -3848.1994 | P21: TV - PGM
I22: Free Cash Flow to Equity | J22: =J21+J20+J13 -> -18488.714 | K22: =K21+K20+K13 -> -20342.862 | L22: =L21+L20+L13 -> 17095.518 | M22: =M21+M20+M13 -> 65825.61 | N22: =N21+N20+N13 -> 172093.91 | O22: =O21+O20+O13 -> 242225.39 | P22: =G32*(1+G34)/(G33-G34) -> 4250638.6
D23: Terminal Value FCFF | I23: DCF (FCFE) | J23: =J22*J18 -> -17591.951 | K23: =K22*K18 -> -17524.03 | L23: =L22*L18 -> 13332.722 | M23: =M22*M18 -> 46477.853 | N23: =N22*N18 -> 110009.78 | O23: =O22*O18 -> 140184.52 | P23: =P22*P18 -> 2459997.1
D24: Perpetuity Growth Model
D25: FCFF (2031e) | G25: =O13 -> 243723.63 | I25: WACC Calculation
D26: WACC | G26: =J33 -> 0.10283526 | I26: Capital Structure
D27: g | G27: =Scenarios!M9 -> 0.045 | I27: Market Capitalization (mn) | J27: =G4*G5 -> 4235982.8 | K27: =G4*G5 -> 4235982.8 | L27: =G4*G5 -> 4235982.8 | M27: =G4*G5 -> 4235982.8 | N27: =G4*G5 -> 4235982.8 | O27: =G4*G5 -> 4235982.8
A28: (usando WACC de 2031) | D28: Terminal Value FCFF | G28: =G25*(1+G27)/(O33-G27) -> 4441192.7 | I28: Debt (mn) | J28: ='Debt Schedule'!Z10 -> 102700.1 | K28: ='Debt Schedule'!AA10 -> 111671.8 | L28: ='Debt Schedule'!AB10 -> 119566.91 | M28: ='Debt Schedule'!AC10 -> 125961.94 | N28: ='Debt Schedule'!AD10 -> 130481.1 | O28: ='Debt Schedule'!AE10 -> 132831.06
I29: E/D+E | J29: =J27/(J27+J28) -> 0.9763292 | K29: =K27/(K27+K28) -> 0.97431447 | L29: =L27/(L27+L28) -> 0.97254838 | M29: =M27/(M27+M28) -> 0.97112253 | N29: =N27/(N27+N28) -> 0.97011744 | O29: =O27/(O27+O28) -> 0.96959562
D30: Terminal Value FCFE | I30: D/D+E | J30: =J28/(J28+J27) -> 0.0236708 | K30: =K28/(K28+K27) -> 0.025685528 | L30: =L28/(L28+L27) -> 0.027451623 | M30: =M28/(M28+M27) -> 0.028877473 | N30: =N28/(N28+N27) -> 0.029882556 | O30: =O28/(O28+O27) -> 0.030404377
D31: Perpetuity Growth Model | I31: Cost of Equity (Ke') | J31: ='Discount Factor'!I9 -> 0.10455 | K31: ='Discount Factor'!I9 -> 0.10455 | L31: ='Discount Factor'!I9 -> 0.10455 | M31: ='Discount Factor'!I9 -> 0.10455 | N31: ='Discount Factor'!I9 -> 0.10455 | O31: ='Discount Factor'!I9 -> 0.10455
D32: FCFE (2031e) | G32: =O22 -> 242225.39 | I32: Cost of Debt (Kd') | J32: ='Discount Factor'!L7 -> 0.032108983 | K32: ='Discount Factor'!L7 -> 0.032108983 | L32: ='Discount Factor'!L7 -> 0.032108983 | M32: ='Discount Factor'!L7 -> 0.032108983 | N32: ='Discount Factor'!L7 -> 0.032108983 | O32: ='Discount Factor'!L7 -> 0.032108983
D33: Ke | G33: ='Discount Factor'!I9 -> 0.10455 | I33: WACC | J33: =(J32*J30)+(J31*J29) -> 0.10283526 | K33: =(K32*K30)+(K31*K29) -> 0.10268931 | L33: =(L32*L30)+(L31*L29) -> 0.10256138 | M33: =(M32*M30)+(M31*M29) -> 0.10245809 | N33: =(N32*N30)+(N31*N29) -> 0.10238528 | O33: =(O32*O30)+(O31*O29) -> 0.10234748
D34: g | G34: =Scenarios!M9 -> 0.045
D35: Terminal Value FCFE | G35: =G32*(1+G34)/(G33-G34) -> 4250638.6
D37: TV FCFF Contribution
D38: =P19/G28 -> 0.58512437
D40: TV FCFE Contribution
D41: =P23/G35 -> 0.57873588

Sheet Discount Factor
F4: Cost of Equity (Ke) | K4: Cost of Debt (Kd)
F5: Risk Free Rate (US 10Y) | I5: 0.046 | K5: Avg Debt Cost (2026e) | L5: ='Debt Compostion'!E15 -> 0.039720358
F6: β | I6: 1.25 | K6: Effective Tax Rate (%) | L6: ='Income Statement'!AA28 -> 0.19162404
F7: Equity Risk Premium (Damodaran) | I7: 0.045 | K7: Kd (post-tax) | L7: =L5*(1-L6) -> 0.032108983
F8: CRP (Damodaran) | I8: 0.0023
F9: Ke | I9: =I5+(I6*I7)+I8 -> 0.10455
F15: Risk Free Rate | G15: https://finance.yahoo.com/quote/%5ETNX/
F16: Equity Risk Premium | G16: https://www.statista.com/statistics/664840/average-market-risk-premium-usa/
F17: Country Risk Premium | G17: https://pages.stern.nyu.edu/~adamodar/New_Home_Page/datafile/ctryprem.html

Sheet Debt Schedule
K1: Hardcode
K2: Formula
K3: Assumption
A5: Debt Schedule (Mn USD) | D5: 2020 | E5: 2021 | F5: 2022 | G5: 1Q23 | H5: 2Q23 | I5: 3Q23 | J5: 4Q23 | K5: 2023 | L5: 1Q24 | M5: 2Q24 | N5: 3Q24 | O5: 4Q24 | P5: 2024 | Q5: 1Q25 | R5: 2Q25 | S5: 3Q25 | T5: 4Q25 | U5: 2025 | V5: 1Q26 | W5: 2Q26 | X5: 3Q26 | Y5: 4Q26 | Z5: 2026 | AA5: 2027 | AB5: 2028 | AC5: 2029 | AD5: 2030 | AE5: 2031
A7: T - 10y | D7: =Macro!P7/100 -> 0.0093 | E7: =Macro!Q7/100 -> 0.0147 | F7: =Macro!R7/100 -> 0.0388 | K7: =Macro!S7/100 -> 0.0388 | P7: =Macro!T7/100 -> 0.0458 | U7: =Macro!U7/100 -> 0.0418 | Z7: =Macro!V7/100 -> 0.0449875 | AA7: =Macro!W7/100 -> 0.0449875 | AB7: =Macro!X7/100 -> 0.0449875 | AC7: =Macro!Y7/100 -> 0.0449875 | AD7: =Macro!Z7/100 -> 0.0449875 | AE7: =AD7 -> 0.0449875
A8: Average Debt Cost | D8: =D16 -> 0.0096899225 | E8: =E16 -> 0.023351556 | F8: =F16 -> 0.024284062 | G8: =G16 -> 0.005840695 | H8: =H16 -> 0.003137541 | I8: =I16 -> 0.0084173863 | J8: =J16 -> 0.0052063684 | K8: =K16 -> 0.023240021 | ... V8: =V16 -> 0.0068773306
A10: Total Debt | D10: =SUM(D12,D23) -> 25078 | E10: =SUM(E12,E23) -> 26206 | F10: =SUM(F12,F23) -> 27202 | G10: =SUM(G12,G23) -> 26496 | H10: =SUM(H12,H23) -> 26451 | I10: =SUM(I12,I23) -> 26331 | J10: =SUM(J12,J23) -> 25713 | K10: =SUM(K12,K23) -> 25713 | ... V10: =SUM(V12,V23) -> 90484 | W10: =W12+W23 -> 94359.05 | X10: =X12+X23 -> 98427.853 | Y10: =Y12+Y23 -> 102700.1 | Z10: =Z12+Z23 -> 102700.1 | AA10: =AA12+AA23 -> 111671.8 | AB10: =AB12+AB23 -> 119566.91 | AC10: =AC12+AC23 -> 125961.94 | AD10: =AD12+AD23 -> 130481.1 | AE10: =AE12+AE23 -> 132831.06
A12: Long Term Debt | D12: =BS!D30 -> 13932 | E12: =BS!E30 -> 14817 | F12: =BS!F30 -> 14701 | G12: =BS!G30 -> 13697 | H12: =BS!H30 -> 13705 | I12: =BS!I30 -> 13781 | J12: =BS!J30 -> 13253 | K12: =BS!K30 -> 13253 | ... V12: =BS!V30 -> 77501 | W12: =V12*(1+W13) -> 81376.05 | X12: =W12*(1+X13) -> 85444.853 | Y12: =X12*(1+Y13) -> 89717.095 | Z12: =Y12 -> 89717.095 | AA12: =Z12*(1+AA13) -> 98688.805 | AB12: =AA12*(1+AB13) -> 106583.91 | AC12: =AB12*(1+AC13) -> 112978.94 | AD12: =AC12*(1+AD13) -> 117498.1 | AE12: =AD12*(1+AE13) -> 119848.06
B13: y/y(%) | E13: =E12/D12-1 -> 0.063522825 | F13: =F12/E12-1 -> -0.0078288452 | K13: =K12/F12-1 -> -0.098496701 | L13: =L12/G12-1 -> -0.034241075 | M13: =M12/H12-1 -> -0.034075155 | N13: =N12/I12-1 -> -0.10768449 | O13: =O12/J12-1 -> -0.17882744 | P13: =P12/K12-1 -> -0.17882744 | Q13: =Q12/L12-1 -> -0.17704868 | R13: =R12/M12-1 -> 0.78327542 | ... U13: =U12/P12-1 -> 3.2770376 | V13: =V12/U12-1 -> 0.66500526 | W13: 0.05 | X13: 0.05 | Y13: 0.05 | AA13: 0.1 | AB13: =AA13-2% -> 0.08 | AC13: =AB13-2% -> 0.06 | AD13: =AC13-2% -> 0.04 | AE13: =AD13-2% -> 0.02
A15: Debt Expenses | D15: ='Income Statement'!D20 -> -135 | E15: ='Income Statement'!E20 -> -346 | F15: ='Income Statement'!J20 -> -357 | G15: ='Income Statement'!K20 -> -80 | H15: ='Income Statement'!L20 -> -43 | I15: ='Income Statement'!M20 -> -116 | J15: ='Income Statement'!N20 -> -69 | K15: ='Income Statement'!O20 -> -308 | L15: ='Income Statement'!P20 -> -94 | M15: ='Income Statement'!Q20 -> -67 | ... V15: ='Income Statement'!Z20 -> -533 | W15: =-W16*W12 -> -796.30662 | X15: =-X16*X12 -> -836.12195 | Y15: =-Y16*Y12 -> -877.92805 | Z15: =SUM(V15:Y15) -> -3043.3566 | AA15: =-AA16*AA12 -> -3919.9547 | AB15: =-AB16*AB12 -> -4233.5511 | AC15: =-AC16*AC12 -> -4487.5641 | AD15: =-AD16*AD12 -> -4667.0667 | AE15: =-AE16*AE12 -> -4760.408
B16: Interest Debt | D16: =-D15/D12 -> 0.0096899225 | E16: =-E15/E12 -> 0.023351556 | F16: =-F15/F12 -> 0.024284062 | G16: =-G15/G12 -> 0.005840695 | H16: =-H15/H12 -> 0.003137541 | I16: =-I15/I12 -> 0.0084173863 | J16: =-J15/J12 -> 0.0052063684 | K16: =-K15/K12 -> 0.023240021 | ... V16: =-V15/V12 -> 0.0068773306 | W16: =(1+AA16)^(1/4)-1 -> 0.0097855158 | X16: =(1+AB16)^(1/4)-1 -> 0.0097855158 | Y16: =(1+AC16)^(1/4)-1 -> 0.0097855158 | AA16: ='Debt Compostion'!E15 -> 0.039720358 | AB16: =AA16 -> 0.039720358 | AC16: =AB16 -> 0.039720358 | AD16: =AC16 -> 0.039720358 | AE16: =AD16 -> 0.039720358
A18: Financial Income | D18: ='Income Statement'!D21 -> 1865 | E18: ='Income Statement'!E21 -> 1499 | F18: ='Income Statement'!J21 -> 2174 | G18: ='Income Statement'!K21 -> 797 | H18: ='Income Statement'!L21 -> 892 | I18: ='Income Statement'!M21 -> 1066 | J18: ='Income Statement'!N21 -> 930 | K18: ='Income Statement'!O21 -> 3685 | L18: ='Income Statement'!P21 -> 1061 | M18: ='Income Statement'!Q21 -> 1090 | ... V18: ='Income Statement'!Z21 -> 1381 | W18: =W19*BS!W10 -> 2216.1618 | X18: =X19*BS!X10 -> 2143.1266 | Y18: =Y19*BS!Y10 -> 1948.3322 | Z18: =SUM(V18:Y18) -> 7688.6207 | AA18: =AA19*BS!AA10 -> 4958.2167 | AB18: =AB19*BS!AB10 -> 2585.2292 | AC18: =AC19*BS!AC10 -> 760.21916 | AD18: =AD19*BS!AD10 -> 2188.478 | AE18: =AE19*BS!AE10 -> 4042.3771
B19: Interest on Cash | D19: =D18/BS!D10 -> 0.013643613 | E19: =E18/BS!E10 -> 0.010734055 | F19: =F18/BS!F10 -> 0.019110072 | G19: =G18/BS!G10 -> 0.0069242932 | H19: =H18/BS!H10 -> 0.0075381131 | I19: =I18/BS!I10 -> 0.0088881477 | J19: =J18/BS!J10 -> 0.0083847236 | K19: =K18/BS!K10 -> 0.03322334 | ... V19: =V18/BS!V10 -> 0.010887733 | W19: =(1+AA19)^(1/4)-1 -> 0.011061967 | X19: =W19 -> 0.011061967 | Y19: =X19 -> 0.011061967 | AA19: =AA7 -> 0.0449875 | AB19: =AB7 -> 0.0449875 | AC19: =AC7 -> 0.0449875 | AD19: =AD7 -> 0.0449875 | AE19: =AE7 -> 0.0449875
A21: Lease
A23: Lease | D23: =BS!D31 -> 11146 | E23: =BS!E31 -> 11389 | F23: =BS!F31 -> 12501 | G23: =BS!G31 -> 12799 | H23: =BS!H31 -> 12746 | I23: =BS!I31 -> 12550 | J23: =BS!J31 -> 12460 | K23: =BS!K31 -> 12460 | ... V23: =BS!V31 -> 12983 | W23: =V23 -> 12983 | X23: =W23 -> 12983 | Y23: =X23 -> 12983 | Z23: =Y23 -> 12983 | AA23: =Z23 -> 12983 | AB23: =AA23 -> 12983 | AC23: =AB23 -> 12983 | AD23: =AC23 -> 12983 | AE23: =AD23 -> 12983
B24: Lease Cost | D24: -2886 | E24: -3425 | F24: -3738 | G24: =K24/4 -> -1262 | H24: =G24 -> -1262 | I24: =H24 -> -1262 | J24: =I24 -> -1262 | K24: -5048 | L24: =P24/4 -> -1293.25 | M24: =L24 -> -1293.25 | N24: =M24 -> -1293.25 | O24: =N24 -> -1293.25 | P24: -5173 | Q24: =U24/4 -> -1425.5 | R24: =Q24 -> -1425.5 | S24: =R24 -> -1425.5 | T24: =S24 -> -1425.5 | U24: -5702 | V24: -5702 | W24: =T24 -> -1425.5 | X24: =W24 -> -1425.5 | Y24: =X24 -> -1425.5 | Z24: =V24 -> -5702 | AA24: =Z24 -> -5702 | AB24: =AA24 -> -5702 | AC24: =AB24 -> -5702 | AD24: =AC24 -> -5702 | AE24: =AD24 -> -5702

Sheet Debt Compostion
D5: Debt | E5: Effective Interest Rate | F5: Value
D6: 2016 U.S. Dollar Notes | E6: 0.0223 | F6: 2000
D7: 2020 U.S. Dollar Notes | E7: 0.0166 | F7: 9000
D8: 2025 U.S. Dollar Notes | E8: 0.0489 | F8: 5000
D9: 2025 U.S. Dollar Notes | E9: 0.0492 | F9: 17500
D10: 2025 Euro Notes | E10: 0.0331 | F10: 7939.5283
D11: 2025 Euro Notes | E11: 0.0344 | F11: 7645.4717
D12: 2026 U.S. Dollar Notes | E12: 0.047 | F12: 20000
D13: 2026 Sterling Notes | E13: 0.0513 | F13: 7310
D14: 2026 Swiss Franc Notes | E14: 0.0121 | F14: 3833
D15: Weighted-averege | E15: =SUMPRODUCT(F6:F14,E6:E14)/F15 -> 0.039720358 | F15: =SUM(F6:F14) -> 80228

Sheet CapEx & D&A 
K1: Hardcode
K2: Formula
K3: Assumption
A5: CapEx & D&A (Mn USD) | D5: 2020 | E5: 2021 | F5: 2022 | G5: 1Q23 | H5: 2Q23 | I5: 3Q23 | J5: 4Q23 | K5: 2023 | L5: 1Q24 | M5: 2Q24 | N5: 3Q24 | O5: 4Q24 | P5: 2024 | Q5: 1Q25 | R5: 2Q25 | S5: 3Q25 | T5: 4Q25 | U5: 2025 | V5: 1Q26 | W5: 2Q26 | X5: 3Q26 | Y5: 4Q26 | Z5: 2026 | AA5: 2027 | AB5: 2028 | AC5: 2029 | AD5: 2030 | AE5: 2031
A6: D&A | D6: ='CFS - Estimates'!D9 -> 13697 | E6: ='CFS - Estimates'!E9 -> 12441 | F6: ='CFS - Estimates'!F9 -> 15928 | G6: ='CFS - Estimates'!G9 -> 3186 | H6: ='CFS - Estimates'!H9 -> 3397 | I6: ='CFS - Estimates'!I9 -> 3800 | J6: ='CFS - Estimates'!J9 -> 1563 | K6: ='CFS - Estimates'!K9 -> 11946 | ... V6: ='CFS - Estimates'!V9 -> 6482 | W6: =W7*W8 -> 5975.5482 | X6: =X7*X8 -> 6741.676 | Y6: =Y7*Y8 -> 7670.4293 | Z6: =SUM(V6:Y6) -> 26869.654 | AA6: =AA7*AA8 -> 31646.23 | AB6: =AB7*AB8 -> 37489.352 | AC6: =AC7*AC8 -> 43046.212 | AD6: =AD7*AD8 -> 48451.581 | AE6: =AE7*AE8 -> 53395.394
B7: Revenue | D7: ='Income Statement'!D6 -> 182527 | E7: ='Income Statement'!E6 -> 257637 | F7: ='Income Statement'!J6 -> 282836 | G7: ='Income Statement'!K6 -> 69787 | H7: ='Income Statement'!L6 -> 74604 | I7: ='Income Statement'!M6 -> 76693 | J7: ='Income Statement'!N6 -> 86310 | K7: ='Income Statement'!O6 -> 307394 | L7: ='Income Statement'!P6 -> 80539 | M7: ='Income Statement'!Q6 -> 84742 | ... AE7: ='Income Statement'!AI6 -> 1067907.9
B8: D&A as (%) of Revenue | D8: =D6/D7 -> 0.075040953 | E8: =E6/E7 -> 0.048288872 | F8: =F6/F7 -> 0.056315321 | G8: =G6/G7 -> 0.045653202 | H8: =H6/H7 -> 0.045533752 | I8: =I6/I7 -> 0.049548199 | J8: =J6/J7 -> 0.018109141 | K8: =K6/K7 -> 0.038862177 | ... V8: =V6/V7 -> 0.058983039 | W8: 0.05 | X8: 0.05 | Y8: 0.05 | AA8: 0.05 | AB8: 0.05 | AC8: 0.05 | AD8: 0.05 | AE8: 0.05
A10: PP&E | D10: =BS!D16 -> 84749 | E10: =BS!E16 -> 97599 | F10: =BS!F16 -> 112668 | G10: =BS!G16 -> 117560 | H10: =BS!H16 -> 121208 | I10: =BS!I16 -> 125705 | J10: =BS!J16 -> 134345 | K10: =BS!K16 -> 134345 | ... V10: =BS!V16 -> 281020 | W10: =V10+W13-W6 -> 319263.51 | X10: =W10+X13-X6 -> 366455.24 | Y10: =X10+Y13-Y6 -> 432420.93 | Z10: =Y10 -> 432420.93 | AA10: =Z10+AA13-AA6 -> 653944.54 | AB10: =AA10+AB13-AB6 -> 878880.65 | AC10: =AB10+AC13-AC6 -> 1094111.7 | AD10: =AC10+AD13-AD6 -> 1239466.5 | AE10: =AD10+AE13-AE6 -> 1346257.2
A13: CapEx | E13: =E10-D10+E6 -> 25291 | F13: =F10-E10+F6 -> 30997 | G13: =G10-F10+G6 -> 8078 | H13: =H10-G10+H6 -> 7045 | I13: =I10-H10+I6 -> 8297 | J13: =J10-I10+J6 -> 10203 | K13: =SUM(G13:J13) -> 33623 | L13: =L10-K10+L6 -> 12250 | M13: =M10-L10+M6 -> 11681 | N13: =N10-M10+N6 -> 14100 | O13: =O10-N10+O6 -> 13971 | P13: =SUM(L13:O13) -> 52002 | Q13: =Q10-P10+Q6 -> 18513 | R13: =R10-Q10+R6 -> 23167 | S13: =S10-R10+S6 -> 26167 | T13: =T10-S10+T6 -> 28850 | U13: =SUM(Q13:T13) -> 96697 | V13: =V10-U10+V6 -> 40905 | W13: =W14*W7 -> 44219.057 | X13: =X14*X7 -> 53933.408 | Y13: =Y14*Y7 -> 73636.121 | Z13: =SUM(V13:Y13) -> 212693.59 | AA13: =AA14*AA7 -> 253169.84 | AB13: =AB14*AB7 -> 262425.46 | AC13: =AC14*AC7 -> 258277.27 | AD13: =AD14*AD7 -> 193806.33 | AE13: =AE14*AE7 -> 160186.18
B14: CapEx as (%) of Revenue | E14: =E13/E7 -> 0.098165248 | F14: =F13/F7 -> 0.10959355 | G14: =G13/G7 -> 0.11575222 | H14: =H13/H7 -> 0.094431934 | I14: =I13/I7 -> 0.10818458 | J14: =J13/J7 -> 0.11821342 | K14: =K13/K7 -> 0.10938079 | L14: =L13/L7 -> 0.15210022 | ... V14: =V13/V7 -> 0.37221555 | W14: =Scenarios!D59 -> 0.37 | X14: =Scenarios!E59 -> 0.4 | Y14: =Scenarios!F59 -> 0.48 | AA14: =Scenarios!G59 -> 0.4 | AB14: =Scenarios!H59 -> 0.35 | AC14: =Scenarios!I59 -> 0.3 | AD14: =Scenarios!J59 -> 0.2 | AE14: =Scenarios!K59 -> 0.15

Sheet Multiplos base
G6: EV/EBITDA | K6: EV/SALES | O6: P/E
G7: FY26 | H7: FY27 | I7: FY28 | K7: FY26 | L7: FY27 | M7: FY28 | O7: FY26 | P7: FY27 | Q7: FY28
F8: Meta Platforms | G8: 10.99 | H8: 9.01 | I8: 7.31 | K8: 6.2 | L8: 5.17 | M8: 4.4 | O8: 19.01 | P8: 17.82 | Q8: 15.19
F9: Amazon.com | G9: 12.41 | H9: 9.76 | I9: 7.7 | K9: 3.2 | L9: 2.83 | M9: 2.48 | O9: 27.29 | P9: 23.58 | Q9: 18.43
F10: Snap | G10: 6.55 | H10: 5.28 | I10: 4.85 | K10: 1.23 | L10: 1.12 | M10: 1.03 | O10: 7.01 | P10: 5.91 | Q10: 4.86
F11: Netflix | G11: 17 | H11: 14.44 | I11: 12.49 | K11: 5.67 | L11: 5.09 | M11: 4.62 | O11: 19.1 | P11: 17.92 | Q11: 14.97
F12: eBay | G12: 14.09 | H12: 13 | I12: 12.01 | K12: 4.29 | L12: 4.07 | M12: 3.88 | O12: 18.15 | P12: 16.61 | Q12: 14.87
F13: Microsoft | G13: 14.79 | H13: 12.3 | I13: 9.98 | K13: 8.88 | L13: 7.61 | M13: 6.41 | O13: 23.14 | P13: 20.09 | Q13: 17.09
F14: Apple | G14: 28.33 | H14: 26.06 | I14: 23.81 | K14: 10.05 | L14: 9.18 | M14: 8.57 | O14: 36.99 | P14: 33.33 | Q14: 29.98

Sheet Income Statement Details
A5: Income Statement (Mn USD) | D5: 2020 | E5: 2021 | F5: 2022 | G5: 2023 | H5: 2024 | I5: 2025 | J5: 2026 | K5: 2027 | L5: 2028 | M5: 2029 | N5: 2030
A6: Revenues | D6: 182527 | E6: 257637 | F6: 282836 | G6: 307394 | H6: 350018 | I6: 402836
E7: =E6/D6-1 -> 0.41150076 | F7: =F6/E6-1 -> 0.097808156 | G7: =G6/F6-1 -> 0.086827702 | H7: =H6/G6-1 -> 0.13866243 | I7: =I6/H6-1 -> 0.15090081
A8: Google Search | D8: 104062 | E8: 148951 | F8: 162450 | G8: 175033 | H8: 198084 | I8: 224532 | O8: =I8/$I$6 -> 0.55737819 | Q8: =SUM(D8:D12) -> 146924 | R8: =SUM(I8,I10,I12) -> 294691
A9: YoY | E9: =E8/D8-1 -> 0.43136784 | F9: =F8/E8-1 -> 0.090627119 | G9: =G8/F8-1 -> 0.077457679 | H9: =H8/G8-1 -> 0.13169517 | I9: =I8/H8-1 -> 0.13351911
A10: Youtube ads | D10: 19772 | E10: 28845 | F10: 29243 | G10: 31510 | H10: 36147 | I10: 40367 | O10: =I10/$I$6 -> 0.10020703
E11: =E10/D10-1 -> 0.45888125 | F11: =F10/E10-1 -> 0.013797885 | G11: =G10/F10-1 -> 0.077522826 | H11: =H10/G10-1 -> 0.14715963 | I11: =I10/H10-1 -> 0.11674551
A12: Google Network | D12: 23090 | E12: 31701 | F12: 32780 | G12: 31312 | H12: 30359 | I12: 29792 | O12: =I12/$I$6 -> 0.073955654
E13: =E12/D12-1 -> 0.37293201 | F13: =F12/E12-1 -> 0.034036781 | G13: =G12/F12-1 -> -0.044783405 | H13: =H12/G12-1 -> -0.030435616 | I13: =I12/H12-1 -> -0.018676504
A14: Google Subscriptions | D14: 21711 | E14: 28032 | F14: 29055 | G14: 34688 | H14: 40340 | I14: 48030 | O14: =I14/$I$6 -> 0.11922966
E15: =E14/D14-1 -> 0.29114274 | F15: =F14/E14-1 -> 0.036494007 | G15: =G14/F14-1 -> 0.19387369 | H15: =H14/G14-1 -> 0.16293819 | I15: =I14/H14-1 -> 0.19062965
A16: Google Cloud | D16: 13059 | E16: 19206 | F16: 26280 | G16: 33088 | H16: 43229 | I16: 58705 | O16: =I16/$I$6 -> 0.14572928
E17: =E16/D16-1 -> 0.47070986 | F17: =F16/E16-1 -> 0.3683224 | G17: =G16/F16-1 -> 0.25905632 | H17: =H16/G16-1 -> 0.30648574 | I17: =I16/H16-1 -> 0.35800042
A18: Other Bets | D18: 657 | E18: 753 | F18: 1068 | G18: 1527 | H18: 1648 | I18: 1537 | O18: =I18/$I$6 -> 0.0038154485
E19: =E18/D18-1 -> 0.14611872 | F19: =F18/E18-1 -> 0.41832669 | G19: =G18/F18-1 -> 0.42977528 | H19: =H18/G18-1 -> 0.079240341 | I19: =I18/H18-1 -> -0.067354369
A20: Hedging | D20: 176 | E20: 149 | F20: 1960 | G20: 236 | H20: 211 | I20: -127
E21: =E20/D20-1 -> -0.15340909 | F21: =F20/E20-1 -> 12.154362 | G21: =G20/F20-1 -> -0.87959184 | H21: =H20/G20-1 -> -0.1059322 | I21: =I20/H20-1 -> -1.6018957
A22: (-)Cost of revenues | D22: 84732 | E22: 110939 | F22: 126203 | G22: 133332 | H22: 146306 | I22: 162535
A24: Gross Profit | D24: =D6-D22 -> 97795 | E24: =E6-E22 -> 146698 | F24: =F6-F22 -> 156633 | G24: =G6-G22 -> 174062 | H24: =H6-H22 -> 203712 | I24: =I6-I22 -> 240301
A26: (-)Expenses | D26: =SUM(D27:D29) -> 56571 | E26: =SUM(E27:E29) -> 67984 | F26: =SUM(F27:F29) -> 81791 | G26: =SUM(G27:G29) -> 89769 | H26: =SUM(H27:H29) -> 91322 | I26: =SUM(I27:I29) -> 111262
B27: Research and development | D27: 27573 | E27: 31562 | F27: 39500 | G27: 45427 | H27: 49326 | I27: 61087
B28: Sales and marketing | D28: 17946 | E28: 22912 | F28: 26567 | G28: 27917 | H28: 27808 | I28: 28693
B29: General and administrative | D29: 11052 | E29: 13510 | F29: 15724 | G29: 16425 | H29: 14188 | I29: 21482
A31: Ebit | D31: 41224 | E31: 78714 | F31: 74842 | G31: 84293 | H31: 112390 | I31: 129039
A33: (+/-)Financial Result | D33: -3514 | E33: 12020 | F33: 6858 | G33: 1424 | H33: 7425 | I33: 29787
A35: EBT | D35: 48082 | E35: 90734 | F35: 71328 | G35: 85717 | H35: 119815 | I35: 158826
A37: (-)Taxes | D37: 7813 | E37: 14701 | F37: 11356 | G37: 11922 | H37: 19697 | I37: 26656
A39: Net Income | D39: 40269 | E39: 76033 | F39: 59972 | G39: 73795 | H39: 100118 | I39: 132170

Sheet Build Up (2)
A5: Build Up | D5: 2017 | E5: 2018 | F5: 2019 | G5: 2020 | H5: 2021 | I5: 2022 | J5: 2023 | K5: 2024 | L5: 2025 | M5: 2026 | N5: 2027 | O5: 2028 | P5: 2029 | Q5: 2030
A6: Revenues | G6: =SUM(G8,G11,G14,G17,G22,G27,G30) -> 182527 | H6: =SUM(H8,H11,H14,H17,H22,H27,H30) -> 257637 | I6: =SUM(I8,I11,I14,I17,I22,I27,I30) -> 282836 | J6: =SUM(J8,J11,J14,J17,J22,J27,J30) -> 307394 | K6: =SUM(K8,K11,K14,K17,K22,K27,K30) -> 350018 | L6: =SUM(L8,L11,L14,L17,L22,L27,L30) -> 402836 | M6: =SUM(M8,M11,M14,M17,M22,M27,M30) -> #REF! | N6: =SUM(N8,N11,N14,N17,N22,N27,N30) -> #REF! | ... Q6: =SUM(Q8,Q11,Q14,Q17,Q22,Q27,Q30) -> #REF!
M7: =M6/L6-1 -> #REF! | N7: =N6/M6-1 -> #REF! | O7: =O6/N6-1 -> #REF! | P7: =P6/O6-1 -> #REF! | Q7: =Q6/P6-1 -> #REF! | S7: =AVERAGE(M7:Q7) -> #REF!
A8: Google Search | D8: 69811 | E8: 85296 | F8: 98115 | G8: 104062 | H8: 148951 | I8: 162450 | J8: 175033 | K8: 198084 | L8: 224532 | M8: =(1+M9)*L8 -> #REF! | N8: =(1+N9)*M8 -> #REF! | O8: =(1+O9)*N8 -> #REF! | P8: =(1+P9)*O8 -> #REF! | Q8: =(1+Q9)*P8 -> #REF!
B9: y/y (%) | H9: =H8/G8-1 -> 0.43136784 | I9: =I8/H8-1 -> 0.090627119 | J9: =J8/I8-1 -> 0.077457679 | K9: =K8/J8-1 -> 0.13169517 | L9: =L8/K8-1 -> 0.13351911 | M9: =#REF! -> #REF! | N9: =#REF! -> #REF! | O9: =#REF! -> #REF! | P9: =#REF! -> #REF! | Q9: =#REF! -> #REF!
A11: Youtube ads | D11: 8150 | E11: 11155 | F11: 15149 | G11: 19772 | H11: 28845 | I11: 29243 | J11: 31510 | K11: 36147 | L11: 40367 | M11: =(M12+1)*L11 -> #REF! | N11: =(N12+1)*M11 -> #REF! | O11: =(O12+1)*N11 -> #REF! | P11: =(P12+1)*O11 -> #REF! | Q11: =(Q12+1)*P11 -> #REF!
B12: y/y (%) | H12: =H11/G11-1 -> 0.45888125 | I12: =I11/H11-1 -> 0.013797885 | J12: =J11/I11-1 -> 0.077522826 | K12: =K11/J11-1 -> 0.14715963 | L12: =L11/K11-1 -> 0.11674551 | M12: =#REF! -> #REF! | N12: =#REF! -> #REF! | O12: =#REF! -> #REF! | P12: =#REF! -> #REF! | Q12: =#REF! -> #REF!
A14: Google Network | D14: 17616 | E14: 20010 | F14: 21547 | G14: 23090 | H14: 31701 | I14: 32780 | J14: 31312 | K14: 30359 | L14: 29792 | M14: =(1+M15)*L14 -> 29494.08 | N14: =(1+N15)*M14 -> 29258.127 | O14: =(1+O15)*N14 -> 29082.579 | P14: =(1+P15)*O14 -> 28966.248 | Q14: =(1+Q15)*P14 -> 28908.316
B15: y/y (%) | H15: =H14/G14-1 -> 0.37293201 | I15: =I14/H14-1 -> 0.034036781 | J15: =J14/I14-1 -> -0.044783405 | K15: =K14/J14-1 -> -0.030435616 | L15: =L14/K14-1 -> -0.018676504 | M15: -0.01 | N15: =M15+0.2% -> -0.008 | O15: =N15+0.2% -> -0.006 | P15: =O15+0.2% -> -0.004 | Q15: =P15+0.2% -> -0.002
A17: Google Subscriptions | D17: 10914 | E17: 14063 | F17: 17014 | G17: 21711 | H17: 28032 | I17: 29055 | J17: 34688 | K17: 40340 | L17: 48030 | M17: =(1+M18)*L17 -> #REF! | N17: =(1+N18)*M17 -> #REF! | O17: =(1+O18)*N17 -> #REF! | P17: =(1+P18)*O17 -> #REF! | Q17: =(1+Q18)*P17 -> #REF!
H18: =H17/G17-1 -> 0.29114274 | I18: =I17/H17-1 -> 0.036494007 | J18: =J17/I17-1 -> 0.19387369 | K18: =K17/J17-1 -> 0.16293819 | L18: =L17/K17-1 -> 0.19062965 | M18: =#REF! -> #REF! | N18: =#REF! -> #REF! | O18: =#REF! -> #REF! | P18: =#REF! -> #REF! | Q18: =#REF! -> #REF!
A20: Google Services | G20: =SUM(G17,G14,G11,G8) -> 168635 | H20: =SUM(H17,H14,H11,H8) -> 237529 | I20: =SUM(I17,I14,I11,I8) -> 253528 | J20: =SUM(J17,J14,J11,J8) -> 272543 | K20: =SUM(K17,K14,K11,K8) -> 304930 | L20: =SUM(L17,L14,L11,L8) -> 342721 | M20: =SUM(M17,M14,M11,M8) -> #REF! | N20: =SUM(N17,N14,N11,N8) -> #REF! | ... Q20: =SUM(Q17,Q14,Q11,Q8) -> #REF!
A22: Google Cloud | D22: 4056 | E22: 5838 | F22: 8918 | G22: 13059 | H22: 19206 | I22: 26280 | J22: 33088 | K22: 43229 | L22: 58705 | M22: =L22*(1+M24)*(M25/L25) -> #REF! | N22: =M22*(1+N24)*(N25/M25) -> #REF! | O22: =N22*(1+O24)*(O25/N25) -> #REF! | P22: =O22*(1+P24)*(P25/O25) -> #REF! | Q22: =P22*(1+Q24)*(Q25/P25) -> #REF!
A23: y/y(%) | H23: =H22/G22-1 -> 0.47070986 | I23: =I22/H22-1 -> 0.3683224 | J23: =J22/I22-1 -> 0.25905632 | K23: =K22/J22-1 -> 0.30648574 | L23: =L22/K22-1 -> 0.35800042 | M23: =M22/L22-1 -> #REF! | N23: =N22/M22-1 -> #REF! | O23: =O22/N22-1 -> #REF! | ... Q23: =Q22/P22-1 -> #REF!
A24: Sector Growth | M24: 0.20083102 | N24: 0.1810842 | O24: 0.13964844 | P24: 0.098543273 | Q24: 0.1599064
A25: Market Share | G25: 0.09 | H25: 0.1 | I25: 0.11 | J25: 0.117 | K25: 0.125 | L25: 0.135 | M25: =#REF! -> #REF! | N25: =#REF! -> #REF! | O25: =#REF! -> #REF! | P25: =#REF! -> #REF! | Q25: =#REF! -> #REF!
A27: Other Bets | D27: 477 | E27: 595 | F27: 659 | G27: 657 | H27: 753 | I27: 1068 | J27: 1527 | K27: 1648 | L27: 1537 | M27: =(1+M28)*L27 -> 1846.2772 | N27: =(1+N28)*M27 -> 2236.2503 | O27: =(1+O28)*N27 -> 2730.9566 | P27: =(1+P28)*O27 -> 3362.412 | Q27: =(1+Q28)*P27 -> 4173.4975
B28: y/y (%) | H28: =H27/G27-1 -> 0.14611872 | I28: =I27/H27-1 -> 0.41832669 | J28: =J27/I27-1 -> 0.42977528 | K28: =K27/J27-1 -> 0.079240341 | L28: =L27/K27-1 -> -0.067354369 | M28: =AVERAGE(H28:L28) -> 0.20122133 | N28: =M28+1% -> 0.21122133 | O28: =N28+1% -> 0.22122133 | P28: =O28+1% -> 0.23122133 | Q28: =P28+1% -> 0.24122133
A30: Hedging | D30: -169 | E30: -138 | F30: 455 | G30: 176 | H30: 149 | I30: 1960 | J30: 236 | K30: 211 | L30: -127 | M30: =SUM(M27,M22,M20)*M31 -> #REF! | N30: =SUM(N27,N22,N20)*N31 -> #REF! | O30: =SUM(O27,O22,O20)*O31 -> #REF! | P30: =SUM(P27,P22,P20)*P31 -> #REF! | Q30: =SUM(Q27,Q22,Q20)*Q31 -> #REF!
B31: As % of Revenue | G31: =G30/G6 -> 0.00096424091 | H31: =H30/H6 -> 0.00057833308 | I31: =I30/I6 -> 0.0069298109 | J31: =J30/J6 -> 0.00076774433 | K31: =K30/K6 -> 0.00060282614 | L31: =L30/L6 -> -0.00031526477 | M31: =MEDIAN(G31:L31) -> 0.00068528523 | N31: =MEDIAN(H31:M31) -> 0.00064405569 | O31: =MEDIAN(I31:N31) -> 0.00066467046 | P31: =MEDIAN(J31:O31) -> 0.00065436307 | Q31: =MEDIAN(K31:P31) -> 0.00064920938
A33: Operating Income
A34: Operating Income | G34: =SUM(G37,G40,G43,G47) -> 41224 | H34: =SUM(H37,H40,H43,H47) -> 78714 | I34: =SUM(I37,I40,I43,I47) -> 74842 | J34: =SUM(J37,J40,J43,J47) -> 84293 | K34: =SUM(K37,K40,K43,K47) -> 112390 | L34: =SUM(L37,L40,L43,L47) -> 129039 | M34: =SUM(M37,M40,M43,M47) -> #REF! | N34: =SUM(N37,N40,N43,N47) -> #REF! | ... Q34: =SUM(Q37,Q40,Q43,Q47) -> #REF!
B35: Margin (%) | G35: =G34/G6 -> 0.22585152 | H35: =H34/H6 -> 0.30552289 | I35: =I34/I6 -> 0.26461271 | J35: =J34/J6 -> 0.2742181 | K35: =K34/K6 -> 0.32109777 | L35: =L34/L6 -> 0.32032639 | M35: =M34/M6 -> #REF! | N35: =N34/N6 -> #REF! | ... Q35: =Q34/Q6 -> #REF!
B37: Google Services | G37: 54606 | H37: 91855 | I37: 82699 | J37: 95858 | K37: 121263 | L37: 139404 | M37: =M38*M20 -> #REF! | N37: =N38*N20 -> #REF! | O37: =O38*O20 -> #REF! | P37: =P38*P20 -> #REF! | Q37: =Q38*Q20 -> #REF!
C38: Margin (%) | G38: =G37/G20 -> 0.32381178 | H38: =H37/H20 -> 0.38671068 | I38: =I37/I20 -> 0.32619277 | J38: =J37/J20 -> 0.35171698 | K38: =K37/K20 -> 0.39767488 | L38: =L37/L20 -> 0.40675652 | M38: =#REF! -> #REF! | N38: =#REF! -> #REF! | O38: =#REF! -> #REF! | P38: =#REF! -> #REF! | Q38: =#REF! -> #REF!
B40: Google Cloud | G40: -5607 | H40: -3099 | I40: -1922 | J40: 1716 | K40: 6112 | L40: 13910 | M40: =M41*M22 -> #REF! | N40: =N41*N22 -> #REF! | O40: =O41*O22 -> #REF! | P40: =P41*P22 -> #REF! | Q40: =Q41*Q22 -> #REF!
C41: Margin (%) | G41: =G40/G22 -> -0.42935906 | H41: =H40/H22 -> -0.16135583 | I41: =I40/I22 -> -0.073135464 | J41: =J40/J22 -> 0.051861702 | K41: =K40/K22 -> 0.14138657 | L41: =L40/L22 -> 0.23694745 | M41: =#REF! -> #REF! | N41: =#REF! -> #REF! | O41: =#REF! -> #REF! | P41: =#REF! -> #REF! | Q41: =#REF! -> #REF!
B43: Other Bets | G43: -4476 | H43: -5281 | I43: -4636 | J43: -4095 | K43: -4444 | L43: -7515 | M43: =M27-M44 -> -7854.1113 | N43: =N27-N44 -> -8304.1932 | O43: =O27-O44 -> -8753.9121 | P43: =P27-P44 -> -9185.9572 | Q43: =Q27-Q44 -> -9574.4976
C44: Expenses | G44: 5133 | H44: 6034 | I44: 5704 | J44: 5622 | K44: 6092 | L44: 8952 | M44: =(M45+1)*L44 -> 9700.3885 | N44: =(N45+1)*M44 -> 10540.443 | O44: =(O45+1)*N44 -> 11484.869 | P44: =(P45+1)*O44 -> 12548.369 | Q44: =(Q45+1)*P44 -> 13747.995
C45: y/y(%) | H45: =H44/G44-1 -> 0.17553088 | I45: =I44/H44-1 -> -0.054690089 | J45: =J44/I44-1 -> -0.014375877 | K45: =K44/J44-1 -> 0.083600142 | L45: =L44/K44-1 -> 0.46946815 | M45: =MEDIAN(H45:L45) -> 0.083600142 | N45: =M45+0.3% -> 0.086600142 | O45: =N45+0.3% -> 0.089600142 | P45: =O45+0.3% -> 0.092600142 | Q45: =P45+0.3% -> 0.095600142
B47: Alphabet Level | G47: -3299 | H47: -4761 | I47: -1299 | J47: -9186 | K47: -10541 | L47: -16760 | M47: =-M48*M6 -> #REF! | N47: =-N48*N6 -> #REF! | O47: =-O48*O6 -> #REF! | P47: =-P48*P6 -> #REF! | Q47: =-Q48*Q6 -> #REF!
C48: As % Revenue | G48: =-G47/G6 -> 0.018074038 | H48: =-H47/H6 -> 0.018479489 | I48: =-I47/I6 -> 0.0045927675 | J48: =-J47/J6 -> 0.029883472 | K48: =-K47/K6 -> 0.030115594 | L48: =-L47/L6 -> 0.04160502 | M48: =AVERAGE(J48:L48) -> 0.033868029 | N48: =M48 -> 0.033868029 | O48: =N48 -> 0.033868029 | P48: =O48 -> 0.033868029 | Q48: =P48 -> 0.033868029
A50: Total Expenses | G50: =G6-G34 -> 141303 | H50: =H6-H34 -> 178923 | I50: =I6-I34 -> 207994 | J50: =J6-J34 -> 223101 | K50: =K6-K34 -> 237628 | L50: =L6-L34 -> 273797 | M50: =M6-M34 -> #REF! | N50: =N6-N34 -> #REF! | ... Q50: =Q6-Q34 -> #REF!
B52: Cost of Revenue | G52: ='Income Statement'!D8 -> 84732 | H52: ='Income Statement'!E8 -> 110939 | I52: ='Income Statement'!J8 -> 126203 | J52: ='Income Statement'!O8 -> 133332 | K52: ='Income Statement'!T8 -> 146306 | L52: ='Income Statement'!Y8 -> 162535 | M52: =M53*M50 -> #REF! | N52: =N53*N50 -> #REF! | O52: =O53*O50 -> #REF! | P52: =P53*P50 -> #REF! | Q52: =Q53*Q50 -> #REF!
C53: As % of Total Expenses | G53: =G52/G50 -> 0.59964757 | H53: =H52/H50 -> 0.62003767 | I53: =I52/I50 -> 0.6067627 | J53: =J52/J50 -> 0.59763067 | K53: =K52/K50 -> 0.61569344 | L53: =L52/L50 -> 0.59363324 | M53: =MEDIAN(G53:L53) -> 0.60320513 | N53: =M53 -> 0.60320513 | O53: =N53 -> 0.60320513 | P53: =O53 -> 0.60320513 | Q53: =P53 -> 0.60320513
B55: SG&A | G55: ='Income Statement'!D12 -> 56571 | H55: ='Income Statement'!E12 -> 67984 | I55: ='Income Statement'!J12 -> 81791 | J55: ='Income Statement'!O12 -> 89769 | K55: ='Income Statement'!T12 -> 91322 | L55: ='Income Statement'!Y12 -> 111262 | M55: =M56*M50 -> #REF! | N55: =N56*N50 -> #REF! | O55: =O56*O50 -> #REF! | P55: =P56*P50 -> #REF! | Q55: =Q56*Q50 -> #REF!
C56: As % of Total Expenses | G56: =G55/G50 -> 0.40035243 | H56: =H55/H50 -> 0.37996233 | I56: =I55/I50 -> 0.3932373 | J56: =J55/J50 -> 0.40236933 | K56: =K55/K50 -> 0.38430656 | L56: =L55/L50 -> 0.40636676 | M56: =1-M53 -> 0.39679487 | N56: =M56 -> 0.39679487 | O56: =N56 -> 0.39679487 | P56: =O56 -> 0.39679487 | Q56: =P56 -> 0.39679487

Sheet Q - Income Statement
B1: Income Statement — Quarterly (Mn USD)
C2: 2022 | H2: 2023 | M2: 2024 | R2: 2025 | W2: 2026
C3: Q1 | D3: Q2 | E3: Q3 | F3: Q4 | G3: FY | H3: Q1 | I3: Q2 | J3: Q3 | K3: Q4 | L3: FY | M3: Q1 | N3: Q2 | O3: Q3 | P3: Q4 | Q3: FY | R3: Q1 | S3: Q2 | T3: Q3 | U3: Q4 | V3: FY | W3: Q1
B5: Revenues | C5: 68011 | D5: 69685 | E5: 69092 | F5: =G5-SUM(C5:E5) -> 76048 | G5: ='Income Statement'!J6 -> 282836 | H5: 69787 | I5: 74604 | J5: 76693 | K5: =L5-SUM(H5:J5) -> 86310 | L5: ='Income Statement'!O6 -> 307394 | M5: 80539 | N5: 84742 | O5: 88268 | P5: =Q5-SUM(M5:O5) -> 96469 | Q5: ='Income Statement'!T6 -> 350018 | R5: 90234 | S5: 96428 | T5: 102346 | U5: =V5-SUM(R5:T5) -> 113828 | V5: ='Income Statement'!Y6 -> 402836 | W5: 109896
B6: y/y (%)
B7: (-) Cost of revenues | C7: 29599 | D7: 30104 | E7: 31158 | F7: =G7-SUM(C7:E7) -> 35342 | G7: ='Income Statement'!J8 -> 126203 | H7: 30612 | I7: 31916 | J7: 33229 | K7: =L7-SUM(H7:J7) -> 37575 | L7: ='Income Statement'!O8 -> 133332 | M7: 33712 | N7: 35507 | O7: 36474 | P7: =Q7-SUM(M7:O7) -> 40613 | Q7: ='Income Statement'!T8 -> 146306 | R7: 36361 | S7: 39039 | T7: 41369 | U7: =V7-SUM(R7:T7) -> 45766 | V7: ='Income Statement'!Y8 -> 162535 | W7: 41271
B8: Gross Profit | C8: =C5-C7 -> 38412 | D8: =D5-D7 -> 39581 | E8: =E5-E7 -> 37934 | F8: =F5-F7 -> 40706 | G8: =G5-G7 -> 156633 | H8: =H5-H7 -> 39175 | I8: =I5-I7 -> 42688 | J8: =J5-J7 -> 43464 | ... W8: =W5-W7 -> 68625
B9: (-) SG&A | C9: =C10+C11+C12 -> 18318 | D9: =D10+D11+D12 -> 20128 | E9: =E10+E11+E12 -> 20799 | F9: =F10+F11+F12 -> 22546 | G9: =G10+G11+G12 -> 81791 | H9: =H10+H11+H12 -> 21760 | I9: =I10+I11+I12 -> 20850 | J9: =J10+J11+J12 -> 22121 | ... W9: =W10+W11+W12 -> 28929
B10: Research & development | C10: 9119 | D10: 9841 | E10: 10273 | F10: =G10-SUM(C10:E10) -> 10267 | G10: ='Income Statement'!J13 -> 39500 | H10: 11468 | I10: 10588 | J10: 11258 | K10: =L10-SUM(H10:J10) -> 12113 | L10: ='Income Statement'!O13 -> 45427 | M10: 11903 | N10: 11860 | O10: 12447 | P10: =Q10-SUM(M10:O10) -> 13116 | Q10: ='Income Statement'!T13 -> 49326 | R10: 13556 | S10: 13808 | T10: 15151 | U10: =V10-SUM(R10:T10) -> 18572 | V10: ='Income Statement'!Y13 -> 61087 | W10: 17032
B11: Sales & marketing | C11: 5825 | D11: 6630 | E11: 6929 | F11: =G11-SUM(C11:E11) -> 7183 | G11: ='Income Statement'!J14 -> 26567 | H11: 6533 | I11: 6781 | J11: 6884 | K11: =L11-SUM(H11:J11) -> 7719 | L11: ='Income Statement'!O14 -> 27917 | M11: 6426 | N11: 6792 | O11: 7227 | P11: =Q11-SUM(M11:O11) -> 7363 | Q11: ='Income Statement'!T14 -> 27808 | R11: 6172 | S11: 7101 | T11: 7205 | U11: =V11-SUM(R11:T11) -> 8215 | V11: ='Income Statement'!Y14 -> 28693 | W11: 7606
B12: General & administrative | C12: 3374 | D12: 3657 | E12: 3597 | F12: =G12-SUM(C12:E12) -> 5096 | G12: ='Income Statement'!J15 -> 15724 | H12: 3759 | I12: 3481 | J12: 3979 | K12: =L12-SUM(H12:J12) -> 5206 | L12: ='Income Statement'!O15 -> 16425 | M12: 3026 | N12: 3158 | O12: 3599 | P12: =Q12-SUM(M12:O12) -> 4405 | Q12: ='Income Statement'!T15 -> 14188 | R12: 3539 | S12: 5209 | T12: 7393 | U12: =V12-SUM(R12:T12) -> 5341 | V12: ='Income Statement'!Y15 -> 21482 | W12: 4291
B14: EBIT | C14: =C8-C9 -> 20094 | D14: =D8-D9 -> 19453 | E14: =E8-E9 -> 17135 | F14: =F8-F9 -> 18160 | G14: =G8-G9 -> 74842 | H14: =H8-H9 -> 17415 | I14: =I8-I9 -> 21838 | J14: =J8-J9 -> 21343 | ... W14: =W8-W9 -> 39696
B15: (+/-) Financial Result | C15: -1160 | D15: -439 | E15: -902 | F15: =G15-SUM(C15:E15) -> -1013 | G15: ='Income Statement'!J19 -> -3514 | H15: 790 | I15: 65 | J15: -146 | K15: =L15-SUM(H15:J15) -> 715 | L15: ='Income Statement'!O19 -> 1424 | M15: 2843 | N15: 126 | O15: 3185 | P15: =Q15-SUM(M15:O15) -> 1271 | Q15: ='Income Statement'!T19 -> 7425 | R15: 11183 | S15: 2662 | T15: 12759 | U15: =V15-SUM(R15:T15) -> 3183 | V15: ='Income Statement'!Y19 -> 29787 | W15: 37716
B17: EBT | C17: =C14+C15 -> 18934 | D17: =D14+D15 -> 19014 | E17: =E14+E15 -> 16233 | F17: =F14+F15 -> 17147 | G17: =G14+G15 -> 71328 | H17: =H14+H15 -> 18205 | I17: =I14+I15 -> 21903 | J17: =J14+J15 -> 21197 | ... W17: =W14+W15 -> 77412
B18: Taxes | C18: 2498 | D18: 3012 | E18: 2323 | F18: =G18-SUM(C18:E18) -> 3523 | G18: ='Income Statement'!J27 -> 11356 | H18: 3154 | I18: 3535 | J18: 1508 | K18: =L18-SUM(H18:J18) -> 3725 | L18: ='Income Statement'!O27 -> 11922 | M18: 4653 | N18: 3932 | O18: 5405 | P18: =Q18-SUM(M18:O18) -> 5707 | Q18: ='Income Statement'!T27 -> 19697 | R18: 7249 | S18: 5737 | T18: 9008 | U18: =V18-SUM(R18:T18) -> 4662 | V18: ='Income Statement'!Y27 -> 26656 | W18: 14834
B19: Effective Tax Rate | C19: =IF(C17=0,0,C18/C17) -> 0.13193197 | D19: =IF(D17=0,0,D18/D17) -> 0.15840959 | E19: =IF(E17=0,0,E18/E17) -> 0.14310355 | F19: =IF(F17=0,0,F18/F17) -> 0.20545868 | G19: =IF(G17=0,0,G18/G17) -> 0.15920817 | H19: =IF(H17=0,0,H18/H17) -> 0.17324911 | I19: =IF(I17=0,0,I18/I17) -> 0.16139342 | J19: =IF(J17=0,0,J18/J17) -> 0.071142143 | ... W19: =IF(W17=0,0,W18/W17) -> 0.19162404
B20: Net Income | C20: =C17-C18 -> 16436 | D20: =D17-D18 -> 16002 | E20: =E17-E18 -> 13910 | F20: =F17-F18 -> 13624 | G20: =G17-G18 -> 59972 | H20: =H17-H18 -> 15051 | I20: =I17-I18 -> 18368 | J20: =J17-J18 -> 19689 | ... W20: =W17-W18 -> 62578
B21: Net Margin (%) | C21: =IF(C5=0,0,C20/C5) -> 0.24166679 | D21: =IF(D5=0,0,D20/D5) -> 0.22963335 | E21: =IF(E5=0,0,E20/E5) -> 0.20132577 | F21: =IF(F5=0,0,F20/F5) -> 0.17915001 | G21: =IF(G5=0,0,G20/G5) -> 0.21203807 | H21: =IF(H5=0,0,H20/H5) -> 0.21567054 | I21: =IF(I5=0,0,I20/I5) -> 0.24620664 | J21: =IF(J5=0,0,J20/J5) -> 0.25672486 | ... W21: =IF(W5=0,0,W20/W5) -> 0.56942928

Sheet Q - Build Up
B1: Build Up — Quarterly (Mn USD)
C2: 2022 | H2: 2023 | M2: 2024 | R2: 2025 | W2: 2026
C3: Q1 | D3: Q2 | E3: Q3 | F3: Q4 | G3: FY | H3: Q1 | I3: Q2 | J3: Q3 | K3: Q4 | L3: FY | M3: Q1 | N3: Q2 | O3: Q3 | P3: Q4 | Q3: FY | R3: Q1 | S3: Q2 | T3: Q3 | U3: Q4 | V3: FY | W3: Q1
B5: Google Search & other | C5: 39618 | D5: 40689 | E5: 39539 | F5: =G5-SUM(C5:E5) -> 42604 | G5: ='Build Up (2)'!I8 -> 162450 | H5: 40359 | I5: 42628 | J5: 44026 | K5: =L5-SUM(H5:J5) -> 48020 | L5: ='Build Up (2)'!J8 -> 175033 | M5: 46156 | N5: 48509 | O5: 49385 | P5: =Q5-SUM(M5:O5) -> 54034 | Q5: ='Build Up (2)'!K8 -> 198084 | R5: 50702 | S5: 54190 | T5: 56567 | U5: =V5-SUM(R5:T5) -> 63073 | V5: ='Build Up (2)'!L8 -> 224532 | W5: 60399
B6: YouTube ads | C6: 6869 | D6: 7340 | E6: 7071 | F6: =G6-SUM(C6:E6) -> 7963 | G6: ='Build Up (2)'!I11 -> 29243 | H6: 6693 | I6: 7665 | J6: 7952 | K6: =L6-SUM(H6:J6) -> 9200 | L6: ='Build Up (2)'!J11 -> 31510 | M6: 8090 | N6: 8663 | O6: 8921 | P6: =Q6-SUM(M6:O6) -> 10473 | Q6: ='Build Up (2)'!K11 -> 36147 | R6: 8927 | S6: 9796 | T6: 10261 | U6: =V6-SUM(R6:T6) -> 11383 | V6: ='Build Up (2)'!L11 -> 40367 | W6: 9883
B7: Google Network | C7: 8174 | D7: 8259 | E7: 7872 | F7: =G7-SUM(C7:E7) -> 8475 | G7: ='Build Up (2)'!I14 -> 32780 | H7: 7496 | I7: 7850 | J7: 7669 | K7: =L7-SUM(H7:J7) -> 8297 | L7: ='Build Up (2)'!J14 -> 31312 | M7: 7413 | N7: 7444 | O7: 7548 | P7: =Q7-SUM(M7:O7) -> 7954 | Q7: ='Build Up (2)'!K14 -> 30359 | R7: 7256 | S7: 7354 | T7: 7354 | U7: =V7-SUM(R7:T7) -> 7828 | V7: ='Build Up (2)'!L14 -> 29792 | W7: 6971
B8: Google subscriptions, platforms & devices | C8: 6811 | D8: 6553 | E8: 6895 | F8: =G8-SUM(C8:E8) -> 8796 | G8: ='Build Up (2)'!I17 -> 29055 | H8: 7413 | I8: 8142 | J8: 8339 | K8: =L8-SUM(H8:J8) -> 10794 | L8: ='Build Up (2)'!J17 -> 34688 | M8: 8739 | N8: 9312 | O8: 10656 | P8: =Q8-SUM(M8:O8) -> 11633 | Q8: ='Build Up (2)'!K17 -> 40340 | R8: 10379 | S8: 11203 | T8: 12870 | U8: =V8-SUM(R8:T8) -> 13578 | V8: ='Build Up (2)'!L17 -> 48030 | W8: 12384
B9: Google Services | C9: =SUM(C5:C8) -> 61472 | D9: =SUM(D5:D8) -> 62841 | E9: =SUM(E5:E8) -> 61377 | F9: =SUM(F5:F8) -> 67838 | G9: =SUM(G5:G8) -> 253528 | H9: =SUM(H5:H8) -> 61961 | I9: =SUM(I5:I8) -> 66285 | J9: =SUM(J5:J8) -> 67986 | ... W9: =SUM(W5:W8) -> 89637
B10: Google Cloud | C10: 5821 | D10: 6276 | E10: 6868 | F10: =G10-SUM(C10:E10) -> 7315 | G10: ='Build Up (2)'!I22 -> 26280 | H10: 7454 | I10: 8031 | J10: 8411 | K10: =L10-SUM(H10:J10) -> 9192 | L10: ='Build Up (2)'!J22 -> 33088 | M10: 9574 | N10: 10347 | O10: 11353 | P10: =Q10-SUM(M10:O10) -> 11955 | Q10: ='Build Up (2)'!K22 -> 43229 | R10: 12260 | S10: 13624 | T10: 15157 | U10: =V10-SUM(R10:T10) -> 17664 | V10: ='Build Up (2)'!L22 -> 58705 | W10: 20028
B11: Other Bets | C11: 440 | D11: 193 | E11: 209 | F11: =G11-SUM(C11:E11) -> 226 | G11: ='Build Up (2)'!I27 -> 1068 | H11: 288 | I11: 285 | J11: 297 | K11: =L11-SUM(H11:J11) -> 657 | L11: ='Build Up (2)'!J27 -> 1527 | M11: 495 | N11: 365 | O11: 388 | P11: =Q11-SUM(M11:O11) -> 400 | Q11: ='Build Up (2)'!K27 -> 1648 | R11: 450 | S11: 373 | T11: 344 | U11: =V11-SUM(R11:T11) -> 370 | V11: ='Build Up (2)'!L27 -> 1537 | W11: 411
B12: Hedging gains (losses) | C12: 278 | D12: 375 | E12: 638 | F12: =G12-SUM(C12:E12) -> 669 | G12: ='Build Up (2)'!I30 -> 1960 | H12: 84 | I12: 3 | J12: -1 | K12: =L12-SUM(H12:J12) -> 150 | L12: ='Build Up (2)'!J30 -> 236 | M12: 72 | N12: 102 | O12: 17 | P12: =Q12-SUM(M12:O12) -> 20 | Q12: ='Build Up (2)'!K30 -> 211 | R12: 260 | S12: -112 | T12: -207 | U12: =V12-SUM(R12:T12) -> -68 | V12: ='Build Up (2)'!L30 -> -127 | W12: -180
B13: Total Revenues | C13: =C9+C10+C11+C12 -> 68011 | D13: =D9+D10+D11+D12 -> 69685 | E13: =E9+E10+E11+E12 -> 69092 | F13: =F9+F10+F11+F12 -> 76048 | G13: =G9+G10+G11+G12 -> 282836 | H13: =H9+H10+H11+H12 -> 69787 | I13: =I9+I10+I11+I12 -> 74604 | J13: =J9+J10+J11+J12 -> 76693 | ... W13: =W9+W10+W11+W12 -> 109896
B15: Operating Income (loss)
B16: Google Services | C16: 21973 | D16: 21621 | E16: 18883 | F16: =G16-SUM(C16:E16) -> 20222 | G16: ='Build Up (2)'!I37 -> 82699 | H16: 21737 | I16: 23454 | J16: 23937 | K16: =L16-SUM(H16:J16) -> 26730 | L16: ='Build Up (2)'!J37 -> 95858 | M16: 27897 | N16: 29674 | O16: 30856 | P16: =Q16-SUM(M16:O16) -> 32836 | Q16: ='Build Up (2)'!K37 -> 121263 | R16: 32682 | S16: 33063 | T16: 33527 | U16: =V16-SUM(R16:T16) -> 40132 | V16: ='Build Up (2)'!L37 -> 139404 | W16: 40589
B17: Margin (%) | C17: =IF(C9=0,0,C16/C9) -> 0.35744729 | D17: =IF(D9=0,0,D16/D9) -> 0.34405882 | E17: =IF(E9=0,0,E16/E9) -> 0.30765596 | F17: =IF(F9=0,0,F16/F9) -> 0.29809251 | G17: =IF(G9=0,0,G16/G9) -> 0.32619277 | H17: =IF(H9=0,0,H16/H9) -> 0.35081745 | I17: =IF(I9=0,0,I16/I9) -> 0.35383571 | J17: =IF(J9=0,0,J16/J9) -> 0.35208719 | ... W17: =IF(W9=0,0,W16/W9) -> 0.45281524
B18: Google Cloud | C18: -706 | D18: -590 | E18: -440 | F18: =G18-SUM(C18:E18) -> -186 | G18: ='Build Up (2)'!I40 -> -1922 | H18: 191 | I18: 395 | J18: 266 | K18: =L18-SUM(H18:J18) -> 864 | L18: ='Build Up (2)'!J40 -> 1716 | M18: 900 | N18: 1172 | O18: 1947 | P18: =Q18-SUM(M18:O18) -> 2093 | Q18: ='Build Up (2)'!K40 -> 6112 | R18: 2177 | S18: 2826 | T18: 3594 | U18: =V18-SUM(R18:T18) -> 5313 | V18: ='Build Up (2)'!L40 -> 13910 | W18: 6598
B19: Margin (%) | C19: =IF(C10=0,0,C18/C10) -> -0.121285 | D19: =IF(D10=0,0,D18/D10) -> -0.094008923 | E19: =IF(E10=0,0,E18/E10) -> -0.06406523 | F19: =IF(F10=0,0,F18/F10) -> -0.025427204 | G19: =IF(G10=0,0,G18/G10) -> -0.073135464 | H19: =IF(H10=0,0,H18/H10) -> 0.025623826 | I19: =IF(I10=0,0,I18/I10) -> 0.04918441 | J19: =IF(J10=0,0,J18/J10) -> 0.031625253 | ... W19: =IF(W10=0,0,W18/W10) -> 0.32943879
B20: Other Bets | C20: -835 | D20: -1339 | E20: -1225 | F20: =G20-SUM(C20:E20) -> -1237 | G20: ='Build Up (2)'!I43 -> -4636 | H20: -1225 | I20: -813 | J20: -1194 | K20: =L20-SUM(H20:J20) -> -863 | L20: ='Build Up (2)'!J43 -> -4095 | M20: -1020 | N20: -1134 | O20: -1116 | P20: =Q20-SUM(M20:O20) -> -1174 | Q20: ='Build Up (2)'!K43 -> -4444 | R20: -1226 | S20: -1246 | T20: -1426 | U20: =V20-SUM(R20:T20) -> -3617 | V20: ='Build Up (2)'!L43 -> -7515 | W20: -2100
B21: Corporate costs / Alphabet-level | C21: -338 | D21: -239 | E21: -83 | F21: =G21-SUM(C21:E21) -> -639 | G21: ='Build Up (2)'!I47 -> -1299 | H21: -3288 | I21: -1198 | J21: -1666 | K21: =L21-SUM(H21:J21) -> -3034 | L21: ='Build Up (2)'!J47 -> -9186 | M21: -2305 | N21: -2287 | O21: -3166 | P21: =Q21-SUM(M21:O21) -> -2783 | Q21: ='Build Up (2)'!K47 -> -10541 | R21: -3027 | S21: -3372 | T21: -4467 | U21: =V21-SUM(R21:T21) -> -5894 | V21: ='Build Up (2)'!L47 -> -16760 | W21: -5391
B22: Total Operating Income | C22: =C16+C18+C20+C21 -> 20094 | D22: =D16+D18+D20+D21 -> 19453 | E22: =E16+E18+E20+E21 -> 17135 | F22: =F16+F18+F20+F21 -> 18160 | G22: =G16+G18+G20+G21 -> 74842 | H22: =H16+H18+H20+H21 -> 17415 | I22: =I16+I18+I20+I21 -> 21838 | J22: =J16+J18+J20+J21 -> 21343 | ... W22: =W16+W18+W20+W21 -> 39696
B23: Margin (%) | C23: =IF(C13=0,0,C22/C13) -> 0.29545221 | D23: =IF(D13=0,0,D22/D13) -> 0.2791562 | E23: =IF(E13=0,0,E22/E13) -> 0.24800266 | F23: =IF(F13=0,0,F22/F13) -> 0.23879655 | G23: =IF(G13=0,0,G22/G13) -> 0.26461271 | H23: =IF(H13=0,0,H22/H13) -> 0.24954504 | I23: =IF(I13=0,0,I22/I13) -> 0.29271889 | J23: =IF(J13=0,0,J22/J13) -> 0.27829137 | ... W23: =IF(W13=0,0,W22/W13) -> 0.36121424
B25: Expenses
B26: Cost of Revenue | C26: ='Q - Income Statement'!C7 -> 29599 | D26: ='Q - Income Statement'!D7 -> 30104 | E26: ='Q - Income Statement'!E7 -> 31158 | F26: ='Q - Income Statement'!F7 -> 35342 | G26: ='Q - Income Statement'!G7 -> 126203 | H26: ='Q - Income Statement'!H7 -> 30612 | I26: ='Q - Income Statement'!I7 -> 31916 | J26: ='Q - Income Statement'!J7 -> 33229 | ... W26: ='Q - Income Statement'!W7 -> 41271
B27: SG&A | C27: ='Q - Income Statement'!C9 -> 18318 | D27: ='Q - Income Statement'!D9 -> 20128 | E27: ='Q - Income Statement'!E9 -> 20799 | F27: ='Q - Income Statement'!F9 -> 22546 | G27: ='Q - Income Statement'!G9 -> 81791 | H27: ='Q - Income Statement'!H9 -> 21760 | I27: ='Q - Income Statement'!I9 -> 20850 | J27: ='Q - Income Statement'!J9 -> 22121 | ... W27: ='Q - Income Statement'!W9 -> 28929

Sheet Q - BS
B1: Balance Sheet — Quarterly (Mn USD)
C2: 2023 | G2: 2024 | K2: 2025 | O2: 2026
C3: Q1 | D3: Q2 | E3: Q3 | F3: Q4 | G3: Q1 | H3: Q2 | I3: Q3 | J3: Q4 | K3: Q1 | L3: Q2 | M3: Q3 | N3: Q4 | O3: Q1
B4: Check (A − L&E) | C4: =IF(ROUND(C6-C38,0)=0,"OK",ROUND(C6-C38,0)) -> OK | D4: =IF(ROUND(D6-D38,0)=0,"OK",ROUND(D6-D38,0)) -> OK | E4: =IF(ROUND(E6-E38,0)=0,"OK",ROUND(E6-E38,0)) -> OK | F4: =IF(ROUND(F6-F38,0)=0,"OK",ROUND(F6-F38,0)) -> OK | G4: =IF(ROUND(G6-G38,0)=0,"OK",ROUND(G6-G38,0)) -> OK | H4: =IF(ROUND(H6-H38,0)=0,"OK",ROUND(H6-H38,0)) -> OK | I4: =IF(ROUND(I6-I38,0)=0,"OK",ROUND(I6-I38,0)) -> OK | J4: =IF(ROUND(J6-J38,0)=0,"OK",ROUND(J6-J38,0)) -> OK | ... O4: =IF(ROUND(O6-O38,0)=0,"OK",ROUND(O6-O38,0)) -> OK
B6: Assets | C6: =C8+C13 -> 369491 | D6: =D8+D13 -> 383044 | E6: =E8+E13 -> 396711 | F6: =F8+F13 -> 402392 | G6: =G8+G13 -> 407350 | H6: =H8+H13 -> 414770 | I6: =I8+I13 -> 430266 | J6: =J8+J13 -> 450256 | ... O6: =O8+O13 -> 703919
B8: Current Assets | C8: =C9+C10+C11 -> 161985 | D8: =D9+D10+D11 -> 168788 | E8: =E9+E10+E11 -> 176310 | F8: =F9+F10+F11 -> 171530 | G8: =G9+G10+G11 -> 165471 | H8: =H9+H10+H11 -> 161995 | I8: =I9+I10+I11 -> 157541 | J8: =J9+J10+J11 -> 163711 | ... O8: =O9+O10+O11 -> 213753
B9: Cash & equivalents | C9: 115102 | D9: 118332 | E9: 119935 | F9: =BS!K10 -> 110916 | G9: 108090 | H9: 100725 | I9: 93230 | J9: =BS!P10 -> 95657 | K9: 95328 | L9: 95148 | M9: 98496 | N9: =BS!U10 -> 126843 | O9: 126840
B10: Accounts receivable | C10: 36036 | D10: 38804 | E10: 41020 | F10: =BS!K11 -> 47964 | G10: 44552 | H10: 47087 | I10: 49104 | J10: =BS!P11 -> 52340 | K10: 51000 | L10: 55048 | M10: 57148 | N10: =BS!U11 -> 62886 | O10: 62999
B11: Other current assets | C11: 10847 | D11: 11652 | E11: 15355 | F11: =BS!K12 -> 12650 | G11: 12829 | H11: 14183 | I11: 15207 | J11: =BS!P12 -> 15714 | K11: 15724 | L11: 16020 | M11: 18303 | N11: =BS!U12 -> 16309 | O11: 23914
B13: Non Current Assets | C13: =SUM(C14:C18) -> 207506 | D13: =SUM(D14:D18) -> 214256 | E13: =SUM(E14:E18) -> 220401 | F13: =SUM(F14:F18) -> 230862 | G13: =SUM(G14:G18) -> 241879 | H13: =SUM(H14:H18) -> 252775 | I13: =SUM(I14:I18) -> 272725 | J13: =SUM(J14:J18) -> 286545 | ... O13: =SUM(O14:O18) -> 490166
B14: Investiments | C14: 31213 | D14: 31224 | E14: 30907 | F14: =BS!K15 -> 31008 | G14: 33994 | H14: 34172 | I14: 36177 | J14: =BS!P15 -> 37982 | K14: 51029 | L14: 52574 | M14: 63800 | N14: =BS!U15 -> 68687 | O14: 106946
B15: PP&E | C15: 117560 | D15: 121208 | E15: 125705 | F15: =BS!K16 -> 134345 | G15: 143182 | H15: 151155 | I15: 161270 | J15: =BS!P16 -> 171036 | K15: 185062 | L15: 203231 | M15: 223787 | N15: =BS!U16 -> 246597 | O15: 281020
B16: Lease | C16: 14447 | D16: 14469 | E16: 14199 | F16: =BS!K17 -> 14091 | G16: 13768 | H16: 13606 | I16: 13561 | J16: =BS!P17 -> 13588 | K16: 13722 | L16: 14255 | M16: 14524 | N16: =BS!U17 -> 15221 | O16: 15509
B17: Goodwill | C17: 28994 | D17: 29210 | E17: 29146 | F17: =BS!K18 -> 29198 | G17: 29183 | H17: 29185 | I17: 31935 | J17: =BS!P18 -> 31885 | K17: 32173 | L17: 32335 | M17: 33269 | N17: =BS!U18 -> 33380 | O17: 57774
B18: Others Non Current Assets | C18: 15292 | D18: 18145 | E18: 20444 | F18: =BS!K19 -> 22220 | G18: 21752 | H18: 24657 | I18: 29782 | J18: =BS!P19 -> 32054 | K18: 31336 | L18: 33442 | M18: 27142 | N18: =BS!U19 -> 25358 | O18: 28917
B20: Liabilities | C20: =C22+C28 -> 108597 | D20: =D22+D28 -> 115903 | E20: =E22+E28 -> 123509 | F20: =F22+F28 -> 119013 | G20: =G22+G28 -> 114506 | H20: =H22+H28 -> 114017 | I20: =I22+I28 -> 116147 | J20: =J22+J28 -> 125172 | ... O20: =O22+O28 -> 225173
B22: Current Liabilities | C22: =C23+C24+C25+C26 -> 68854 | D22: =D23+D24+D25+D26 -> 77709 | E22: =E23+E24+E25+E26 -> 86295 | F22: =F23+F24+F25+F26 -> 81814 | G22: =G23+G24+G25+G26 -> 76997 | H22: =H23+H24+H25+H26 -> 77913 | I22: =I23+I24+I25+I26 -> 80803 | J22: =J23+J24+J25+J26 -> 89122 | ... O22: =O23+O24+O25+O26 -> 111188
B23: Accounts Payable | C23: 4184 | D23: 5313 | E23: 5803 | F23: =BS!K24 -> 7493 | G23: 6198 | H23: 6092 | I23: 7049 | J23: =BS!P24 -> 7987 | K23: 8497 | L23: 8347 | M23: 10546 | N23: =BS!U24 -> 12200 | O23: 16852
B24: Salary | C24: 9954 | D24: 11260 | E24: 12562 | F24: =BS!K25 -> 15140 | G24: 9703 | H24: 11373 | I24: 12908 | J24: =BS!P25 -> 15069 | K24: 9984 | L24: 12168 | M24: 13944 | N24: =BS!U25 -> 17546 | O24: 13947
B25: Accrued Revenue Share | C25: 7816 | D25: 7990 | E25: 8025 | F25: =BS!K26 -> 8876 | G25: 8520 | H25: 8899 | I25: 9365 | J25: =BS!P26 -> 9802 | K25: 9965 | L25: 9787 | M25: 10081 | N25: =BS!U26 -> 10864 | O25: 10208
B26: Other Current Liabilities | C26: 46900 | D26: 53146 | E26: 59905 | F26: =BS!K27 -> 50305 | G26: 52576 | H26: 51549 | I26: 51481 | J26: =BS!P27 -> 56264 | K26: 63208 | L26: 57008 | M26: 64979 | N26: =BS!U27 -> 62135 | O26: 70181
B28: Non Current Liabilities | C28: =C29+C30+C31+C32 -> 39743 | D28: =D29+D30+D31+D32 -> 38194 | E28: =E29+E30+E31+E32 -> 37214 | F28: =F29+F30+F31+F32 -> 37199 | G28: =G29+G30+G31+G32 -> 37509 | H28: =H29+H30+H31+H32 -> 36104 | I28: =I29+I30+I31+I32 -> 35344 | J28: =J29+J30+J31+J32 -> 36050 | ... O28: =O29+O30+O31+O32 -> 113985
B29: Long term Debt | C29: 13697 | D29: 13705 | E29: 13781 | F29: =BS!K30 -> 13253 | G29: 13228 | H29: 13238 | I29: 12297 | J29: =BS!P30 -> 10883 | K29: 10886 | L29: 23607 | M29: 21607 | N29: =BS!U30 -> 46547 | O29: 77501
B30: Lease | C30: 12799 | D30: 12746 | E30: 12550 | F30: =BS!K31 -> 12460 | G30: 11957 | H30: 11708 | I30: 11654 | J30: =BS!P31 -> 11691 | K30: 11678 | L30: 11952 | M30: 12106 | N30: =BS!U31 -> 12744 | O30: 12983
B31: Taxes | C31: 9722 | D31: 8753 | E31: 8038 | F31: =BS!K32 -> 8474 | G31: 9234 | H31: 7703 | I31: 8219 | J31: =BS!P32 -> 8782 | K31: 9773 | L31: 10027 | M31: 10072 | N31: =BS!U32 -> 9531 | O31: 12457
B32: Other Non Current Liabilities | C32: 3525 | D32: 2990 | E32: 2845 | F32: =BS!K33 -> 3012 | G32: 3090 | H32: 3455 | I32: 3174 | J32: =BS!P33 -> 4694 | K32: 6116 | L32: 6241 | M32: 6267 | N32: =BS!U33 -> 8449 | O32: 11044
B34: Equity | C34: =C35+C36 -> 260894 | D34: =D35+D36 -> 267141 | E34: =E35+E36 -> 273202 | F34: =F35+F36 -> 283379 | G34: =G35+G36 -> 292844 | H34: =H35+H36 -> 300753 | I34: =I35+I36 -> 314119 | J34: =J35+J36 -> 325084 | ... O34: =O35+O36 -> 478746
B35: Share Capital | C35: 70269 | D35: 72248 | E35: 74591 | F35: =BS!K36 -> 76534 | G35: 77913 | H35: 79732 | I35: 82030 | J35: =BS!P36 -> 84800 | K35: 86725 | L35: 89283 | M35: 91695 | N35: =BS!U36 -> 93126 | O35: 96902
B36: Income Reserves | C36: 190625 | D36: 194893 | E36: 198611 | F36: =BS!K37 -> 206845 | G36: 214931 | H36: 221021 | I36: 232089 | J36: =BS!P37 -> 240284 | K36: 258542 | L36: 273633 | M36: 295172 | N36: =BS!U37 -> 322139 | O36: 381844
B38: Liabilities + Equity | C38: =C20+C34 -> 369491 | D38: =D20+D34 -> 383044 | E38: =E20+E34 -> 396711 | F38: =F20+F34 -> 402392 | G38: =G20+G34 -> 407350 | H38: =H20+H34 -> 414770 | I38: =I20+I34 -> 430266 | J38: =J20+J34 -> 450256 | ... O38: =O20+O34 -> 703919
B40: OWC | C40: =C10+C11-C23-C24-C25-C26 -> -21971 | D40: =D10+D11-D23-D24-D25-D26 -> -27253 | E40: =E10+E11-E23-E24-E25-E26 -> -29920 | F40: =F10+F11-F23-F24-F25-F26 -> -21200 | G40: =G10+G11-G23-G24-G25-G26 -> -19616 | H40: =H10+H11-H23-H24-H25-H26 -> -16643 | I40: =I10+I11-I23-I24-I25-I26 -> -16492 | J40: =J10+J11-J23-J24-J25-J26 -> -21068 | ... O40: =O10+O11-O23-O24-O25-O26 -> -24275
B41: Δ OWC | C41: =C40-BS!F42 -> -3704 | D41: =D40-C40 -> -5282 | E41: =E40-D40 -> -2667 | F41: =F40-E40 -> 8720 | G41: =G40-F40 -> 1584 | H41: =H40-G40 -> 2973 | I41: =I40-H40 -> 151 | J41: =J40-I40 -> -4576 | K41: =K40-J40 -> -3862 | ... O41: =O40-N40 -> -725

Sheet Q - CFS Historical
B1: Cash Flow Statement (Historical / Reported) — Quarterly (Mn USD)
C2: 2023 | H2: 2024 | M2: 2025 | R2: 2026
C3: Q1 | D3: Q2 | E3: Q3 | F3: Q4 | G3: FY | H3: Q1 | I3: Q2 | J3: Q3 | K3: Q4 | L3: FY | M3: Q1 | N3: Q2 | O3: Q3 | P3: Q4 | Q3: FY | R3: Q1
B5: Operating Activities
B6: Net Income | C6: 15051 | D6: 18368 | E6: 19689 | F6: 20687 | G6: =SUM(C6:F6) -> 73795 | H6: 23662 | I6: 23619 | J6: 26301 | K6: 26536 | L6: =SUM(H6:K6) -> 100118 | M6: 34540 | N6: 28196 | O6: 34979 | P6: 34455 | Q6: =SUM(M6:P6) -> 132170 | R6: 62578
B7: Adjustments: | C7: =SUM(C8:C12) -> 7085 | D7: =SUM(D8:D12) -> 7362 | E7: =SUM(E8:E12) -> 8850 | F7: =SUM(F8:F12) -> 8499 | G7: =SUM(C7:F7) -> 31796 | H7: =SUM(H8:H12) -> 7649 | I7: =SUM(I8:I12) -> 8291 | J7: =SUM(J8:J12) -> 8186 | K7: =SUM(K8:K12) -> 9461 | L7: =SUM(H7:K7) -> 33587 | M7: =SUM(M8:M12) -> -628 | N7: =SUM(N8:N12) -> 9661 | O7: =SUM(O8:O12) -> 9652 | P7: =SUM(P8:P12) -> 13240 | Q7: =SUM(M7:P7) -> 31925 | R7: =SUM(R8:R12) -> -15386
B8: Depreciation & Amortization | C8: 3186 | D8: 3397 | E8: 3800 | F8: 1563 | G8: =SUM(C8:F8) -> 11946 | H8: 3413 | I8: 3708 | J8: 3985 | K8: 4205 | L8: =SUM(H8:K8) -> 15311 | M8: 4487 | N8: 4998 | O8: 5611 | P8: 6040 | Q8: =SUM(M8:P8) -> 21136 | R8: 6482
B9: Stock-based compensation | C9: 5284 | D9: 5774 | E9: 5743 | F9: 5659 | G9: =SUM(C9:F9) -> 22460 | H9: 5264 | I9: 5865 | J9: 5846 | K9: 5810 | L9: =SUM(H9:K9) -> 22785 | M9: 5516 | N9: 5998 | O9: 6368 | P9: 7071 | Q9: =SUM(M9:P9) -> 24953 | R9: 6751
B10: Deferred income taxes | C10: -1854 | D10: -2415 | E10: -1824 | F10: -1670 | G10: =SUM(C10:F10) -> -7763 | H10: 419 | I10: -3157 | J10: -1071 | K10: -1448 | L10: =SUM(H10:K10) -> -5257 | M10: -1152 | N10: -444 | O10: 8726 | P10: 1218 | Q10: =SUM(M10:P10) -> 8348 | R10: 6920
B11: Loss (gain) on securities | C11: -84 | D11: 509 | E11: 869 | F11: -471 | G11: =SUM(C11:F11) -> 823 | H11: -1781 | I11: 1024 | J11: -1981 | K11: 67 | L11: =SUM(H11:K11) -> -2671 | M11: -9960 | N11: -1451 | O11: -10855 | P11: -2354 | Q11: =SUM(M11:P11) -> -24620 | R11: -36804
